Workbook

Sheet Summary Menu
A1: Summary Menu
A2: Menu | B2: COGS | C2: Selling Price | D2: =IFERROR(B2/C2,0) -> 0 | E2: Status | F2: Description
A3: Yakitori Stall | B3: =IFERROR(AVERAGE(B4:B9),0) -> 8334.496 | C3: =IFERROR(AVERAGE(C4:C9),0) -> 21666.667 | D3: =IFERROR(B3/C3,0) -> 0.38466905
A4: Negima | B4: ='Yakitori Stall'!E15 -> 8712.2285 | C4: ='Yakitori Stall'!E18 -> 20000 | D4: =IFERROR(B4/C4,0) -> 0.43561142 | E4: Recipe Available | F4: Chicken thigh with leek and soy tare
A5: Tsukune | B5: ='Yakitori Stall'!E33 -> 10772.127 | C5: ='Yakitori Stall'!E36 -> 25000 | D5: =IFERROR(B5/C5,0) -> 0.43088507 | E5: Recipe Available | F5: chicken meat ball served with soy tare
A6: Torikawa | B6: ='Yakitori Stall'!E51 -> 5733.7285 | C6: ='Yakitori Stall'!E54 -> 15000 | D6: =IFERROR(B6/C6,0) -> 0.38224857 | E6: Recipe Available | F6: Crispy Chicken skin with salt
A7: Tebasaki | B7: ='Yakitori Stall'!E69 -> 7362.8952 | C7: ='Yakitori Stall'!E72 -> 20000 | D7: =IFERROR(B7/C7,0) -> 0.36814476 | E7: Recipe Available | F7: Chicken wings
A8: Beef Enoki Roll | B8: ='Yakitori Stall'!E87 -> 8666.2285 | C8: ='Yakitori Stall'!E90 -> 25000 | D8: =IFERROR(B8/C8,0) -> 0.34664914 | E8: Recipe Available | F8: Enoki mushroom wrapped with USDA shortplate beef
A9: Beef Mochi | B9: ='Yakitori Stall'!E105 -> 8759.7686 | C9: ='Yakitori Stall'!E108 -> 25000 | D9: =IFERROR(B9/C9,0) -> 0.35039075 | E9: Recipe Available | F9: Chewy mochi wrapped with USDA shortplate beef
A11: Teppanyaki Stall | B11: =IFERROR(AVERAGE(B12:B16),0) -> 7552.4294 | C11: =IFERROR(AVERAGE(C12:C16),0) -> 61000 | D11: =IFERROR(B11/C11,0) -> 0.12381032
A12: Takoyaki | B12: ='Teppanyaki Stall '!E18 -> 16487.147 | C12: ='Teppanyaki Stall '!E21 -> 60000 | D12: =IFERROR(B12/C12,0) -> 0.27478579 | E12: Recipe Pending | F12: Classic takoyaki with condiment
A13: Yasai Itame | B13: ='Teppanyaki Stall '!E36 -> 0 | C13: ='Teppanyaki Stall '!E39 -> 65000 | D13: =IFERROR(B13/C13,0) -> 0 | E13: Recipe Pending | F13: Stir-fry mix vegetables with usda beef topping with katsuobushi
A14: Ika Sugatayaki | B14: ='Teppanyaki Stall '!E54 -> 21275 | C14: ='Teppanyaki Stall '!E57 -> 55000 | D14: =IFERROR(B14/C14,0) -> 0.38681818 | E14: Recipe Pending | F14: grilled fresh squid served with shoyu tare
A15: Ika Okonomiyaki | B15: ='Teppanyaki Stall '!E72 -> 0 | C15: ='Teppanyaki Stall '!E75 -> 60000 | D15: =IFERROR(B15/C15,0) -> 0 | E15: Recipe Pending | F15: Osaka style okonomiyaki served with grilled squid
A16: Beef Okonomiyaki | B16: ='Teppanyaki Stall '!E90 -> 0 | C16: ='Teppanyaki Stall '!E93 -> 65000 | D16: =IFERROR(B16/C16,0) -> 0 | E16: Recipe Pending | F16: Osaka style okonomiyaki served with grilled beef
A18: Dumpling Stall | B18: =IFERROR(AVERAGE(B19:B23),0) -> 9895.1602 | C18: =IFERROR(AVERAGE(C19:C23),0) -> 31000 | D18: =IFERROR(B18/C18,0) -> 0.31919872
A19: Okonomiyaki Gyoza | B19: ='Dumpling Stall'!E15 -> 12606.184 | C19: ='Dumpling Stall'!E18 -> 35000 | D19: =IFERROR(B19/C19,0) -> 0.3601767 | E19: Recipe Available | F19: seared japanese dumpling,crispy tuille,okonomiyaki sauce and katsuobushi
A20: Slider Gyoza Mentai | B20: ='Dumpling Stall'!E33 -> 11933.94 | C20: ='Dumpling Stall'!E36 -> 35000 | D20: =IFERROR(B20/C20,0) -> 0.34096971 | E20: Recipe Available | F20: Deep fried japanese dumpling served creamy mentaiko sauce
A21: Spicy Tteokboki Gyoza | B21: ='Dumpling Stall'!E51 -> 17929.966 | C21: ='Dumpling Stall'!E54 -> 35000 | D21: =IFERROR(B21/C21,0) -> 0.51228475 | E21: Recipe Available | F21: steam gyoza served with spicy and creamy miso tteokboki
A22: Yaki Gyoza | B22: ='Dumpling Stall'!E69 -> 3439.765 | C22: ='Dumpling Stall'!E72 -> 25000 | D22: =IFERROR(B22/C22,0) -> 0.1375906 | E22: Recipe Pending | F22: Pan seared Japanese chicken dumpling
A23: Age Gyoza | B23: ='Dumpling Stall'!E87 -> 3565.9456 | C23: ='Dumpling Stall'!E90 -> 25000 | D23: =IFERROR(B23/C23,0) -> 0.14263782 | E23: Recipe Pending | F23: Deep fried japanese chicken dumpling
A25: Sushi - Sashimi Stall | B25: =IFERROR(AVERAGE(B26:B39),0) -> 56386.936 | C25: =IFERROR(AVERAGE(C26:C39),0) -> 78333.333 | D25: =IFERROR(B25/C25,0) -> 0.71983322
A26: Tamagoyaki Mentai | B26: ='Sushi - Sashimi Stall'!E15 -> 8605.9571 | C26: ='Sushi - Sashimi Stall'!E18 | D26: =IFERROR(B26/C26,0) -> 0 | E26: Recipe Pending | F26: Sweet Japanese omelette egg served with creamy mentai mayo
A27: Tuna Wasabi Mayo Taco | B27: ='Sushi - Sashimi Stall'!E33 -> 11582.417 | C27: ='Sushi - Sashimi Stall'!E36 | D27: =IFERROR(B27/C27,0) -> 0 | E27: Recipe Pending | F27: cube fresh tuna mixwd with creamy wasabi mayo and wrapped with crispy nori
A28: Unagi Nigiri | B28: ='Sushi - Sashimi Stall'!E51 -> 48519.545 | C28: 65000 | D28: =IFERROR(B28/C28,0) -> 0.74645455 | E28: Recipe Pending | F28: Sushi rice on top grilled uangi
A29: Chuka Idako Gunkan | B29: ='Sushi - Sashimi Stall'!E69 -> 0 | C29: ='Sushi - Sashimi Stall'!E72 | D29: =IFERROR(B29/C29,0) -> 0 | E29: Recipe Pending | F29: Seasoned baby octopus sushi
A30: Chuka Idako Tsumami | B30: ='Sushi - Sashimi Stall'!E87 -> 0 | C30: ='Sushi - Sashimi Stall'!E90 | D30: =IFERROR(B30/C30,0) -> 0 | E30: Recipe Pending | F30: Seasoned baby octopus salad
A31: Unagi Sushi Roll | B31: ='Sushi - Sashimi Stall'!E105 -> 215487.52 | C31: 80000 | D31: =IFERROR(B31/C31,0) -> 2.693594 | E31: Recipe Pending | F31: Sushi roll with avocado,cucumber and crispy on top with grilled unagi
A32: Crispy Salmon Roll | B32: ='Sushi - Sashimi Stall'!E123 -> 0 | C32: 80000 | D32: =IFERROR(B32/C32,0) -> 0 | E32: Recipe Pending | F32: Sushi roll inside crabstick,avocado and crispy on top aburi salmon
A33: Salmon Cured Yuzu | B33: ='Sushi - Sashimi Stall'!E141 -> 0 | C33: ='Sushi - Sashimi Stall'!E144 | D33: =IFERROR(B33/C33,0) -> 0 | E33: Recipe Pending | F33: Salmon Cured served with yuzu dressing
A34: Tuna Cured Yuzu | B34: ='Sushi - Sashimi Stall'!E159 -> 0 | C34: ='Sushi - Sashimi Stall'!E162 | D34: =IFERROR(B34/C34,0) -> 0 | E34: Recipe Pending | F34: Tuna cured served with yuzu dressing
A35: Maguro Maki | B35: ='Sushi - Sashimi Stall'!E177 -> 0 | C35: ='Sushi - Sashimi Stall'!E180 | D35: =IFERROR(B35/C35,0) -> 0 | E35: Recipe Pending | F35: small roll sushi with tuna
A36: Salmon Maki | B36: ='Sushi - Sashimi Stall'!E195 -> 0 | C36: 85000 | D36: =IFERROR(B36/C36,0) -> 0 | E36: Recipe Pending | F36: small roll sushi with salmon
A37: Salmon Philadelpia | B37: ='Sushi - Sashimi Stall'!E213 -> 168193.77 | C37: 85000 | D37: =IFERROR(B37/C37,0) -> 1.9787503 | E37: Recipe Pending | F37: sushi roll wrapped with salmon and inside cream cheese and cucumber
A38: Crispy Temaki Sushi | B38: ='Sushi - Sashimi Stall'!E231 -> 168834.11 | C38: ='Sushi - Sashimi Stall'!E234 | D38: =IFERROR(B38/C38,0) -> 0 | E38: Recipe Pending | F38: crispy corn sushi with spicy tuna mayo and cucumber
A39: California Roll | B39: ='Sushi - Sashimi Stall'!E249 -> 168193.77 | C39: 75000 | D39: =IFERROR(B39/C39,0) -> 2.2425836 | E39: Recipe Pending | F39: avocado,cucumber,crab stick and tobiko served with creamy mayonaise
A41: Bakery Stall | B41: =IFERROR(AVERAGE(B42:B54),0) -> 5328.0886 | C41: =IFERROR(AVERAGE(C42:C54),0) -> 17222.222 | D41: =IFERROR(B41/C41,0) -> 0.30937289
A42: Doughnut Matcha | B42: ='Bakery Stall'!E15 -> 3044.9101 | C42: ='Bakery Stall'!E18 -> 15000 | D42: =IFERROR(B42/C42,0) -> 0.20299401 | E42: Assembly Qty Pending | F42: glazed with matcha cream and garnish
A43: Doughnut Hojicha | B43: ='Bakery Stall'!E33 -> 3134.7598 | C43: ='Bakery Stall'!E36 -> 15000 | D43: =IFERROR(B43/C43,0) -> 0.20898399 | E43: Assembly Qty Pending | F43: glazed with matcha cream and garnish
A44: Shuffle Pancake Mochi Chocolate | B44: ='Bakery Stall'!E51 -> 6205.7488 | C44: ='Bakery Stall'!E54 | D44: =IFERROR(B44/C44,0) -> 0 | E44: Assembly Qty Pending | F44: Mochi blanket with chocolate sauce
A45: Shuffle Pancake Mochi Matcha | B45: ='Bakery Stall'!E69 -> 6875.4611 | C45: ='Bakery Stall'!E72 | D45: =IFERROR(B45/C45,0) -> 0 | E45: Assembly Qty Pending | F45: Mochi blanket with matcha sauce
A46: Shuffle Pancake Mochi Hojicha | B46: ='Bakery Stall'!E87 -> 7125.0304 | C46: ='Bakery Stall'!E90 | D46: =IFERROR(B46/C46,0) -> 0 | E46: Assembly Qty Pending | F46: Mochi blanket with hojicha sauce
A47: Shuffle Pancake Mochi Vanilla | B47: ='Bakery Stall'!E105 -> 5486.4871 | C47: ='Bakery Stall'!E108 | D47: =IFERROR(B47/C47,0) -> 0 | E47: Assembly Qty Pending | F47: Mochi blanket with vanilla sauce
A48: Bomboloni Mochi Chocolate | B48: ='Bakery Stall'!E123 -> 6484.0745 | C48: ='Bakery Stall'!E126 -> 20000 | D48: =IFERROR(B48/C48,0) -> 0.32420373 | E48: Assembly Qty Pending | F48: Bomboloni mochi with Chocolate Filling WIP
A49: Bomboloni Mochi Matcha | B49: ='Bakery Stall'!E141 -> 5120.6695 | C49: ='Bakery Stall'!E144 -> 20000 | D49: =IFERROR(B49/C49,0) -> 0.25603348 | E49: Assembly Qty Pending | F49: Bomboloni mochi with Matcha Filling WIP
A50: Bomboloni Mochi Hojicha | B50: ='Bakery Stall'!E159 -> 5243.1919 | C50: ='Bakery Stall'!E162 -> 20000 | D50: =IFERROR(B50/C50,0) -> 0.26215959 | E50: Assembly Qty Pending | F50: Bomboloni mochi with Hojicha Filling WIP
A51: Bomboloni Mochi Strawberry | B51: ='Bakery Stall'!E177 -> 5822.4313 | C51: ='Bakery Stall'!E180 -> 20000 | D51: =IFERROR(B51/C51,0) -> 0.29112156 | E51: Assembly Qty Pending | F51: Bomboloni mochi with Strawberry Jam WIP
A52: Shio Pan OG | B52: ='Bakery Stall'!E195 -> 2851.2586 | C52: ='Bakery Stall'!E198 -> 15000 | D52: =IFERROR(B52/C52,0) -> 0.1900839 | E52: Assembly Qty Pending | F52: Plan and original salt bread
A53: Shio Pan Cheese Furikake | B53: ='Bakery Stall'!E213 -> 7731.6904 | C53: ='Bakery Stall'!E216 -> 15000 | D53: =IFERROR(B53/C53,0) -> 0.51544603 | E53: Assembly Qty Pending | F53: Topping with cheese furikake
A54: Egg Tartar Shio Pan | B54: ='Bakery Stall'!E231 -> 4139.4386 | C54: ='Bakery Stall'!E234 -> 15000 | D54: =IFERROR(B54/C54,0) -> 0.27596257 | E54: Assembly Qty Pending | F54: Topping with creamy savory egg tartar
D55: =IFERROR(B55/C55,0) -> 0
A56: Burger - sandwiches Stall | B56: =IFERROR(AVERAGE(B57:B63),0) -> 57962.491 | C56: =IFERROR(AVERAGE(C57:C63),0) -> 53333.333 | D56: =IFERROR(B56/C56,0) -> 1.0867967
A57: Gyuniku Burger | B57: ='Burger - sandwiches Stall'!E15 -> 344894.27 | C57: ='Burger - sandwiches Stall'!E18 | D57: =IFERROR(B57/C57,0) -> 0 | E57: Recipe Pending | F57: Beef sukiyaki, pickles, garlic tartar and lettuce
A58: Chicken Namban Burger | B58: ='Burger - sandwiches Stall'!E33 -> 9706.5427 | C58: ='Burger - sandwiches Stall'!E36 | D58: =IFERROR(B58/C58,0) -> 0 | E58: Recipe Pending | F58: classic burger with juice chicken namban and creamy tartar
A59: Tempura Kimchi Hotdog | B59: ='Burger - sandwiches Stall'!E51 -> 6774.5211 | C59: ='Burger - sandwiches Stall'!E54 | D59: =IFERROR(B59/C59,0) -> 0 | E59: Recipe Pending | F59: Crispy tempura and spicy refreshing from kimchi on soft bread
A60: Large Sausage Hotdog | B60: ='Burger - sandwiches Stall'!E69 -> 19937.546 | C60: ='Burger - sandwiches Stall'!F69 | D60: =IFERROR(B60/C60,0) -> 0 | E60: Recipe Pending | F60: Smoked chicken sausage with and mentai mayo
A61: Large Sausage Hotdog | B61: ='Burger - sandwiches Stall'!E87 -> 0 | C61: ='Burger - sandwiches Stall'!E90 -> 55000 | D61: =IFERROR(B61/C61,0) -> 0 | E61: Recipe Pending | F61: Smoked beef sausage with and mentai mayo
A62: Yakiniku Hotdog | B62: ='Burger - sandwiches Stall'!E105 -> 3490.6646 | C62: ='Burger - sandwiches Stall'!E108 -> 50000 | D62: =IFERROR(B62/C62,0) -> 0.069813293 | E62: Recipe Pending | F62: Sweet and umami USDA beef, pickles and condiment
A63: Ebi Shinjo Toasted | B63: ='Burger - sandwiches Stall'!E123 -> 20933.894 | C63: ='Burger - sandwiches Stall'!E126 -> 55000 | D63: =IFERROR(B63/C63,0) -> 0.38061625 | E63: Recipe Pending | F63: Fried Shrimp cake sandwich with sesame and egg tartar mayo
D64: =IFERROR(B64/C64,0) -> 0
D65: =IFERROR(B65/C65,0) -> 0
A66: Agemono - Frying Section Stall | B66: =IFERROR(AVERAGE(B67:B74),0) -> 12193.328 | C66: =IFERROR(AVERAGE(C67:C74),0) -> 40714.286 | D66: =IFERROR(B66/C66,0) -> 0.29948524
A67: Chicken Namban | B67: ='Agemono - Frying Section Stall'!E15 -> 10771.575 | C67: ='Agemono - Frying Section Stall'!E18 -> 40000 | D67: =IFERROR(B67/C67,0) -> 0.26928937 | E67: Recipe Available | F67: Japanese fried chicken coating soy vinegar and egg tartar
A68: Signature Torikaraage | B68: ='Agemono - Frying Section Stall'!E33 -> 8770.8879 | C68: ='Agemono - Frying Section Stall'!E36 -> 40000 | D68: =IFERROR(B68/C68,0) -> 0.2192722 | E68: Recipe Available | F68: Japanese fried chicken served with cheese sauce or BBQ sauce
A69: Cheese Minched Katsu | B69: ='Agemono - Frying Section Stall'!E51 -> 23558.677 | C69: ='Agemono - Frying Section Stall'!E54 -> 50000 | D69: =IFERROR(B69/C69,0) -> 0.47117355 | E69: Recipe Available | F69: Umami and cheesy minched beef katsu served with signature sauce
A70: Ebi Furai Signature | B70: ='Agemono - Frying Section Stall'!E69 -> 30894.87 | C70: ='Agemono - Frying Section Stall'!E72 -> 60000 | D70: =IFERROR(B70/C70,0) -> 0.51491449 | E70: Recipe Available | F70: Coating prawn with bread crumb served with cheese sauce
A71: Tomorokoshi Ribs | B71: ='Agemono - Frying Section Stall'!E87 -> 3464.9345 | C71: ='Agemono - Frying Section Stall'!E90 -> 25000 | D71: =IFERROR(B71/C71,0) -> 0.13859738 | E71: Recipe Available | F71: triple cook corn ribs mixed with signature spice
A72: SFC Signature | B72: ='Agemono - Frying Section Stall'!E105 -> 11463.744 | C72: ='Agemono - Frying Section Stall'!E108 -> 35000 | D72: =IFERROR(B72/C72,0) -> 0.32753555 | E72: Recipe Available | F72: Prologue fried chicken
A73: Crispy Wings | B73: ='Agemono - Frying Section Stall'!E123 -> 8621.932 | C73: ='Agemono - Frying Section Stall'!E126 -> 35000 | D73: =IFERROR(B73/C73,0) -> 0.24634091 | E73: Recipe Available | F73: Fried Chicken wings coating with special sauce
A74: Tendon Club | B74: ='Agemono - Frying Section Stall'!E141 -> 0 | C74: ='Agemono - Frying Section Stall'!E144 | D74: =IFERROR(B74/C74,0) -> 0 | E74: Recipe Available | F74: Rice bowl tempura coating with tendon sauce
B75: ='Rice bowl Stall'!E33 -> 14647.844 | C75: ='Rice bowl Stall'!F33 | D75: =IFERROR(B75/C75,0) -> 0
A76: Rice bowl Stall | B76: =IFERROR(AVERAGE(B77:B79),0) -> 22452.511 | C76: =IFERROR(AVERAGE(C77:C79),0) -> 75000 | D76: =IFERROR(B76/C76,0) -> 0.29936681
A77: Gyutan Donburi | B77: ='Rice bowl Stall'!E15 -> 14647.844 | C77: ='Rice bowl Stall'!E18 -> 75000 | D77: =IFERROR(B77/C77,0) -> 0.19530459 | E77: Recipe Available | F77: Ricebowl with grilled beef tongue
A78: Beef Yakiniku Bowl | B78: ='Rice bowl Stall'!E33 -> 14647.844 | C78: ='Rice bowl Stall'!E36 -> 70000 | D78: =IFERROR(B78/C78,0) -> 0.20925492 | E78: Recipe Available | F78: Rice bowl USDA beef with yakiniku sauce
A79: Smoked Duck Donburi | B79: ='Rice bowl Stall'!E51 -> 38061.844 | C79: ='Rice bowl Stall'!E54 -> 80000 | D79: =IFERROR(B79/C79,0) -> 0.47577305 | E79: Recipe Available | F79: Smocked duck rice bowl served with black sauce and condiment
D80: =IFERROR(B80/C80,0) -> 0
A81: Ramen - Noodles Stall | B81: =IFERROR(AVERAGE(B82:B87),0) -> 30771.866 | C81: =IFERROR(AVERAGE(C82:C87),0) -> 0 | D81: =IFERROR(B81/C81,0) -> 0
A82: Aka Miso Ramen | B82: ='Ramen - Noodles Stall'!E17 -> 54600.392 | C82: ='Ramen - Noodles Stall'!E20 | D82: =IFERROR(B82/C82,0) -> 0 | E82: Recipe Available | F82: served with kind of condiment, chicken and smoked duck, spicy miso broth
A83: Spicy Goma Ramen | B83: ='Ramen - Noodles Stall'!E38 -> 20207.981 | C83: ='Ramen - Noodles Stall'!F38 | D83: =IFERROR(B83/C83,0) -> 0 | E83: Recipe Available | F83: chicken broth with sesame, smoked duck, pokcoy and katsuobushi chili oil
A84: Signature Shoyu Ramen | B84: ='Ramen - Noodles Stall'!E58 -> 8002.9156 | C84: ='Ramen - Noodles Stall'!E61 | D84: =IFERROR(B84/C84,0) -> 0 | E84: Recipe Available | F84: served with shio tare,beef and vegetables
A85: Beef Abura Soba | B85: ='Ramen - Noodles Stall'!E82 -> 19927.031 | C85: ='Ramen - Noodles Stall'!E85 | D85: =IFERROR(B85/C85,0) -> 0 | E85: Recipe Available | F85: Dry ramen,Smoked Beef, kimchi, soy butter and truffle oil
A86: Smoked Duck Abura Soba | B86: ='Ramen - Noodles Stall'!E106 -> 25602.281 | C86: ='Ramen - Noodles Stall'!E109 | D86: =IFERROR(B86/C86,0) -> 0 | E86: Recipe Available | F86: Dry ramen,Smocked Duck, kimchi, soy butter and truffle oil
A87: Tori Abura Soba | B87: ='Ramen - Noodles Stall'!E130 -> 56290.597 | C87: ='Ramen - Noodles Stall'!E133 | D87: =IFERROR(B87/C87,0) -> 0 | E87: Recipe Available | F87: Dry ramen,Chicken Karaage, kimchi, soy butter and truffle oil
B88: ='Udon - Noodles Stall'!E33 -> 0 | C88: ='Udon - Noodles Stall'!F33 | D88: =IFERROR(B88/C88,0) -> 0
A89: Udon - Noodles Stall | B89: =IFERROR(AVERAGE(B90:B92),0) -> 27213.6 | C89: =IFERROR(AVERAGE(C90:C92),0) -> 0 | D89: =IFERROR(B89/C89,0) -> 0
A90: Udon Carbonara | B90: ='Udon - Noodles Stall'!E15 -> 81640.8 | C90: ='Udon - Noodles Stall'!E18 | D90: =IFERROR(B90/C90,0) -> 0 | E90: Recipe Available | F90: Creamy and chewy udon noodles served with smoked beef, cheese and eggyolk
A91: Gyutan Udon | B91: ='Udon - Noodles Stall'!E33 -> 0 | C91: ='Udon - Noodles Stall'!E36 | D91: =IFERROR(B91/C91,0) -> 0 | E91: Recipe Pending | F91: Dashi broth,Beef Tongue, and seaweed
A92: Beefu Udon | B92: ='Udon - Noodles Stall'!E51 -> 0 | C92: ='Udon - Noodles Stall'!E54 | D92: =IFERROR(B92/C92,0) -> 0 | E92: Recipe Pending | F92: Dashi broth, shortplate beef, and seaweed
B93: ='Japanese Poridge Stall'!E33 -> 0 | C93: ='Japanese Poridge Stall'!F33 | D93: =IFERROR(B93/C93,0) -> 0
A94: Japanese Poridge Stall | B94: =IFERROR(AVERAGE(B95:B97),0) -> 0 | C94: =IFERROR(AVERAGE(C95:C97),0) -> 0 | D94: =IFERROR(B94/C94,0) -> 0
A95: Okayu Beef | B95: ='Japanese Poridge Stall'!E15 -> 0 | C95: ='Japanese Poridge Stall'!E18 | D95: =IFERROR(B95/C95,0) -> 0 | E95: Recipe Pending | F95: Japanese Umami Poridge served with beef and condiment
A96: Smoked Duck Okayu | B96: ='Japanese Poridge Stall'!E33 -> 0 | C96: ='Japanese Poridge Stall'!E36 | D96: =IFERROR(B96/C96,0) -> 0 | E96: Recipe Pending | F96: Japanese Umami Poridge served with Smocked duck and condiment
A97: Tori Okayu | B97: ='Japanese Poridge Stall'!E51 -> 0 | C97: ='Japanese Poridge Stall'!E54 | D97: =IFERROR(B97/C97,0) -> 0 | E97: Recipe Pending | F97: Japanese Umami Poridge served with Chicken and condiment
D98: 0
A99: Yakimono - Griiled Stall | B99: =IFERROR(AVERAGE(B100:B103),0) -> 0 | C99: =IFERROR(AVERAGE(C100:C103),0) -> 0 | D99: =IFERROR(B99/C99,0) -> 0
A100: Beefu Hikiniku | B100: ='Yakimono - Griiled Stall'!E15 -> 0 | C100: ='Yakimono - Griiled Stall'!E18 | D100: =IFERROR(B100/C100,0) -> 0 | E100: Recipe Pending | F100: Wagyu Beef patty served with furikake rice and miso soup
A101: Salmon Don | B101: ='Yakimono - Griiled Stall'!E33 -> 0 | C101: ='Yakimono - Griiled Stall'!E36 | D101: =IFERROR(B101/C101,0) -> 0 | E101: Recipe Pending | F101: grilled Salmon with teriyaki sauce served with rice and miso soup
A102: Unagimeshi | B102: ='Yakimono - Griiled Stall'!E54 | C102: ='Yakimono - Griiled Stall'!E57 -> Value /pcs | D102: =IFERROR(B102/C102,0) -> 0 | E102: Recipe Pending | F102: grill eel with soy tare sauce served with japanese fried riceand miso soup
A103: Gyudon | B103: ='Yakimono - Griiled Stall'!E72 | C103: ='Yakimono - Griiled Stall'!E75 | D103: =IFERROR(B103/C103,0) -> 0 | E103: Recipe Pending | F103: Grilled Beef with umami rice and onsen egg
B104: ='Onigiri Corner Stall'!E33 -> 0 | C104: ='Onigiri Corner Stall'!F33 | D104: =IFERROR(B104/C104,0) -> 0
...

Sheet Yakitori Stall
A1: Yakitori Stall
A2: Negima
A3: Element | B3: UOM | C3: Element Cost/(g) | D3: Portion Used | E3: Value /pcs | F3: Major Step | G3: Units
A4: Ayam Paha Fillet | B4: GR | C4: =IFERROR(VLOOKUP(A4,'Market List'!$B:$F,5,FALSE),0) -> 40 | D4: 85 | E4: =IFERROR(C4*D4,0) -> 3400 | F4: Prep: Potong 3 @28 gr/pcs. pastikan ayam paha fillet , kulit ayam, batang daun bawang pun sudah terpotong sesuai ukuran
A5: Kulit Ayam | B5: GR | C5: =IFERROR(VLOOKUP(A5,'Market List'!$B:$F,5,FALSE),0) -> 30 | D5: 15 | E5: =IFERROR(C5*D5,0) -> 450 | F5: Prep: Potong 3 @5 gr/pcs; gunakan untuk menutupi setiap ayam. langkah awal,tusuk batang daun bawang setelah itu tusuk kulit ayam 1 sisi dulu, tusuk ayam paha fillet secara melengkung setelah itu lapisi dengan tusuk kulit ayam disisi ujungnya.
A6: Daun Bawang | B6: GR | C6: =IFERROR(VLOOKUP(A6,'Market List'!$B:$F,5,FALSE),0) -> 20 | D6: 12 | E6: =IFERROR(C6*D6,0) -> 240 | F6: Prep: Gunakan batang; potong ukuran 2 ruas jari (3 pcs). lakukan secara terus menerus dengan rasio batang daun bawang, ayam+ayam+batang daun bawang+terakhir ayam lagi.
A7: Yakitori Butter WIP | B7: GR | C7: ='WIP FOOD'!$B$691 -> 76.564551 | D7: 35 | E7: =IFERROR(C7*D7,0) -> 2679.7593 | F7: pastikan arang sudah siap dengan suhu tinggi, tempatkan tusukan negima tepat diatas arang, oleskan yakitori butter di kedua sisi negima, focus dan teliti ketika bakar
A8: Tusuk Sate Yakitori 18cm | B8: PCS | C8: =IFERROR(VLOOKUP(A8,'Market List'!$B:$F,5,FALSE),0) -> 217.92 | D8: 1 | E8: =IFERROR(C8*D8,0) -> 217.92 | F8: dapatkan teksture negima warna dengan golden brown dan sedikit char gosong, untuk olesan yakitori butter nya bisa dilakukan 3-4 kali olesan sekali bakar.
A9: Furikake WIP | B9: GR | C9: ='WIP FOOD'!$B$218 -> 362.72092 | D9: 1 | E9: =IFERROR(C9*D9,0) -> 362.72092
A10: Onion Pickles | B10: GR | C10: =IFERROR(VLOOKUP(A10,'Market List'!$B:$F,5,FALSE),0) -> 91.76 | D10: 2 | E10: =IFERROR(C10*D10,0) -> 183.52
A11: Cucumber Pickles WIP | B11: GR | C11: ='WIP FOOD'!$B$119 -> 13.97688 | D11: 3 | E11: =IFERROR(C11*D11,0) -> 41.930639
A12: Boxes, packaging, etc. | E12: 0
A13: Direct Cost | E13: =SUM(E4:E12) -> 7575.8509 | F13: Source: SULU-bdg FoodTesting.xlsx - ITEM SALES RECIPE
A14: Indirect Cost | E14: =E13*15% -> 1136.3776 | F14: Status: Recipe Available
A15: Cost of Goods Sold (COGS) | E15: =E13+E14 -> 8712.2285
A16: Margin | E16: =IF(E18>0,E18-E15,0) -> 11287.772
A17: Div COGS | E17: =IFERROR(E15/E18,0) -> 0.43561142
A18: Selling Price | E18: 20000
A20: Tsukune
A21: Element | B21: UOM | C21: Element Cost/(g) | D21: Portion Used | E21: Value /pcs | F21: Major Step | G21: Units
A22: Minched Beef WIP | B22: GR | C22: ='WIP FOOD'!$B$372 -> 94.388263 | D22: 60 | E22: =IFERROR(C22*D22,0) -> 5663.2958 | F22: Siapkan Adonan Tsukune, Tusuk menggunakan tusukan yakitori 2 pcs dengan cara tusukan satenya dibuat menyamping kedalam masing masing, kepal kepal tsukune pada tusukan
A23: Yakitori Butter WIP | B23: GR | C23: ='WIP FOOD'!$B$691 -> 76.564551 | D23: 35 | E23: =IFERROR(C23*D23,0) -> 2679.7593 | F23: tempatkan pada tumpuan hibachi,oleskan yakitori butter di kedua sisi,fokus dan teliti ketika bakar hingga golden brown dan sedikit char gosong,
A24: Tusuk Sate Yakitori 18cm | B24: PCS | C24: =IFERROR(VLOOKUP(A24,'Market List'!$B:$F,5,FALSE),0) -> 217.92 | D24: 2 | E24: =IFERROR(C24*D24,0) -> 435.84 | F24: untuk olesan yakitori butter nya bisa dilakukan 3-4 kali olesan sekali bakar, dengan bulak balik tsukune
A25: Furikake WIP | B25: GR | C25: ='WIP FOOD'!$B$218 -> 362.72092 | D25: 1 | E25: =IFERROR(C25*D25,0) -> 362.72092
A26: Onion Pickles | B26: GR | C26: =IFERROR(VLOOKUP(A26,'Market List'!$B:$F,5,FALSE),0) -> 91.76 | D26: 2 | E26: =IFERROR(C26*D26,0) -> 183.52
A27: Cucumber Pickles WIP | B27: GR | C27: ='WIP FOOD'!$B$119 -> 13.97688 | D27: 3 | E27: =IFERROR(C27*D27,0) -> 41.930639
C28: 0 | E28: =IFERROR(C28*D28,0) -> 0
C29: 0 | E29: =IFERROR(C29*D29,0) -> 0
A30: Boxes, packaging, etc. | E30: 0
A31: Direct Cost | E31: =SUM(E22:E30) -> 9367.0666 | F31: Source: SULU-bdg FoodTesting.xlsx - ITEM SALES RECIPE
A32: Indirect Cost | E32: =E31*15% -> 1405.06 | F32: Status: Recipe Available
A33: Cost of Goods Sold (COGS) | E33: =E31+E32 -> 10772.127
A34: Margin | E34: =IF(E36>0,E36-E33,0) -> 14227.873
A35: Div COGS | E35: =IFERROR(E33/E36,0) -> 0.43088507
A36: Selling Price | E36: 25000
A38: Torikawa
A39: Element | B39: UOM | C39: Element Cost/(g) | D39: Portion Used | E39: Value /pcs | F39: Major Step | G39: Units
A40: Kulit Ayam | B40: GR | C40: =IFERROR(VLOOKUP(A40,'Market List'!$B:$F,5,FALSE),0) -> 30 | D40: 50 | E40: =IFERROR(C40*D40,0) -> 1500 | F40: Potong kecil kecil kulit ayam yang sudah direbus,lalu tusukan pada tusuk sate satu persatu hingga ke ujung rapat dan lebar.pastikan arang sudah siap dengan suhu tinggi,tempatkan
A41: Yakitori Butter WIP | B41: GR | C41: ='WIP FOOD'!$B$691 -> 76.564551 | D41: 35 | E41: =IFERROR(C41*D41,0) -> 2679.7593 | F41: tusukan torikawa diatas arang,oleskan yakitori butter di kedua sisi torikawa,fokus dan teliti ketika bakar dapatkan tekstur torikawa dengan golden brown dan sedikit char gosong,
A42: Tusuk Sate Yakitori 18cm | B42: PCS | C42: =IFERROR(VLOOKUP(A42,'Market List'!$B:$F,5,FALSE),0) -> 217.92 | D42: 1 | E42: =IFERROR(C42*D42,0) -> 217.92 | F42: untuk olesan yakitori butter nya bisa dilakukan 3-4 kali olesan sekali bakar.
A43: Furikake WIP | B43: GR | C43: ='WIP FOOD'!$B$218 -> 362.72092 | D43: 1 | E43: =IFERROR(C43*D43,0) -> 362.72092
A44: Onion Pickles | B44: GR | C44: =IFERROR(VLOOKUP(A44,'Market List'!$B:$F,5,FALSE),0) -> 91.76 | D44: 2 | E44: =IFERROR(C44*D44,0) -> 183.52
A45: Cucumber Pickles WIP | B45: GR | C45: ='WIP FOOD'!$B$119 -> 13.97688 | D45: 3 | E45: =IFERROR(C45*D45,0) -> 41.930639
C46: 0 | E46: =IFERROR(C46*D46,0) -> 0
C47: 0 | E47: =IFERROR(C47*D47,0) -> 0
A48: Boxes, packaging, etc. | E48: 0
A49: Direct Cost | E49: =SUM(E40:E48) -> 4985.8509 | F49: Source: SULU-bdg FoodTesting.xlsx - ITEM SALES RECIPE
A50: Indirect Cost | E50: =E49*15% -> 747.87763 | F50: Status: Recipe Available
A51: Cost of Goods Sold (COGS) | E51: =E49+E50 -> 5733.7285
A52: Margin | E52: =IF(E54>0,E54-E51,0) -> 9266.2715
A53: Div COGS | E53: =IFERROR(E51/E54,0) -> 0.38224857
A54: Selling Price | E54: 15000
A56: Tebasaki
A57: Element | B57: UOM | C57: Element Cost/(g) | D57: Portion Used | E57: Value /pcs | F57: Major Step | G57: Units
A58: Sayap Ayam utuh | B58: PCS | C58: =IFERROR(VLOOKUP(A58,'Market List'!$B:$F,5,FALSE),0) -> 2916.6667 | D58: 1 | E58: =IFERROR(C58*D58,0) -> 2916.6667 | F58: Potong sayap menjadi 2, yang bagian ujung sayap tidak dipakai ,lalu bagian sayap di fillet butterfly posisi tulang terlihat, tusukan bambu di bagian atas tulang secara rapih
A59: Yakitori Butter WIP | B59: GR | C59: ='WIP FOOD'!$B$691 -> 76.564551 | D59: 35 | E59: =IFERROR(C59*D59,0) -> 2679.7593
A60: Tusuk Sate Yakitori 18cm | B60: PCS | C60: =IFERROR(VLOOKUP(A60,'Market List'!$B:$F,5,FALSE),0) -> 217.92 | D60: 1 | E60: =IFERROR(C60*D60,0) -> 217.92
A61: Furikake WIP | B61: GR | C61: ='WIP FOOD'!$B$218 -> 362.72092 | D61: 1 | E61: =IFERROR(C61*D61,0) -> 362.72092
A62: Onion Pickles | B62: GR | C62: =IFERROR(VLOOKUP(A62,'Market List'!$B:$F,5,FALSE),0) -> 91.76 | D62: 2 | E62: =IFERROR(C62*D62,0) -> 183.52
A63: Cucumber Pickles WIP | B63: GR | C63: ='WIP FOOD'!$B$119 -> 13.97688 | D63: 3 | E63: =IFERROR(C63*D63,0) -> 41.930639
C64: 0 | E64: =IFERROR(C64*D64,0) -> 0
C65: 0 | E65: =IFERROR(C65*D65,0) -> 0
A66: Boxes, packaging, etc. | E66: 0
A67: Direct Cost | E67: =SUM(E58:E66) -> 6402.5175 | F67: Source: SULU-bdg FoodTesting.xlsx - ITEM SALES RECIPE
A68: Indirect Cost | E68: =E67*15% -> 960.37763 | F68: Status: Recipe Available
A69: Cost of Goods Sold (COGS) | E69: =E67+E68 -> 7362.8952
A70: Margin | E70: =IF(E72>0,E72-E69,0) -> 12637.105
A71: Div COGS | E71: =IFERROR(E69/E72,0) -> 0.36814476
A72: Selling Price | E72: 20000
A74: Beef Enoki Roll
A75: Element | B75: UOM | C75: Element Cost/(g) | D75: Portion Used | E75: Value /pcs | F75: Major Step | G75: Units
A76: Beef Shorplate | B76: GR | C76: =IFERROR(VLOOKUP(A76,'Market List'!$B:$F,5,FALSE),0) -> 135 | D76: 30 | E76: =IFERROR(C76*D76,0) -> 4050 | F76: Lebarkan beef pada talenan, tempatkan enoki pada bagian bawang terlebih dahulu, gulung dengan cara dipadatkan setiap gulungan, lakukan hingga selesai
A77: Enoki Mushroom | B77: GR | C77: =IFERROR(VLOOKUP(A77,'Market List'!$B:$F,5,FALSE),0) -> 0 | D77: 8 | E77: =IFERROR(C77*D77,0) -> 0 | F77: Potong menjadi 2 bagian, lalu tusuk menggunakan tusukan yakitpri perlahan, pastikan jamur enoki tidak hancur didalam dan merekat dengan baik
A78: Yakitori Butter WIP | B78: GR | C78: ='WIP FOOD'!$B$691 -> 76.564551 | D78: 35 | E78: =IFERROR(C78*D78,0) -> 2679.7593 | F78: tempatkan pada hibachi yang sudah siap dengan arangnya, lalu oleskan yakitori butter dengan berulang kali, dan pastikan kematangan beef cukup medium, yang dimana
A79: Tusuk Sate Yakitori 18cm | B79: PCS | C79: =IFERROR(VLOOKUP(A79,'Market List'!$B:$F,5,FALSE),0) -> 217.92 | D79: 1 | E79: =IFERROR(C79*D79,0) -> 217.92 | F79: beef tidak terlalu coklat tua, cukup dipastikan tidak ada bagian merah atau pink di bagian daging
A80: Furikake WIP | B80: GR | C80: ='WIP FOOD'!$B$218 -> 362.72092 | D80: 1 | E80: =IFERROR(C80*D80,0) -> 362.72092
A81: Onion Pickles | B81: GR | C81: =IFERROR(VLOOKUP(A81,'Market List'!$B:$F,5,FALSE),0) -> 91.76 | D81: 2 | E81: =IFERROR(C81*D81,0) -> 183.52
A82: Cucumber Pickles WIP | B82: GR | C82: ='WIP FOOD'!$B$119 -> 13.97688 | D82: 3 | E82: =IFERROR(C82*D82,0) -> 41.930639
C83: 0 | E83: =IFERROR(C83*D83,0) -> 0
A84: Boxes, packaging, etc. | E84: 0
A85: Direct Cost | E85: =SUM(E76:E84) -> 7535.8509 | F85: Source: SULU-bdg FoodTesting.xlsx - ITEM SALES RECIPE
A86: Indirect Cost | E86: =E85*15% -> 1130.3776 | F86: Status: Recipe Available
A87: Cost of Goods Sold (COGS) | E87: =E85+E86 -> 8666.2285
A88: Margin | E88: =IF(E90>0,E90-E87,0) -> 16333.772
A89: Div COGS | E89: =IFERROR(E87/E90,0) -> 0.34664914
A90: Selling Price | E90: 25000
A92: Beef Mochi
A93: Element | B93: UOM | C93: Element Cost/(g) | D93: Portion Used | E93: Value /pcs | F93: Major Step | G93: Units
A94: Beef Shorplate | B94: GR | C94: =IFERROR(VLOOKUP(A94,'Market List'!$B:$F,5,FALSE),0) -> 135 | D94: 30 | E94: =IFERROR(C94*D94,0) -> 4050 | F94: Lebarkan beef pada talenan, Potong Mochi menjadi 3 bagian dan tempatkan mochi pada bagian bawah terlebih dahulu, gulung dengan cara dipadatkan setiap gulungan,
A95: Mochi Block | B95: PACK | C95: =IFERROR(VLOOKUP(A95,'Market List'!$B:$F,5,FALSE),0) -> 299.25926 | D95: 1 | E95: =IFERROR(C95*D95,0) -> 299.25926 | F95: pastikan mochi tidak hancur didalam dan merekat dengan baik
A96: Yakitori Butter WIP | B96: GR | C96: ='WIP FOOD'!$B$691 -> 76.564551 | D96: 35 | E96: =IFERROR(C96*D96,0) -> 2679.7593 | F96: tempatkan pada hibachi yang sudah siap dengan arangnya, lalu oleskan yakitori butter dengan berulang kali, dan pastikan kematangan beef cukup medium, yang dimana
A97: Furikake WIP | B97: GR | C97: ='WIP FOOD'!$B$218 -> 362.72092 | D97: 1 | E97: =IFERROR(C97*D97,0) -> 362.72092 | F97: beef tidak terlalu coklat tua, cukup dipastikan tidak ada bagian merah atau pink di bagian daging
A98: Onion Pickles | B98: GR | C98: =IFERROR(VLOOKUP(A98,'Market List'!$B:$F,5,FALSE),0) -> 91.76 | D98: 2 | E98: =IFERROR(C98*D98,0) -> 183.52
A99: Cucumber Pickles WIP | B99: GR | C99: ='WIP FOOD'!$B$119 -> 13.97688 | D99: 3 | E99: =IFERROR(C99*D99,0) -> 41.930639
C100: 0 | E100: =IFERROR(C100*D100,0) -> 0
C101: 0 | E101: =IFERROR(C101*D101,0) -> 0
A102: Boxes, packaging, etc. | E102: 0
A103: Direct Cost | E103: =SUM(E94:E102) -> 7617.1901 | F103: Source: SULU-bdg FoodTesting.xlsx - ITEM SALES RECIPE
A104: Indirect Cost | E104: =E103*15% -> 1142.5785 | F104: Status: Recipe Available
A105: Cost of Goods Sold (COGS) | E105: =E103+E104 -> 8759.7686
...

Sheet Teppanyaki Stall 
A1: Teppanyaki Stall
A2: Takoyaki
A3: Element | B3: UOM | C3: Element Cost/(g) | D3: Portion Used | E3: Value /pcs | F3: Major Step | G3: Units
A4: Adonan Takoyaki WIP | B4: Pcs | C4: ='WIP FOOD'!$B$28 -> 546.0819 | D4: 5 | E4: =IFERROR(C4*D4,0) -> 2730.4095 | F4: Recipe detail belum ditemukan pada ITEM SALES RECIPE / PDF yang tersedia.
A5: Udang Vaname | B5: Gr | C5: =IFERROR(VLOOKUP(A5,'Market List'!$B:$F,5,FALSE),0) -> 148 | D5: 25 | E5: =IFERROR(C5*D5,0) -> 3700
A6: Cumi | C6: =IFERROR(VLOOKUP(A6,'Market List'!$B:$F,5,FALSE),0) -> 185 | D6: 25 | E6: =IFERROR(C6*D6,0) -> 4625
A7: Aonori | B7: gr | C7: =IFERROR(VLOOKUP(A7,'Market List'!$B:$F,5,FALSE),0) -> 496 | D7: 1 | E7: =IFERROR(C7*D7,0) -> 496
A8: Daun Bawang | B8: gr | C8: =IFERROR(VLOOKUP(A8,'Market List'!$B:$F,5,FALSE),0) -> 20 | D8: 5 | E8: =IFERROR(C8*D8,0) -> 100
A9: Tanuki | B9: gr | C9: =IFERROR(VLOOKUP(A9,'Market List'!$B:$F,5,FALSE),0) -> 0 | D9: 20 | E9: =IFERROR(C9*D9,0) -> 0
A10: Okonomiyaki Sauce WIP | C10: ='WIP FOOD'!$B$452 -> 74.822755 | D10: 15 | E10: =IFERROR(C10*D10,0) -> 1122.3413
A11: Mayonaise | C11: =IFERROR(VLOOKUP(A11,'Market List'!$B:$F,5,FALSE),0) -> 72.3 | D11: 15 | E11: =IFERROR(C11*D11,0) -> 1084.5
A12: Katsuobushi | B12: gr | C12: =IFERROR(VLOOKUP(A12,'Market List'!$B:$F,5,FALSE),0) -> 478.3989 | D12: 1 | E12: =IFERROR(C12*D12,0) -> 478.3989
A15: Boxes, packaging, etc. | E15: 0
A16: Direct Cost | E16: =SUM(E4:E15) -> 14336.65 | F16: Source: -
A17: Indirect Cost | E17: =E16*15% -> 2150.4975 | F17: Status: Recipe Pending
A18: Cost of Goods Sold (COGS) | E18: =E16+E17 -> 16487.147
A19: Margin | E19: =IF(E21>0,E21-E18,0) -> 43512.853
A20: Div COGS | E20: =IFERROR(E18/E21,0) -> 0.27478579
A21: Selling Price | E21: 60000
A23: Yasai Itame
A24: Element | B24: UOM | C24: Element Cost/(g) | D24: Portion Used | E24: Value /pcs | F24: Major Step | G24: Units
A25: Kol | B25: GR | C25: =IFERROR(VLOOKUP(A25,'Market List'!$B:$F,5,FALSE),0) -> 13 | E25: =IFERROR(C25*D25,0) -> 0 | F25: Recipe detail belum ditemukan pada ITEM SALES RECIPE / PDF yang tersedia.
A26: Wortel | B26: GR | C26: =IFERROR(VLOOKUP(A26,'Market List'!$B:$F,5,FALSE),0) -> 20 | E26: =IFERROR(C26*D26,0) -> 0
A27: paprika merah | B27: GR | C27: =IFERROR(VLOOKUP(A27,'Market List'!$B:$F,5,FALSE),0) -> 0 | E27: =IFERROR(C27*D27,0) -> 0
A28: paprica hijau | B28: GR | C28: =IFERROR(VLOOKUP(A28,'Market List'!$B:$F,5,FALSE),0) -> 65 | E28: =IFERROR(C28*D28,0) -> 0
A29: Bawang Bombay | B29: GR | C29: =IFERROR(VLOOKUP(A29,'Market List'!$B:$F,5,FALSE),0) -> 35 | E29: =IFERROR(C29*D29,0) -> 0
A30: Beef Shortplate Slice | B30: GR | C30: =IFERROR(VLOOKUP(A30,'Market List'!$B:$F,5,FALSE),0) -> 135 | E30: =IFERROR(C30*D30,0) -> 0
E31: =IFERROR(C31*D31,0) -> 0
E32: =IFERROR(C32*D32,0) -> 0
A33: Boxes, packaging, etc. | E33: 0
A34: Direct Cost | E34: =SUM(E25:E33) -> 0 | F34: Source: -
A35: Indirect Cost | E35: =E34*15% -> 0 | F35: Status: Recipe Pending
A36: Cost of Goods Sold (COGS) | E36: =E34+E35 -> 0
A37: Margin | E37: =IF(E39>0,E39-E36,0) -> 65000
A38: Div COGS | E38: =IFERROR(E36/E39,0) -> 0
A39: Selling Price | E39: 65000
A41: Ika Sugatayaki
A42: Element | B42: UOM | C42: Element Cost/(g) | D42: Portion Used | E42: Value /pcs | F42: Major Step | G42: Units
A43: Cumi | C43: =IFERROR(VLOOKUP(A43,'Market List'!$B:$F,5,FALSE),0) -> 185 | D43: 100 | E43: =IFERROR(C43*D43,0) -> 18500 | F43: Recipe detail belum ditemukan pada ITEM SALES RECIPE / PDF yang tersedia.
E44: =IFERROR(C44*D44,0) -> 0
E45: =IFERROR(C45*D45,0) -> 0
E46: =IFERROR(C46*D46,0) -> 0
E47: =IFERROR(C47*D47,0) -> 0
E48: =IFERROR(C48*D48,0) -> 0
E49: =IFERROR(C49*D49,0) -> 0
E50: =IFERROR(C50*D50,0) -> 0
A51: Boxes, packaging, etc. | E51: 0
A52: Direct Cost | E52: =SUM(E43:E51) -> 18500 | F52: Source: -
A53: Indirect Cost | E53: =E52*15% -> 2775 | F53: Status: Recipe Pending
A54: Cost of Goods Sold (COGS) | E54: =E52+E53 -> 21275
A55: Margin | E55: =IF(E57>0,E57-E54,0) -> 33725
A56: Div COGS | E56: =IFERROR(E54/E57,0) -> 0.38681818
A57: Selling Price | E57: 55000
A59: Ika Okonomiyaki
A60: Element | B60: UOM | C60: Element Cost/(g) | D60: Portion Used | E60: Value /pcs | F60: Major Step | G60: Units
A61: Adonan Okonomiyaki WIP | B61: GR | C61: ='WIP FOOD'!$B$17 -> 2346.1984 | E61: =IFERROR(C61*D61,0) -> 0 | F61: Recipe detail belum ditemukan pada ITEM SALES RECIPE / PDF yang tersedia.
A62: Kol | B62: GR | C62: =IFERROR(VLOOKUP(A62,'Market List'!$B:$F,5,FALSE),0) -> 13 | E62: =IFERROR(C62*D62,0) -> 0
A63: Daun Bawang | B63: GR | C63: =IFERROR(VLOOKUP(A63,'Market List'!$B:$F,5,FALSE),0) -> 20 | E63: =IFERROR(C63*D63,0) -> 0
A64: Aonori | B64: GR | C64: =IFERROR(VLOOKUP(A64,'Market List'!$B:$F,5,FALSE),0) -> 496 | E64: =IFERROR(C64*D64,0) -> 0
A65: Okonomiyaki Sauce WIP | C65: ='WIP FOOD'!$B$452 -> 74.822755 | E65: =IFERROR(C65*D65,0) -> 0
A66: Mayonaise | C66: =IFERROR(VLOOKUP(A66,'Market List'!$B:$F,5,FALSE),0) -> 72.3 | E66: =IFERROR(C66*D66,0) -> 0
A67: Cumi | C67: =IFERROR(VLOOKUP(A67,'Market List'!$B:$F,5,FALSE),0) -> 185 | E67: =IFERROR(C67*D67,0) -> 0
A68: Togarashi | C68: =IFERROR(VLOOKUP(A68,'Market List'!$B:$F,5,FALSE),0) -> 351.66667 | E68: =IFERROR(C68*D68,0) -> 0
A69: Boxes, packaging, etc. | E69: 0
A70: Direct Cost | E70: =SUM(E61:E69) -> 0 | F70: Source: -
A71: Indirect Cost | E71: =E70*15% -> 0 | F71: Status: Recipe Pending
A72: Cost of Goods Sold (COGS) | E72: =E70+E71 -> 0
A73: Margin | E73: =IF(E75>0,E75-E72,0) -> 60000
A74: Div COGS | E74: =IFERROR(E72/E75,0) -> 0
A75: Selling Price | E75: 60000
A77: Beef Okonomiyaki
A78: Element | B78: UOM | C78: Element Cost/(g) | D78: Portion Used | E78: Value /pcs | F78: Major Step | G78: Units
A79: Adonan Okonomiyaki WIP | B79: GR | C79: ='WIP FOOD'!$B$17 -> 2346.1984 | E79: =IFERROR(C79*D79,0) -> 0 | F79: Recipe detail belum ditemukan pada ITEM SALES RECIPE / PDF yang tersedia.
A80: Kol | B80: GR | C80: =IFERROR(VLOOKUP(A80,'Market List'!$B:$F,5,FALSE),0) -> 13 | E80: =IFERROR(C80*D80,0) -> 0
A81: Daun Bawang | B81: GR | C81: =IFERROR(VLOOKUP(A81,'Market List'!$B:$F,5,FALSE),0) -> 20 | E81: =IFERROR(C81*D81,0) -> 0
A82: Aonori | B82: GR | C82: =IFERROR(VLOOKUP(A82,'Market List'!$B:$F,5,FALSE),0) -> 496 | E82: =IFERROR(C82*D82,0) -> 0
A83: Okonomiyaki Sauce WIP | C83: ='WIP FOOD'!$B$452 -> 74.822755 | E83: =IFERROR(C83*D83,0) -> 0
A84: Mayonaise | C84: =IFERROR(VLOOKUP(A84,'Market List'!$B:$F,5,FALSE),0) -> 72.3 | E84: =IFERROR(C84*D84,0) -> 0
A85: Beef marinasi yakiniku | B85: GR | C85: =IFERROR(VLOOKUP(A85,'Market List'!$B:$F,5,FALSE),0) -> 0 | E85: =IFERROR(C85*D85,0) -> 0
E86: =IFERROR(C86*D86,0) -> 0
A87: Boxes, packaging, etc. | E87: 0
A88: Direct Cost | E88: =SUM(E79:E87) -> 0 | F88: Source: -
A89: Indirect Cost | E89: =E88*15% -> 0 | F89: Status: Recipe Pending
A90: Cost of Goods Sold (COGS) | E90: =E88+E89 -> 0
A91: Margin | E91: =IF(E93>0,E93-E90,0) -> 65000
A92: Div COGS | E92: =IFERROR(E90/E93,0) -> 0
A93: Selling Price | E93: 65000

Sheet Dumpling Stall
A1: Dumpling Stall
A2: Okonomiyaki Gyoza
A3: Element | B3: UOM | C3: Element Cost/(g) | D3: Portion Used | E3: Value /pcs | F3: Major Step | G3: Units
A4: Adonan Gyoza WIP | B4: PCS | C4: ='WIP FOOD'!$B$3 -> 598.22 | D4: 5 | E4: =IFERROR(C4*D4,0) -> 2991.1 | F4: Panaskan Teplon dan tuangkan minyak goreng, masukan gyoza dengan lipatan diatas, gunakan api kecil terlebih dahulu dan tutup dengan teplon 1 nya guna uap panas biar merata
A5: Gyoza Tuile WIP | B5: PCS | C5: ='WIP FOOD'!$B$229 -> 168.975 | D5: 1 | E5: =IFERROR(C5*D5,0) -> 168.975 | F5: setelah kurang lebih 3 menit, berikan air secukupnya gunakan teknik masak kukus agar gyoza matang merata dan tutup kembali, dan gunakan api sedang.
A6: Okonomiyaki Sauce WIP | B6: GR | C6: ='WIP FOOD'!$B$452 -> 74.822755 | D6: 50 | E6: =IFERROR(C6*D6,0) -> 3741.1378 | F6: setelah dirasa cukup dari segi warna sedikit char dari bagian bawah gyoza, angkat dan tata diatas plate, tempatkan tuille di bagian atas gyoza hingga menutupi seluruh gyozanya
A7: Mayonaise | B7: GR | C7: =IFERROR(VLOOKUP(A7,'Market List'!$B:$F,5,FALSE),0) -> 72.3 | D7: 30 | E7: =IFERROR(C7*D7,0) -> 2169 | F7: berikan sauce okonomiyaki pada bagian tuille nya setelah itu mayonaise, berikan katsuobushi dan taburan aonori.
A8: Katsuobushi | B8: GR | C8: =IFERROR(VLOOKUP(A8,'Market List'!$B:$F,5,FALSE),0) -> 478.3989 | D8: 2 | E8: =IFERROR(C8*D8,0) -> 956.7978
A9: Aonori | B9: GR | C9: =IFERROR(VLOOKUP(A9,'Market List'!$B:$F,5,FALSE),0) -> 496 | D9: 1 | E9: =IFERROR(C9*D9,0) -> 496
A10: Minyak Goreng | B10: ML | C10: =IFERROR(VLOOKUP(A10,'Market List'!$B:$F,5,FALSE),0) -> 21.944444 | D10: 20 | E10: =IFERROR(C10*D10,0) -> 438.88889
E11: =IFERROR(C11*D11,0) -> 0
A12: Boxes, packaging, etc. | E12: 0
A13: Direct Cost | E13: =SUM(E4:E12) -> 10961.899 | F13: Source: SULU-bdg FoodTesting.xlsx - ITEM SALES RECIPE
A14: Indirect Cost | E14: =E13*15% -> 1644.2849 | F14: Status: Recipe Available
A15: Cost of Goods Sold (COGS) | E15: =E13+E14 -> 12606.184
A16: Margin | E16: =IF(E18>0,E18-E15,0) -> 22393.816
A17: Div COGS | E17: =IFERROR(E15/E18,0) -> 0.3601767
A18: Selling Price | E18: 35000
A20: Slider Gyoza Mentai
A21: Element | B21: UOM | C21: Element Cost/(g) | D21: Portion Used | E21: Value /pcs | F21: Major Step | G21: Units
A22: Adonan Gyoza WIP | B22: PCS | C22: ='WIP FOOD'!$B$3 -> 598.22 | D22: 5 | E22: =IFERROR(C22*D22,0) -> 2991.1 | F22: Goreng Gyoza dengan temprature normal 150-170 derajat, pastikan selesai dengan warna golden brown.
A23: Mentaiko Mayo WIP | B23: GR | C23: ='WIP FOOD'!$B$362 -> 163.41546 | D23: 30 | E23: =IFERROR(C23*D23,0) -> 4902.4638 | F23: setelah dapat dipastikan matang, tata di piring dengan memanjang rapi, berikan sauce mentaiko terlebih dahulu, taburi furikake dan terakhir berikan garnish ditata memanjang
A24: Furikake WIP | B24: GR | C24: ='WIP FOOD'!$B$218 -> 362.72092 | D24: 2 | E24: =IFERROR(C24*D24,0) -> 725.44184 | F24: mengikuti persentasi gyoza nya. terakhir tempatkan lime sichimi nya di bagian atas gyoza
A25: Garnish daun bawang dan paprika | B25: GR | C25: =IFERROR(VLOOKUP(A25,'Market List'!$B:$F,5,FALSE),0) -> 0 | D25: 2 | E25: =IFERROR(C25*D25,0) -> 0
A26: Lime Sichimi | B26: GR | C26: =IFERROR(VLOOKUP(A26,'Market List'!$B:$F,5,FALSE),0) -> 351.66667 | D26: 5 | E26: =IFERROR(C26*D26,0) -> 1758.3333
E27: =IFERROR(C27*D27,0) -> 0
E28: =IFERROR(C28*D28,0) -> 0
E29: =IFERROR(C29*D29,0) -> 0
A30: Boxes, packaging, etc. | E30: 0
A31: Direct Cost | E31: =SUM(E22:E30) -> 10377.339 | F31: Source: SULU-bdg FoodTesting.xlsx - ITEM SALES RECIPE
A32: Indirect Cost | E32: =E31*15% -> 1556.6008 | F32: Status: Recipe Available
A33: Cost of Goods Sold (COGS) | E33: =E31+E32 -> 11933.94
A34: Margin | E34: =IF(E36>0,E36-E33,0) -> 23066.06
A35: Div COGS | E35: =IFERROR(E33/E36,0) -> 0.34096971
A36: Selling Price | E36: 35000
A38: Spicy Tteokboki Gyoza
A39: Element | B39: UOM | C39: Element Cost/(g) | D39: Portion Used | E39: Value /pcs | F39: Major Step | G39: Units
A40: Adonan Gyoza WIP | B40: PCS | C40: ='WIP FOOD'!$B$3 -> 598.22 | D40: 5 | E40: =IFERROR(C40*D40,0) -> 2991.1 | F40: Panaskan Teplon dan tuangkan minyak goreng, masukan gyoza dengan lipatan diatas, gunakan api kecil terlebih dahulu dan tutup dengan teplon 1 nya guna uap panas biar merata
A41: Minyak Goreng | B41: ML | C41: =IFERROR(VLOOKUP(A41,'Market List'!$B:$F,5,FALSE),0) -> 21.944444 | D41: 20 | E41: =IFERROR(C41*D41,0) -> 438.88889 | F41: setelah kurang lebih 3 menit, berikan air secukupnya gunakan teknik masak kukus agar gyoza matang merata dan tutup kembali, dan gunakan api sedang.
A42: Tteokbokki Sauce WIP | B42: GR | C42: ='WIP FOOD'!$B$650 -> 80.31259 | D42: 120 | E42: =IFERROR(C42*D42,0) -> 9637.5108 | F42: Panaskan Sauce tteokbokki hingga mendidih dan panas merata, tuang pada bagian plate, angkat gyoza yang sudah dirasa cukup matang, dan tata pada bagian atas tteokbokki saucenya
A43: Furikake WIP | B43: GR | C43: ='WIP FOOD'!$B$218 -> 362.72092 | D43: 2 | E43: =IFERROR(C43*D43,0) -> 725.44184 | F43: taburi furikake dan daun bawang, tempatkan lime sichimi pada bagian atas untuk final persentasi
A44: Daun Bawang | B44: GR | C44: =IFERROR(VLOOKUP(A44,'Market List'!$B:$F,5,FALSE),0) -> 20 | D44: 2 | E44: =IFERROR(C44*D44,0) -> 40
A45: Lime Sichimi | B45: GR | C45: =IFERROR(VLOOKUP(A45,'Market List'!$B:$F,5,FALSE),0) -> 351.66667 | D45: 5 | E45: =IFERROR(C45*D45,0) -> 1758.3333
E46: =IFERROR(C46*D46,0) -> 0
E47: =IFERROR(C47*D47,0) -> 0
A48: Boxes, packaging, etc. | E48: 0
A49: Direct Cost | E49: =SUM(E40:E48) -> 15591.275 | F49: Source: SULU-bdg FoodTesting.xlsx - ITEM SALES RECIPE
A50: Indirect Cost | E50: =E49*15% -> 2338.6912 | F50: Status: Recipe Available
A51: Cost of Goods Sold (COGS) | E51: =E49+E50 -> 17929.966
A52: Margin | E52: =IF(E54>0,E54-E51,0) -> 17070.034
A53: Div COGS | E53: =IFERROR(E51/E54,0) -> 0.51228475
A54: Selling Price | E54: 35000
A56: Yaki Gyoza
A57: Element | B57: UOM | C57: Element Cost/(g) | D57: Portion Used | E57: Value /pcs | F57: Major Step | G57: Units
A58: Adonan Gyoza WIP | B58: GR | C58: ='WIP FOOD'!$B$3 -> 598.22 | D58: 5 | E58: =IFERROR(C58*D58,0) -> 2991.1 | F58: Recipe detail belum ditemukan pada ITEM SALES RECIPE / PDF yang tersedia.
E59: =IFERROR(C59*D59,0) -> 0
E60: =IFERROR(C60*D60,0) -> 0
E61: =IFERROR(C61*D61,0) -> 0
E62: =IFERROR(C62*D62,0) -> 0
E63: =IFERROR(C63*D63,0) -> 0
E64: =IFERROR(C64*D64,0) -> 0
E65: =IFERROR(C65*D65,0) -> 0
A66: Boxes, packaging, etc. | E66: 0
A67: Direct Cost | E67: =SUM(E58:E66) -> 2991.1 | F67: Source: -
A68: Indirect Cost | E68: =E67*15% -> 448.665 | F68: Status: Recipe Pending
A69: Cost of Goods Sold (COGS) | E69: =E67+E68 -> 3439.765
A70: Margin | E70: =IF(E72>0,E72-E69,0) -> 21560.235
A71: Div COGS | E71: =IFERROR(E69/E72,0) -> 0.1375906
A72: Selling Price | E72: 25000
A74: Age Gyoza
A75: Element | B75: UOM | C75: Element Cost/(g) | D75: Portion Used | E75: Value /pcs | F75: Major Step | G75: Units
A76: Adonan Gyoza WIP | B76: GR | C76: ='WIP FOOD'!$B$3 -> 598.22 | D76: 5 | E76: =IFERROR(C76*D76,0) -> 2991.1 | F76: Recipe detail belum ditemukan pada ITEM SALES RECIPE / PDF yang tersedia.
A77: Minyak Goreng | B77: ML | C77: =IFERROR(VLOOKUP(A77,'Market List'!$B:$F,5,FALSE),0) -> 21.944444 | D77: 5 | E77: =IFERROR(C77*D77,0) -> 109.72222
E78: =IFERROR(C78*D78,0) -> 0
E79: =IFERROR(C79*D79,0) -> 0
E80: =IFERROR(C80*D80,0) -> 0
E81: =IFERROR(C81*D81,0) -> 0
E82: =IFERROR(C82*D82,0) -> 0
E83: =IFERROR(C83*D83,0) -> 0
A84: Boxes, packaging, etc. | E84: 0
A85: Direct Cost | E85: =SUM(E76:E84) -> 3100.8222 | F85: Source: -
A86: Indirect Cost | E86: =E85*15% -> 465.12333 | F86: Status: Recipe Pending
A87: Cost of Goods Sold (COGS) | E87: =E85+E86 -> 3565.9456
A88: Margin | E88: =IF(E90>0,E90-E87,0) -> 21434.054
A89: Div COGS | E89: =IFERROR(E87/E90,0) -> 0.14263782
A90: Selling Price | E90: 25000

Sheet Sushi - Sashimi Stall
A1: Sushi - Sashimi Stall
A2: Tamagoyaki Mentai
A3: Element | B3: UOM | C3: Element Cost/(g) | D3: Portion Used | E3: Value /pcs | F3: Major Step | G3: Units
A4: Adonan Tamagoyaki WIP | B4: PCS | C4: ='WIP FOOD'!$B$41 -> 1405.0439 | D4: 3 | E4: =IFERROR(C4*D4,0) -> 4215.1317 | F4: Recipe detail belum ditemukan pada ITEM SALES RECIPE / PDF yang tersedia.
A5: Mentaiko Mayo WIP | B5: GR | C5: ='WIP FOOD'!$B$362 -> 163.41546 | D5: 20 | E5: =IFERROR(C5*D5,0) -> 3268.3092
A6: Tobiko Orange | B6: ML | C6: =IFERROR(VLOOKUP(A6,'Market List'!$B:$F,5,FALSE),0) -> 0 | D6: 5 | E6: =IFERROR(C6*D6,0) -> 0
B7: GR | E7: =IFERROR(C7*D7,0) -> 0
E8: =IFERROR(C8*D8,0) -> 0
E9: =IFERROR(C9*D9,0) -> 0
E10: =IFERROR(C10*D10,0) -> 0
E11: =IFERROR(C11*D11,0) -> 0
A12: Boxes, packaging, etc. | E12: 0
A13: Direct Cost | E13: =SUM(E4:E12) -> 7483.4409 | F13: Source: -
A14: Indirect Cost | E14: =E13*15% -> 1122.5161 | F14: Status: Recipe Pending
A15: Cost of Goods Sold (COGS) | E15: =E13+E14 -> 8605.9571
A16: Margin | E16: =IF(E18>0,E18-E15,0) -> 0
A17: Div COGS | E17: =IFERROR(E15/E18,0) -> 0
A18: Selling Price
A20: Tuna Wasabi Mayo Taco
A21: Element | B21: UOM | C21: Element Cost/(g) | D21: Portion Used | E21: Value /pcs | F21: Major Step | G21: Units
A22: Tuna Saku | B22: GR | C22: =IFERROR(VLOOKUP(A22,'Market List'!$B:$F,5,FALSE),0) -> 0 | D22: 50 | E22: =IFERROR(C22*D22,0) -> 0 | F22: Recipe detail belum ditemukan pada ITEM SALES RECIPE / PDF yang tersedia.
A23: Mayonaise | B23: GR | C23: =IFERROR(VLOOKUP(A23,'Market List'!$B:$F,5,FALSE),0) -> 72.3 | D23: 100 | E23: =IFERROR(C23*D23,0) -> 7230
A24: Nori Sheets | B24: SHEET | C24: =IFERROR(VLOOKUP(A24,'Market List'!$B:$F,5,FALSE),0) -> 2741.6667 | D24: 1 | E24: =IFERROR(C24*D24,0) -> 2741.6667
A25: tobiko hitam | B25: GR | C25: =IFERROR(VLOOKUP(A25,'Market List'!$B:$F,5,FALSE),0) -> 0 | D25: 20 | E25: =IFERROR(C25*D25,0) -> 0
A26: Daun Bawang | B26: GR | C26: =IFERROR(VLOOKUP(A26,'Market List'!$B:$F,5,FALSE),0) -> 20 | D26: 5 | E26: =IFERROR(C26*D26,0) -> 100
A27: adonan tempura | B27: GR | C27: =IFERROR(VLOOKUP(A27,'Market List'!$B:$F,5,FALSE),0) -> 0 | D27: 10 | E27: =IFERROR(C27*D27,0) -> 0
E28: =IFERROR(C28*D28,0) -> 0
E29: =IFERROR(C29*D29,0) -> 0
A30: Boxes, packaging, etc. | E30: 0
A31: Direct Cost | E31: =SUM(E22:E30) -> 10071.667 | F31: Source: -
A32: Indirect Cost | E32: =E31*15% -> 1510.75 | F32: Status: Recipe Pending
A33: Cost of Goods Sold (COGS) | E33: =E31+E32 -> 11582.417
A34: Margin | E34: =IF(E36>0,E36-E33,0) -> 0
A35: Div COGS | E35: =IFERROR(E33/E36,0) -> 0
A36: Selling Price
A38: Unagi Nigiri
A39: Element | B39: UOM | C39: Element Cost/(g) | D39: Portion Used | E39: Value /pcs | F39: Major Step | G39: Units
A40: UNAGI | B40: GR | C40: =IFERROR(VLOOKUP(A40,'Market List'!$B:$F,5,FALSE),0) -> 0 | D40: 48 | E40: =IFERROR(C40*D40,0) -> 0 | F40: Recipe detail belum ditemukan pada ITEM SALES RECIPE / PDF yang tersedia.
A41: Nasi Sushi WIP | B41: GR | C41: ='WIP FOOD'!$B$421 -> 811.36364 | D41: 52 | E41: =IFERROR(C41*D41,0) -> 42190.909
A42: NORI IKETAN | C42: =IFERROR(VLOOKUP(A42,'Market List'!$B:$F,5,FALSE),0) -> 0 | D42: 40 | E42: =IFERROR(C42*D42,0) -> 0
E43: =IFERROR(C43*D43,0) -> 0
E44: =IFERROR(C44*D44,0) -> 0
E45: =IFERROR(C45*D45,0) -> 0
E46: =IFERROR(C46*D46,0) -> 0
E47: =IFERROR(C47*D47,0) -> 0
A48: Boxes, packaging, etc. | E48: 0
A49: Direct Cost | E49: =SUM(E40:E48) -> 42190.909 | F49: Source: -
A50: Indirect Cost | E50: =E49*15% -> 6328.6364 | F50: Status: Recipe Pending
A51: Cost of Goods Sold (COGS) | E51: =E49+E50 -> 48519.545
A52: Margin | E52: =IF(E54>0,E54-E51,0) -> 0
A53: Div COGS | E53: =IFERROR(E51/E54,0) -> 0
A54: Selling Price
A56: Chuka Idako Gunkan
A57: Element | B57: UOM | C57: Element Cost/(g) | D57: Portion Used | E57: Value /pcs | F57: Major Step | G57: Units
E58: =IFERROR(C58*D58,0) -> 0 | F58: Recipe detail belum ditemukan pada ITEM SALES RECIPE / PDF yang tersedia.
E59: =IFERROR(C59*D59,0) -> 0
E60: =IFERROR(C60*D60,0) -> 0
E61: =IFERROR(C61*D61,0) -> 0
E62: =IFERROR(C62*D62,0) -> 0
E63: =IFERROR(C63*D63,0) -> 0
E64: =IFERROR(C64*D64,0) -> 0
E65: =IFERROR(C65*D65,0) -> 0
A66: Boxes, packaging, etc. | E66: 0
A67: Direct Cost | E67: =SUM(E58:E66) -> 0 | F67: Source: -
A68: Indirect Cost | E68: =E67*15% -> 0 | F68: Status: Recipe Pending
A69: Cost of Goods Sold (COGS) | E69: =E67+E68 -> 0
A70: Margin | E70: =IF(E72>0,E72-E69,0) -> 0
A71: Div COGS | E71: =IFERROR(E69/E72,0) -> 0
A72: Selling Price
A74: Chuka Idako Tsumami
A75: Element | B75: UOM | C75: Element Cost/(g) | D75: Portion Used | E75: Value /pcs | F75: Major Step | G75: Units
E76: =IFERROR(C76*D76,0) -> 0 | F76: Recipe detail belum ditemukan pada ITEM SALES RECIPE / PDF yang tersedia.
E77: =IFERROR(C77*D77,0) -> 0
E78: =IFERROR(C78*D78,0) -> 0
E79: =IFERROR(C79*D79,0) -> 0
E80: =IFERROR(C80*D80,0) -> 0
E81: =IFERROR(C81*D81,0) -> 0
E82: =IFERROR(C82*D82,0) -> 0
E83: =IFERROR(C83*D83,0) -> 0
A84: Boxes, packaging, etc. | E84: 0
A85: Direct Cost | E85: =SUM(E76:E84) -> 0 | F85: Source: -
A86: Indirect Cost | E86: =E85*15% -> 0 | F86: Status: Recipe Pending
A87: Cost of Goods Sold (COGS) | E87: =E85+E86 -> 0
A88: Margin | E88: =IF(E90>0,E90-E87,0) -> 0
A89: Div COGS | E89: =IFERROR(E87/E90,0) -> 0
A90: Selling Price
A92: Unagi Sushi Roll
A93: Element | B93: UOM | C93: Element Cost/(g) | D93: Portion Used | E93: Value /pcs | F93: Major Step | G93: Units
A94: Nasi Sushi WIP | B94: GR | C94: ='WIP FOOD'!$B$421 -> 811.36364 | D94: 180 | E94: =IFERROR(C94*D94,0) -> 146045.45 | F94: Recipe detail belum ditemukan pada ITEM SALES RECIPE / PDF yang tersedia.
A95: Nori Sheets | B95: GR | C95: =IFERROR(VLOOKUP(A95,'Market List'!$B:$F,5,FALSE),0) -> 2741.6667 | D95: 15 | E95: =IFERROR(C95*D95,0) -> 41125
A96: Kyuri/japanese cucumber | B96: GR | C96: =IFERROR(VLOOKUP(A96,'Market List'!$B:$F,5,FALSE),0) -> 17.5 | D96: 12 | E96: =IFERROR(C96*D96,0) -> 210
A97: SLICE UNAGI | B97: GR | C97: =IFERROR(VLOOKUP(A97,'Market List'!$B:$F,5,FALSE),0) -> 0 | D97: 60 | E97: =IFERROR(C97*D97,0) -> 0
A98: CREAM CHEESE | B98: GR | C98: =IFERROR(VLOOKUP(A98,'Market List'!$B:$F,5,FALSE),0) -> 0 | D98: 24 | E98: =IFERROR(C98*D98,0) -> 0
A99: Tare Sauce WIP | C99: ='WIP FOOD'!$B$627 -> 34.238304 | E99: =IFERROR(C99*D99,0) -> 0
A100: Mentaiko Mayo WIP | C100: ='WIP FOOD'!$B$362 -> 163.41546 | E100: =IFERROR(C100*D100,0) -> 0
A101: Furikake WIP | B101: GR | C101: ='WIP FOOD'!$B$218 -> 362.72092 | E101: =IFERROR(C101*D101,0) -> 0
A102: Boxes, packaging, etc. | E102: 0
A103: Direct Cost | E103: =SUM(E94:E102) -> 187380.45 | F103: Source: -
A104: Indirect Cost | E104: =E103*15% -> 28107.068 | F104: Status: Recipe Pending
A105: Cost of Goods Sold (COGS) | E105: =E103+E104 -> 215487.52
...

Sheet Bakery Stall
A1: Bakery Stall
A2: Doughnut Matcha
A3: Element | B3: UOM | C3: Element Cost/(g) | D3: Portion Used | E3: Value /pcs | F3: Major Step | G3: Units
A4: Donat / Bomboloni WIP | B4: PCS | C4: ='WIP FOOD'!$B$150 -> 1131.0914 | D4: 1 | E4: =IFERROR(C4*D4,0) -> 1131.0914
A5: Matcha Filling WIP | B5: GR | C5: ='WIP FOOD'!$B$329 -> 68.93893 | D5: 22 | E5: =IFERROR(C5*D5,0) -> 1516.6565
E6: =IFERROR(C6*D6,0) -> 0
E7: =IFERROR(C7*D7,0) -> 0
E8: =IFERROR(C8*D8,0) -> 0
E9: =IFERROR(C9*D9,0) -> 0
E10: =IFERROR(C10*D10,0) -> 0
E11: =IFERROR(C11*D11,0) -> 0
A12: Boxes, packaging, etc. | E12: 0
A13: Direct Cost | E13: =SUM(E4:E12) -> 2647.7479 | F13: Source: Uploaded Bakery Recipe PDFs
A14: Indirect Cost | E14: =E13*15% -> 397.16219 | F14: Status: Assembly Qty Pending
A15: Cost of Goods Sold (COGS) | E15: =E13+E14 -> 3044.9101
A16: Margin | E16: =IF(E18>0,E18-E15,0) -> 11955.09
A17: Div COGS | E17: =IFERROR(E15/E18,0) -> 0.20299401
A18: Selling Price | E18: 15000
A20: Doughnut Hojicha
A21: Element | B21: UOM | C21: Element Cost/(g) | D21: Portion Used | E21: Value /pcs | F21: Major Step | G21: Units
A22: Donat / Bomboloni WIP | B22: PCS | C22: ='WIP FOOD'!$B$150 -> 1131.0914 | D22: 1 | E22: =IFERROR(C22*D22,0) -> 1131.0914
A23: Hojicha Filling WIP | B23: GR | C23: ='WIP FOOD'!$B$250 -> 72.490303 | D23: 22 | E23: =IFERROR(C23*D23,0) -> 1594.7867
E24: =IFERROR(C24*D24,0) -> 0
E25: =IFERROR(C25*D25,0) -> 0
E26: =IFERROR(C26*D26,0) -> 0
E27: =IFERROR(C27*D27,0) -> 0
E28: =IFERROR(C28*D28,0) -> 0
E29: =IFERROR(C29*D29,0) -> 0
A30: Boxes, packaging, etc. | E30: 0
A31: Direct Cost | E31: =SUM(E22:E30) -> 2725.8781 | F31: Source: Uploaded Bakery Recipe PDFs
A32: Indirect Cost | E32: =E31*15% -> 408.88172 | F32: Status: Assembly Qty Pending
A33: Cost of Goods Sold (COGS) | E33: =E31+E32 -> 3134.7598
A34: Margin | E34: =IF(E36>0,E36-E33,0) -> 11865.24
A35: Div COGS | E35: =IFERROR(E33/E36,0) -> 0.20898399
A36: Selling Price | E36: 15000
A38: Shuffle Pancake Mochi Chocolate
A39: Element | B39: UOM | C39: Element Cost/(g) | D39: Portion Used | E39: Value /pcs | F39: Major Step | G39: Units
A40: Souffle Pancake WIP | B40: PORTION | C40: ='WIP FOOD'!$B$531 -> 2380.0482 | D40: 1 | E40: =IFERROR(C40*D40,0) -> 2380.0482
A41: Mochi Plain WIP | B41: PCS | C41: ='WIP FOOD'!$B$401 -> 41.783225 | D41: 30 | E41: =IFERROR(C41*D41,0) -> 1253.4968
A42: Chocolate Sauce WIP | B42: GR | C42: ='WIP FOOD'!$B$109 -> 76.641669 | D42: 23 | E42: =IFERROR(C42*D42,0) -> 1762.7584
E43: =IFERROR(C43*D43,0) -> 0
E44: =IFERROR(C44*D44,0) -> 0
E45: =IFERROR(C45*D45,0) -> 0
E46: =IFERROR(C46*D46,0) -> 0
E47: =IFERROR(C47*D47,0) -> 0
A48: Boxes, packaging, etc. | E48: 0
A49: Direct Cost | E49: =SUM(E40:E48) -> 5396.3033 | F49: Source: Uploaded Bakery Recipe PDFs
A50: Indirect Cost | E50: =E49*15% -> 809.4455 | F50: Status: Assembly Qty Pending
A51: Cost of Goods Sold (COGS) | E51: =E49+E50 -> 6205.7488
A52: Margin | E52: =IF(E54>0,E54-E51,0) -> 0
A53: Div COGS | E53: =IFERROR(E51/E54,0) -> 0
A54: Selling Price
A56: Shuffle Pancake Mochi Matcha
A57: Element | B57: UOM | C57: Element Cost/(g) | D57: Portion Used | E57: Value /pcs | F57: Major Step | G57: Units
A58: Souffle Pancake WIP | B58: PORTION | C58: ='WIP FOOD'!$B$531 -> 2380.0482 | D58: 1 | E58: =IFERROR(C58*D58,0) -> 2380.0482
A59: Mochi Plain WIP | B59: PCS | C59: ='WIP FOOD'!$B$401 -> 41.783225 | D59: 30 | E59: =IFERROR(C59*D59,0) -> 1253.4968
A60: Matcha Sauce WIP | B60: GR | C60: ='WIP FOOD'!$B$339 -> 101.9616 | D60: 23 | E60: =IFERROR(C60*D60,0) -> 2345.1169
E61: =IFERROR(C61*D61,0) -> 0
E62: =IFERROR(C62*D62,0) -> 0
E63: =IFERROR(C63*D63,0) -> 0
E64: =IFERROR(C64*D64,0) -> 0
E65: =IFERROR(C65*D65,0) -> 0
A66: Boxes, packaging, etc. | E66: 0
A67: Direct Cost | E67: =SUM(E58:E66) -> 5978.6618 | F67: Source: Uploaded Bakery Recipe PDFs
A68: Indirect Cost | E68: =E67*15% -> 896.79927 | F68: Status: Assembly Qty Pending
A69: Cost of Goods Sold (COGS) | E69: =E67+E68 -> 6875.4611
A70: Margin | E70: =IF(E72>0,E72-E69,0) -> 0
A71: Div COGS | E71: =IFERROR(E69/E72,0) -> 0
A72: Selling Price
A74: Shuffle Pancake Mochi Hojicha
A75: Element | B75: UOM | C75: Element Cost/(g) | D75: Portion Used | E75: Value /pcs | F75: Major Step | G75: Units
A76: Souffle Pancake WIP | B76: PORTION | C76: ='WIP FOOD'!$B$531 -> 2380.0482 | D76: 1 | E76: =IFERROR(C76*D76,0) -> 2380.0482
A77: Mochi Plain WIP | B77: PCS | C77: ='WIP FOOD'!$B$401 -> 41.783225 | D77: 30 | E77: =IFERROR(C77*D77,0) -> 1253.4968
A78: Hojicha Sauce WIP | B78: GR | C78: ='WIP FOOD'!$B$260 -> 111.39712 | D78: 23 | E78: =IFERROR(C78*D78,0) -> 2562.1337
E79: =IFERROR(C79*D79,0) -> 0
E80: =IFERROR(C80*D80,0) -> 0
E81: =IFERROR(C81*D81,0) -> 0
E82: =IFERROR(C82*D82,0) -> 0
E83: =IFERROR(C83*D83,0) -> 0
A84: Boxes, packaging, etc. | E84: 0
A85: Direct Cost | E85: =SUM(E76:E84) -> 6195.6786 | F85: Source: Uploaded Bakery Recipe PDFs
A86: Indirect Cost | E86: =E85*15% -> 929.35179 | F86: Status: Assembly Qty Pending
A87: Cost of Goods Sold (COGS) | E87: =E85+E86 -> 7125.0304
A88: Margin | E88: =IF(E90>0,E90-E87,0) -> 0
A89: Div COGS | E89: =IFERROR(E87/E90,0) -> 0
A90: Selling Price
A92: Shuffle Pancake Mochi Vanilla
A93: Element | B93: UOM | C93: Element Cost/(g) | D93: Portion Used | E93: Value /pcs | F93: Major Step | G93: Units
A94: Souffle Pancake WIP | B94: PORTION | C94: ='WIP FOOD'!$B$531 -> 2380.0482 | D94: 1 | E94: =IFERROR(C94*D94,0) -> 2380.0482
A95: Mochi Plain WIP | B95: PCS | C95: ='WIP FOOD'!$B$401 -> 41.783225 | D95: 30 | E95: =IFERROR(C95*D95,0) -> 1253.4968
A96: Vanilla Sauce WIP | B96: GR | C96: ='WIP FOOD'!$B$664 -> 49.448411 | D96: 23 | E96: =IFERROR(C96*D96,0) -> 1137.3135
E97: =IFERROR(C97*D97,0) -> 0
E98: =IFERROR(C98*D98,0) -> 0
E99: =IFERROR(C99*D99,0) -> 0
E100: =IFERROR(C100*D100,0) -> 0
E101: =IFERROR(C101*D101,0) -> 0
A102: Boxes, packaging, etc. | E102: 0
A103: Direct Cost | E103: =SUM(E94:E102) -> 4770.8584 | F103: Source: Uploaded Bakery Recipe PDFs
A104: Indirect Cost | E104: =E103*15% -> 715.62876 | F104: Status: Assembly Qty Pending
A105: Cost of Goods Sold (COGS) | E105: =E103+E104 -> 5486.4871
...

Sheet Burger - sandwiches Stall
A1: Burger - sandwiches Stall
A2: Gyuniku Burger
A3: Element | B3: UOM | C3: Element Cost/(g) | D3: Portion Used | E3: Value /pcs | F3: Major Step | G3: Units
A4: Brioche Burger Bun WIP | B4: PCS | C4: ='WIP FOOD'!$B$51 -> 3998.7741 | D4: 75 | E4: =IFERROR(C4*D4,0) -> 299908.06 | F4: Recipe detail belum ditemukan pada ITEM SALES RECIPE / PDF yang tersedia.
A5: BEEF NOODLE | B5: GR | C5: =IFERROR(VLOOKUP(A5,'Market List'!$B:$F,5,FALSE),0) -> 0 | D5: 20 | E5: =IFERROR(C5*D5,0) -> 0
E6: =IFERROR(C6*D6,0) -> 0
E7: =IFERROR(C7*D7,0) -> 0
E8: =IFERROR(C8*D8,0) -> 0
E9: =IFERROR(C9*D9,0) -> 0
E10: =IFERROR(C10*D10,0) -> 0
E11: =IFERROR(C11*D11,0) -> 0
A12: Boxes, packaging, etc. | E12: 0
A13: Direct Cost | E13: =SUM(E4:E12) -> 299908.06 | F13: Source: -
A14: Indirect Cost | E14: =E13*15% -> 44986.209 | F14: Status: Recipe Pending
A15: Cost of Goods Sold (COGS) | E15: =E13+E14 -> 344894.27
A16: Margin | E16: =IF(E18>0,E18-E15,0) -> 0
A17: Div COGS | E17: =IFERROR(E15/E18,0) -> 0
A18: Selling Price
A20: Chicken Namban Burger
A21: Element | B21: UOM | C21: Element Cost/(g) | D21: Portion Used | E21: Value /pcs | F21: Major Step | G21: Units
A22: Brioche Burger Bun WIP | B22: PCS | C22: =IFERROR(VLOOKUP(A22,'Market List'!$B:$F,5,FALSE),0) -> 3998.7741 | D22: 1 | E22: =IFERROR(C22*D22,0) -> 3998.7741 | F22: Recipe detail belum ditemukan pada ITEM SALES RECIPE / PDF yang tersedia.
A23: Soy Chicken WIP | B23: GR | C23: =IFERROR(VLOOKUP(A23,'Market List'!$B:$F,5,FALSE),0) -> 1225.7319 | D23: 2 | E23: =IFERROR(C23*D23,0) -> 2451.4637
A24: Namban Sauce WIP | B24: ML | C24: ='WIP FOOD'!$B$411 -> 37.76749 | D24: 15 | E24: =IFERROR(C24*D24,0) -> 566.51235
A25: Egg Tartar WIP | B25: GR | C25: ='WIP FOOD'!$B$207 -> 45.457392 | D25: 30 | E25: =IFERROR(C25*D25,0) -> 1363.7218
A26: Daun Bawang | B26: GR | C26: =IFERROR(VLOOKUP(A26,'Market List'!$B:$F,5,FALSE),0) -> 20 | D26: 3 | E26: =IFERROR(C26*D26,0) -> 60
E27: =IFERROR(C27*D27,0) -> 0
E28: =IFERROR(C28*D28,0) -> 0
E29: =IFERROR(C29*D29,0) -> 0
A30: Boxes, packaging, etc. | E30: 0
A31: Direct Cost | E31: =SUM(E22:E30) -> 8440.4719 | F31: Source: -
A32: Indirect Cost | E32: =E31*15% -> 1266.0708 | F32: Status: Recipe Pending
A33: Cost of Goods Sold (COGS) | E33: =E31+E32 -> 9706.5427
A34: Margin | E34: =IF(E36>0,E36-E33,0) -> 0
A35: Div COGS | E35: =IFERROR(E33/E36,0) -> 0
A36: Selling Price
A38: Tempura Kimchi Hotdog
A39: Element | B39: UOM | C39: Element Cost/(g) | D39: Portion Used | E39: Value /pcs | F39: Major Step | G39: Units
A40: Udang Tempura | B40: PCS | C40: =IFERROR(VLOOKUP(A40,'Market List'!$B:$F,5,FALSE),0) -> 132 | D40: 15 | E40: =IFERROR(C40*D40,0) -> 1980 | F40: Recipe detail belum ditemukan pada ITEM SALES RECIPE / PDF yang tersedia.
A41: Kol Kimchi WIP | B41: GR | C41: ='WIP FOOD'!$B$288 -> 29.984632 | D41: 10 | E41: =IFERROR(C41*D41,0) -> 299.84632
A42: Brioche Hot Dog WIP | B42: PCS | C42: ='WIP FOOD'!$B$712 -> 2525.5416 | D42: 1 | E42: =IFERROR(C42*D42,0) -> 2525.5416
A43: Kyuri/japanese cucumber | B43: GR | C43: =IFERROR(VLOOKUP(A43,'Market List'!$B:$F,5,FALSE),0) -> 17.5 | D43: 10 | E43: =IFERROR(C43*D43,0) -> 175
A44: Cheese Cheddar | B44: GR | C44: =IFERROR(VLOOKUP(A44,'Market List'!$B:$F,5,FALSE),0) -> 91.05 | D44: 10 | E44: =IFERROR(C44*D44,0) -> 910.5
A45: KOREANDER | C45: =IFERROR(VLOOKUP(A45,'Market List'!$B:$F,5,FALSE),0) -> 0 | E45: =IFERROR(C45*D45,0) -> 0
E46: =IFERROR(C46*D46,0) -> 0
E47: =IFERROR(C47*D47,0) -> 0
A48: Boxes, packaging, etc. | E48: 0
A49: Direct Cost | E49: =SUM(E40:E48) -> 5890.8879 | F49: Source: -
A50: Indirect Cost | E50: =E49*15% -> 883.63318 | F50: Status: Recipe Pending
A51: Cost of Goods Sold (COGS) | E51: =E49+E50 -> 6774.5211
A52: Margin | E52: =IF(E54>0,E54-E51,0) -> 0
A53: Div COGS | E53: =IFERROR(E51/E54,0) -> 0
A54: Selling Price
A56: Large Sausage Hotdog
A57: Element | B57: UOM | C57: Element Cost/(g) | D57: Portion Used | E57: Value /pcs | F57: Major Step | G57: Units
A58: BEEF SAUSAGE | B58: PCS | C58: =IFERROR(VLOOKUP(A58,'Market List'!$B:$F,5,FALSE),0) -> 23616 | D58: 0.5 | E58: =IFERROR(C58*D58,0) -> 11808 | F58: Recipe detail belum ditemukan pada ITEM SALES RECIPE / PDF yang tersedia.
A59: Brioche Hot Dog WIP | B59: PCS | C59: ='WIP FOOD'!$B$712 -> 2525.5416 | D59: 1 | E59: =IFERROR(C59*D59,0) -> 2525.5416
A60: Mentaiko Mayo WIP | B60: ML | C60: ='WIP FOOD'!$B$362 -> 163.41546 | D60: 10 | E60: =IFERROR(C60*D60,0) -> 1634.1546
A61: Cheese Cheddar | B61: GR | C61: =IFERROR(VLOOKUP(A61,'Market List'!$B:$F,5,FALSE),0) -> 91.05 | D61: 10 | E61: =IFERROR(C61*D61,0) -> 910.5
A62: Onion Pickles | B62: GR | C62: =IFERROR(VLOOKUP(A62,'Market List'!$B:$F,5,FALSE),0) -> 91.76 | D62: 5 | E62: =IFERROR(C62*D62,0) -> 458.8
E63: =IFERROR(C63*D63,0) -> 0
E64: =IFERROR(C64*D64,0) -> 0
E65: =IFERROR(C65*D65,0) -> 0
A66: Boxes, packaging, etc. | E66: 0
A67: Direct Cost | E67: =SUM(E58:E66) -> 17336.996 | F67: Source: -
A68: Indirect Cost | E68: =E67*15% -> 2600.5494 | F68: Status: Recipe Pending
A69: Cost of Goods Sold (COGS) | E69: =E67+E68 -> 19937.546
A70: Margin | E70: =IF(E72>0,E72-E69,0) -> 40062.454
A71: Div COGS | E71: =IFERROR(E69/E72,0) -> 0.33229243
A72: Selling Price | E72: 60000
A74: Large Sausage Hotdog
A75: Element | B75: UOM | C75: Element Cost/(g) | D75: Portion Used | E75: Value /pcs | F75: Major Step | G75: Units
E76: =IFERROR(C76*D76,0) -> 0 | F76: Recipe detail belum ditemukan pada ITEM SALES RECIPE / PDF yang tersedia.
E77: =IFERROR(C77*D77,0) -> 0
E78: =IFERROR(C78*D78,0) -> 0
E79: =IFERROR(C79*D79,0) -> 0
E80: =IFERROR(C80*D80,0) -> 0
E81: =IFERROR(C81*D81,0) -> 0
E82: =IFERROR(C82*D82,0) -> 0
E83: =IFERROR(C83*D83,0) -> 0
A84: Boxes, packaging, etc. | E84: 0
A85: Direct Cost | E85: =SUM(E76:E84) -> 0 | F85: Source: -
A86: Indirect Cost | E86: =E85*15% -> 0 | F86: Status: Recipe Pending
A87: Cost of Goods Sold (COGS) | E87: =E85+E86 -> 0
A88: Margin | E88: =IF(E90>0,E90-E87,0) -> 55000
A89: Div COGS | E89: =IFERROR(E87/E90,0) -> 0
A90: Selling Price | E90: 55000
A92: Yakiniku Hotdog
A93: Element | B93: UOM | C93: Element Cost/(g) | D93: Portion Used | E93: Value /pcs | F93: Major Step | G93: Units
A94: Brioche Hot Dog WIP | B94: PCS | C94: ='WIP FOOD'!$B$712 -> 2525.5416 | D94: 1 | E94: =IFERROR(C94*D94,0) -> 2525.5416 | F94: Recipe detail belum ditemukan pada ITEM SALES RECIPE / PDF yang tersedia.
A95: Beef marinasi yakiniku | B95: GR | C95: =IFERROR(VLOOKUP(A95,'Market List'!$B:$F,5,FALSE),0) -> 0 | D95: 30 | E95: =IFERROR(C95*D95,0) -> 0
A96: Onion Pickles | B96: GR | C96: =IFERROR(VLOOKUP(A96,'Market List'!$B:$F,5,FALSE),0) -> 91.76 | D96: 5 | E96: =IFERROR(C96*D96,0) -> 458.8
A97: Wijen Putih | B97: GR | C97: =IFERROR(VLOOKUP(A97,'Market List'!$B:$F,5,FALSE),0) -> 51.019 | D97: 1 | E97: =IFERROR(C97*D97,0) -> 51.019
A98: KOREANDER | C98: =IFERROR(VLOOKUP(A98,'Market List'!$B:$F,5,FALSE),0) -> 0 | E98: =IFERROR(C98*D98,0) -> 0
E99: =IFERROR(C99*D99,0) -> 0
E100: =IFERROR(C100*D100,0) -> 0
E101: =IFERROR(C101*D101,0) -> 0
A102: Boxes, packaging, etc. | E102: 0
A103: Direct Cost | E103: =SUM(E94:E102) -> 3035.3606 | F103: Source: -
A104: Indirect Cost | E104: =E103*15% -> 455.30408 | F104: Status: Recipe Pending
A105: Cost of Goods Sold (COGS) | E105: =E103+E104 -> 3490.6646
...

Sheet Agemono - Frying Section Stall
A1: Agemono - Frying Section Stall
A2: Chicken Namban
A3: Element | B3: UOM | C3: Element Cost/(g) | D3: Portion Used | E3: Value /pcs | F3: Major Step | G3: Units
A4: Soy Chicken WIP | B4: PCS | C4: ='WIP FOOD'!$B$543 -> 1225.7319 | D4: 3 | E4: =IFERROR(C4*D4,0) -> 3677.1956 | F4: Pastikan minyak deepfrying panas dengan temp 170 derajat celcius
A5: Egg Tartar WIP | B5: GR | C5: ='WIP FOOD'!$B$207 -> 45.457392 | D5: 40 | E5: =IFERROR(C5*D5,0) -> 1818.2957 | F5: siap kan tepung tapioka, masukan 3 potong ayam kedalam tapioka dan baluri secara menyeluruh dan tercover dengan cukup
A6: Namban Sauce WIP | B6: ML | C6: ='WIP FOOD'!$B$411 -> 37.76749 | D6: 50 | E6: =IFERROR(C6*D6,0) -> 1888.3745 | F6: masukan ayam yang sudah terbaluri tapioka, goreng selama kurang lebih 2 menit, lalu angkat ayam dan resting kurang lebih 1 menit
A7: Furikake WIP | B7: PINCHED | C7: ='WIP FOOD'!$B$218 -> 362.72092 | D7: 1 | E7: =IFERROR(C7*D7,0) -> 362.72092 | F7: setelah ayam resting, goreng kembali ayam kurang lebih selama 1,5 menit. setelah selesai langsung baluri ayam dengan sauce namban
A8: Daun Bawang slice | B8: PINCHED | C8: =IFERROR(VLOOKUP(A8,'Market List'!$B:$F,5,FALSE),0) -> 20 | D8: 1 | E8: =IFERROR(C8*D8,0) -> 20 | F8: plating 3 ayam tadi yang sudah di goreng dan terbaluti namban sauce, berikan eggtartar mayo dibagian atas ayamnya,berikan
A9: Tepung Tapioka | B9: GR | C9: =IFERROR(VLOOKUP(A9,'Market List'!$B:$F,5,FALSE),0) -> 16 | D9: 100 | E9: =IFERROR(C9*D9,0) -> 1600 | F9: taburan furikake dan daun bawang diatas eggtartar.
E10: =IFERROR(C10*D10,0) -> 0
E11: =IFERROR(C11*D11,0) -> 0
A12: Boxes, packaging, etc. | E12: 0
A13: Direct Cost | E13: =SUM(E4:E12) -> 9366.5867 | F13: Source: SULU-bdg FoodTesting.xlsx - ITEM SALES RECIPE
A14: Indirect Cost | E14: =E13*15% -> 1404.988 | F14: Status: Recipe Available
A15: Cost of Goods Sold (COGS) | E15: =E13+E14 -> 10771.575
A16: Margin | E16: =IF(E18>0,E18-E15,0) -> 29228.425
A17: Div COGS | E17: =IFERROR(E15/E18,0) -> 0.26928937
A18: Selling Price | E18: 40000
A20: Signature Torikaraage
A21: Element | B21: UOM | C21: Element Cost/(g) | D21: Portion Used | E21: Value /pcs | F21: Major Step | G21: Units
A22: Soy Chicken WIP | B22: PCS | C22: ='WIP FOOD'!$B$543 -> 1225.7319 | D22: 3 | E22: =IFERROR(C22*D22,0) -> 3677.1956 | F22: Pastikan minyak deepfrying panas dengan temp 170 derajat celcius
A23: Tapioka charcoal | B23: GR | C23: =IFERROR(VLOOKUP(A23,'Market List'!$B:$F,5,FALSE),0) -> 0 | D23: 100 | E23: =IFERROR(C23*D23,0) -> 0 | F23: siap kan tepung tapioka charcoal, masukan 3 potong ayam kedalam tapioka dan baluri secara menyeluruh dan tercover dengan cukup
A24: Okonomiyaki Sauce WIP | B24: GR | C24: ='WIP FOOD'!$B$452 -> 74.822755 | D24: 30 | E24: =IFERROR(C24*D24,0) -> 2244.6827 | F24: masukan ayam yang sudah terbaluri tapioka, goreng selama kurang lebih 2 menit, lalu angkat ayam dan resting kurang lebih 1 menit
A25: Furikake WIP | B25: GR | C25: ='WIP FOOD'!$B$218 -> 362.72092 | D25: 2 | E25: =IFERROR(C25*D25,0) -> 725.44184 | F25: setelah ayam resting, goreng kembali ayam kurang lebih selama 1,5 menit.
A26: Kol Kimchi WIP | B26: GR | C26: ='WIP FOOD'!$B$288 -> 29.984632 | D26: 30 | E26: =IFERROR(C26*D26,0) -> 899.53896 | F26: Plating karaage, berikan sauce okonomiyaki pada bagian ayam, taburi furikake, tempatkan kol kimchi setelah furikake, dan taburi daun bawang
A27: Daun Bawang | B27: GR | C27: =IFERROR(VLOOKUP(A27,'Market List'!$B:$F,5,FALSE),0) -> 20 | D27: 4 | E27: =IFERROR(C27*D27,0) -> 80
E28: =IFERROR(C28*D28,0) -> 0
E29: =IFERROR(C29*D29,0) -> 0
A30: Boxes, packaging, etc. | E30: 0
A31: Direct Cost | E31: =SUM(E22:E30) -> 7626.8591 | F31: Source: SULU-bdg FoodTesting.xlsx - ITEM SALES RECIPE
A32: Indirect Cost | E32: =E31*15% -> 1144.0289 | F32: Status: Recipe Available
A33: Cost of Goods Sold (COGS) | E33: =E31+E32 -> 8770.8879
A34: Margin | E34: =IF(E36>0,E36-E33,0) -> 31229.112
A35: Div COGS | E35: =IFERROR(E33/E36,0) -> 0.2192722
A36: Selling Price | E36: 40000
A38: Cheese Minched Katsu
A39: Element | B39: UOM | C39: Element Cost/(g) | D39: Portion Used | E39: Value /pcs | F39: Major Step | G39: Units
A40: Minched Beef WIP | B40: PCS | C40: ='WIP FOOD'!$B$372 -> 94.388263 | D40: 100 | E40: =IFERROR(C40*D40,0) -> 9438.8263 | F40: Goreng Minched katsu yang sudah diprep dengan suhu minyak standart 170 derajat kurang lebih 2 menit,lalu istirahatkan 1 menit dan goreng kembali di 2menit lagi
A41: Okonomiyaki Sauce WIP | B41: GR | C41: ='WIP FOOD'!$B$452 -> 74.822755 | D41: 30 | E41: =IFERROR(C41*D41,0) -> 2244.6827 | F41: angkat dan tiriskan minched katsunya.
A42: Wasabi mayo | B42: GR | C42: =IFERROR(VLOOKUP(A42,'Market List'!$B:$F,5,FALSE),0) -> 627.77778 | D42: 10 | E42: =IFERROR(C42*D42,0) -> 6277.7778 | F42: siapkan piring/rice paper, berikan wasabi mayo untuk bagian pertama, setelah itu minched katsunya, berikan sauce okonomiyaki, setelah itu furikake
A43: Kol Kimchi WIP | B43: GR | C43: ='WIP FOOD'!$B$288 -> 29.984632 | D43: 60 | E43: =IFERROR(C43*D43,0) -> 1799.0779 | F43: berikan kol kimchi nya di bagian paling atas minched katsu nya.
A44: Furikake WIP | B44: GR | C44: ='WIP FOOD'!$B$218 -> 362.72092 | D44: 2 | E44: =IFERROR(C44*D44,0) -> 725.44184
E45: =IFERROR(C45*D45,0) -> 0
E46: =IFERROR(C46*D46,0) -> 0
E47: =IFERROR(C47*D47,0) -> 0
A48: Boxes, packaging, etc. | E48: 0
A49: Direct Cost | E49: =SUM(E40:E48) -> 20485.807 | F49: Source: SULU-bdg FoodTesting.xlsx - ITEM SALES RECIPE
A50: Indirect Cost | E50: =E49*15% -> 3072.871 | F50: Status: Recipe Available
A51: Cost of Goods Sold (COGS) | E51: =E49+E50 -> 23558.677
A52: Margin | E52: =IF(E54>0,E54-E51,0) -> 26441.323
A53: Div COGS | E53: =IFERROR(E51/E54,0) -> 0.47117355
A54: Selling Price | E54: 50000
A56: Ebi Furai Signature
A57: Element | B57: UOM | C57: Element Cost/(g) | D57: Portion Used | E57: Value /pcs | F57: Major Step | G57: Units
A58: Ebi Furai/Katsu WIP | B58: PCS | C58: ='WIP FOOD'!$B$180 -> 10969.455 | D58: 2 | E58: =IFERROR(C58*D58,0) -> 21938.91 | F58: Pastikan minyak sudah standart temprature, masukan perlahan udang yang sudah di prep goreng hingga warna kecoklatan namun tidak gosong
A59: Cheese Sauce WIP | B59: GR | C59: ='WIP FOOD'!$B$62 -> 89.062036 | D59: 30 | E59: =IFERROR(C59*D59,0) -> 2671.8611 | F59: angkat dan tiriskan, di paper plate tuang cheese saucenya terlebih dahulu, tata udang tepat diatas sauce secara memanjang, taburi aonori
A60: Aonori | B60: GR | C60: =IFERROR(VLOOKUP(A60,'Market List'!$B:$F,5,FALSE),0) -> 496 | D60: 1 | E60: =IFERROR(C60*D60,0) -> 496 | F60: tempatkan lime sichimi pada bagian pojok paper plate
A61: Lime Sichimi | B61: GR | C61: =IFERROR(VLOOKUP(A61,'Market List'!$B:$F,5,FALSE),0) -> 351.66667 | D61: 5 | E61: =IFERROR(C61*D61,0) -> 1758.3333
E62: =IFERROR(C62*D62,0) -> 0
E63: =IFERROR(C63*D63,0) -> 0
E64: =IFERROR(C64*D64,0) -> 0
E65: =IFERROR(C65*D65,0) -> 0
A66: Boxes, packaging, etc. | E66: 0
A67: Direct Cost | E67: =SUM(E58:E66) -> 26865.104 | F67: Source: SULU-bdg FoodTesting.xlsx - ITEM SALES RECIPE
A68: Indirect Cost | E68: =E67*15% -> 4029.7656 | F68: Status: Recipe Available
A69: Cost of Goods Sold (COGS) | E69: =E67+E68 -> 30894.87
A70: Margin | E70: =IF(E72>0,E72-E69,0) -> 29105.13
A71: Div COGS | E71: =IFERROR(E69/E72,0) -> 0.51491449
A72: Selling Price | E72: 60000
A74: Tomorokoshi Ribs
A75: Element | B75: UOM | C75: Element Cost/(g) | D75: Portion Used | E75: Value /pcs | F75: Major Step | G75: Units
A76: Jagung Manis | B76: GR | C76: =IFERROR(VLOOKUP(A76,'Market List'!$B:$F,5,FALSE),0) -> 13 | D76: 90 | E76: =IFERROR(C76*D76,0) -> 1170 | F76: Goreng terlebih dahulu jagung yang sudah direbus cukup sebentar sekitar 1 menit, angkat dan tiriskan
A77: Sulu Spice WIP | B77: GR | C77: ='WIP FOOD'!$B$607 -> 203.89356 | D77: 2 | E77: =IFERROR(C77*D77,0) -> 407.78711 | F77: keadaan jagung baru diangkat dari gorengan, masukan jagung kedalam wadah stainless bowllangsung berikan butter aduk hingga rata,
A78: Butter unsalted | B78: GR | C78: =IFERROR(VLOOKUP(A78,'Market List'!$B:$F,5,FALSE),0) -> 140 | D78: 5 | E78: =IFERROR(C78*D78,0) -> 700 | F78: lalu torch jagung tujuan untuk mendapatkan warna gosong sedikit saja
A79: Aonori | B79: GR | C79: =IFERROR(VLOOKUP(A79,'Market List'!$B:$F,5,FALSE),0) -> 496 | D79: 1 | E79: =IFERROR(C79*D79,0) -> 496 | F79: lalu taburi sulu spice aduk hingga rata (Pastikan)
A80: Katsuobushi | B80: GR | C80: =IFERROR(VLOOKUP(A80,'Market List'!$B:$F,5,FALSE),0) -> 478.3989 | D80: 0.5 | E80: =IFERROR(C80*D80,0) -> 239.19945 | F80: Plating jagung disusun rapih, taburi aonori dan berikan topping terakhir katsuobushi nya
E81: =IFERROR(C81*D81,0) -> 0
E82: =IFERROR(C82*D82,0) -> 0
E83: =IFERROR(C83*D83,0) -> 0
A84: Boxes, packaging, etc. | E84: 0
A85: Direct Cost | E85: =SUM(E76:E84) -> 3012.9866 | F85: Source: SULU-bdg FoodTesting.xlsx - ITEM SALES RECIPE
A86: Indirect Cost | E86: =E85*15% -> 451.94798 | F86: Status: Recipe Available
A87: Cost of Goods Sold (COGS) | E87: =E85+E86 -> 3464.9345
A88: Margin | E88: =IF(E90>0,E90-E87,0) -> 21535.065
A89: Div COGS | E89: =IFERROR(E87/E90,0) -> 0.13859738
A90: Selling Price | E90: 25000
A92: SFC Signature
A93: Element | B93: UOM | C93: Element Cost/(g) | D93: Portion Used | E93: Value /pcs | F93: Major Step | G93: Units
A94: SFC Marinated WIP | B94: PCS | C94: =IFERROR(VLOOKUP(A94,'Market List'!$B:$F,5,FALSE),0) -> 2004.9029 | D94: 2 | E94: =IFERROR(C94*D94,0) -> 4009.8057 | F94: Pastikan minyak deepfrying panas dengan temp 170 derajat celcius
A95: Dry Flour Dry Mix WIP | B95: GR | C95: =IFERROR(VLOOKUP(A95,'Market List'!$B:$F,5,FALSE),0) -> 20.208939 | D95: 30 | E95: =IFERROR(C95*D95,0) -> 606.26816 | F95: siap kan mix flour, masukan ayam kedalam tepung dan baluri secara menyeluruh dan tercover dengan cukup,lalu celupkan kedalam air es kurang lebih 1 menit
A96: Sulu Spice WIP | B96: GR | C96: ='WIP FOOD'!$B$607 -> 203.89356 | D96: 2 | E96: =IFERROR(C96*D96,0) -> 407.78711 | F96: setelah dari air es, masukan kembali kedalam mix flour dan di tekan tekan secara perlahan dan pastikan tepung berbentuk kriting dan ayam terbaluri dengan baik
A97: Aonori | B97: GR | C97: =IFERROR(VLOOKUP(A97,'Market List'!$B:$F,5,FALSE),0) -> 496 | D97: 1 | E97: =IFERROR(C97*D97,0) -> 496 | F97: goreng ayam selama kurang lebih 3 menit pertama, lalu resting 2 menit, lalu kembali goreng dengan waktu 2-3 menit, angkat lalu tiriskan ayam
A98: lemon | B98: GR | C98: =IFERROR(VLOOKUP(A98,'Market List'!$B:$F,5,FALSE),0) -> 53 | D98: 5 | E98: =IFERROR(C98*D98,0) -> 265 | F98: tata ayam di piring, taburi sulu spice dan aonori, berikan irisan lemon di bagian sisi ayam. untuk chili oil dan cheese sauce di hidangkan secara terpisah di mangkuk kecil
A99: Cheese Sauce WIP | B99: GR | C99: ='WIP FOOD'!$B$62 -> 89.062036 | D99: 20 | E99: =IFERROR(C99*D99,0) -> 1781.2407
A100: Chili Oil WIP | B100: GR | C100: ='WIP FOOD'!$B$72 -> 120.11858 | D100: 20 | E100: =IFERROR(C100*D100,0) -> 2402.3715
E101: =IFERROR(C101*D101,0) -> 0
A102: Boxes, packaging, etc. | E102: 0
A103: Direct Cost | E103: =SUM(E94:E102) -> 9968.4732 | F103: Source: SULU-bdg FoodTesting.xlsx - ITEM SALES RECIPE
A104: Indirect Cost | E104: =E103*15% -> 1495.271 | F104: Status: Recipe Available
A105: Cost of Goods Sold (COGS) | E105: =E103+E104 -> 11463.744
...

Sheet Rice bowl Stall
A1: Rice bowl Stall
A2: Gyutan Donburi
A3: Element | B3: UOM | C3: Element Cost/(g) | D3: Portion Used | E3: Value /pcs | F3: Major Step | G3: Units
A4: Gyutan Marinasi | B4: GR | C4: =IFERROR(VLOOKUP(A4,'Market List'!$B:$F,5,FALSE),0) -> 0 | D4: 80 | E4: =IFERROR(C4*D4,0) -> 0 | F4: Panaskan teflon terlebih dahulu, masukan butter dan bawang bombay tumis terlebih dahulu, masukan gyutan yang sudah dimarinasi sauce yakiniku, lalu masak hingga matang
A5: Rice | B5: GR | C5: =IFERROR(VLOOKUP(A5,'Market List'!$B:$F,5,FALSE),0) -> 41.26 | D5: 160 | E5: =IFERROR(C5*D5,0) -> 6601.6 | F5: namun dipastikan tidak gosong dari bagian sauce nya gunakan api sedang dan terus di tumis.
A6: Furikake WIP | B6: GR | C6: ='WIP FOOD'!$B$218 -> 362.72092 | D6: 3 | E6: =IFERROR(C6*D6,0) -> 1088.1628 | F6: tuang nasi kedalam mangkuk, taburi furikake terlebih dahulu, tata rapih gyutan yang sudah dimasak, tempatkan onsen egg dibagian tengahnya, taburi daun bawang pada final
A7: Telur | B7: PCS | C7: =IFERROR(VLOOKUP(A7,'Market List'!$B:$F,5,FALSE),0) -> 1785.7143 | D7: 1 | E7: =IFERROR(C7*D7,0) -> 1785.7143 | F7: Untuk chili oilnya diberikan on the side
A8: Daun Bawang | B8: GR | C8: =IFERROR(VLOOKUP(A8,'Market List'!$B:$F,5,FALSE),0) -> 20 | D8: 3 | E8: =IFERROR(C8*D8,0) -> 60
A9: Chili Oil WIP | B9: GR | C9: ='WIP FOOD'!$B$72 -> 120.11858 | D9: 15 | E9: =IFERROR(C9*D9,0) -> 1801.7786
A10: Butter | B10: GR | C10: =IFERROR(VLOOKUP(A10,'Market List'!$B:$F,5,FALSE),0) -> 140 | D10: 8 | E10: =IFERROR(C10*D10,0) -> 1120
A11: Bawang Bombay | B11: GR | C11: =IFERROR(VLOOKUP(A11,'Market List'!$B:$F,5,FALSE),0) -> 35 | D11: 8 | E11: =IFERROR(C11*D11,0) -> 280
A12: Boxes, packaging, etc. | E12: 0
A13: Direct Cost | E13: =SUM(E4:E12) -> 12737.256 | F13: Source: SULU-bdg FoodTesting.xlsx - ITEM SALES RECIPE
A14: Indirect Cost | E14: =E13*15% -> 1910.5884 | F14: Status: Recipe Available
A15: Cost of Goods Sold (COGS) | E15: =E13+E14 -> 14647.844
A16: Margin | E16: =IF(E18>0,E18-E15,0) -> 60352.156
A17: Div COGS | E17: =IFERROR(E15/E18,0) -> 0.19530459
A18: Selling Price | E18: 75000
A20: Beef Yakiniku Bowl
A21: Element | B21: UOM | C21: Element Cost/(g) | D21: Portion Used | E21: Value /pcs | F21: Major Step | G21: Units
A22: Beef marinasi yakiniku | B22: GR | C22: =IFERROR(VLOOKUP(A22,'Market List'!$B:$F,5,FALSE),0) -> 0 | D22: 80 | E22: =IFERROR(C22*D22,0) -> 0 | F22: Panaskan teflon terlebih dahulu, masukan butter dan bawang bombay tumis terlebih dahulu, masukan beef yang sudah dimarinasi sauce yakiniku, lalu masak hingga matang
A23: Rice | B23: GR | C23: =IFERROR(VLOOKUP(A23,'Market List'!$B:$F,5,FALSE),0) -> 41.26 | D23: 160 | E23: =IFERROR(C23*D23,0) -> 6601.6 | F23: namun dipastikan tidak gosong dari bagian sauce nya gunakan api sedang dan terus di tumis.
A24: Furikake WIP | B24: GR | C24: ='WIP FOOD'!$B$218 -> 362.72092 | D24: 3 | E24: =IFERROR(C24*D24,0) -> 1088.1628 | F24: tuang nasi kedalam mangkuk, taburi furikake terlebih dahulu, tata rapih gyutan yang sudah dimasak, tempatkan onsen egg dibagian tengahnya, taburi daun bawang pada final
A25: Telur | B25: PCS | C25: =IFERROR(VLOOKUP(A25,'Market List'!$B:$F,5,FALSE),0) -> 1785.7143 | D25: 1 | E25: =IFERROR(C25*D25,0) -> 1785.7143 | F25: Untuk chili oilnya diberikan on the side
A26: Daun Bawang | B26: GR | C26: =IFERROR(VLOOKUP(A26,'Market List'!$B:$F,5,FALSE),0) -> 20 | D26: 3 | E26: =IFERROR(C26*D26,0) -> 60
A27: Chili Oil WIP | B27: GR | C27: ='WIP FOOD'!$B$72 -> 120.11858 | D27: 15 | E27: =IFERROR(C27*D27,0) -> 1801.7786
A28: Butter | B28: GR | C28: =IFERROR(VLOOKUP(A28,'Market List'!$B:$F,5,FALSE),0) -> 140 | D28: 8 | E28: =IFERROR(C28*D28,0) -> 1120
A29: Bawang Bombay | B29: GR | C29: =IFERROR(VLOOKUP(A29,'Market List'!$B:$F,5,FALSE),0) -> 35 | D29: 8 | E29: =IFERROR(C29*D29,0) -> 280
A30: Boxes, packaging, etc. | E30: 0
A31: Direct Cost | E31: =SUM(E22:E30) -> 12737.256 | F31: Source: SULU-bdg FoodTesting.xlsx - ITEM SALES RECIPE
A32: Indirect Cost | E32: =E31*15% -> 1910.5884 | F32: Status: Recipe Available
A33: Cost of Goods Sold (COGS) | E33: =E31+E32 -> 14647.844
A34: Margin | E34: =IF(E36>0,E36-E33,0) -> 55352.156
A35: Div COGS | E35: =IFERROR(E33/E36,0) -> 0.20925492
A36: Selling Price | E36: 70000
A38: Smoked Duck Donburi
A39: Element | B39: UOM | C39: Element Cost/(g) | D39: Portion Used | E39: Value /pcs | F39: Major Step | G39: Units
A40: Smocked Duck | B40: GR | C40: =IFERROR(VLOOKUP(A40,'Market List'!$B:$F,5,FALSE),0) -> 254.5 | D40: 80 | E40: =IFERROR(C40*D40,0) -> 20360 | F40: Panaskan teflon terlebih dahulu, masukan butter dan bawang bombay tumis terlebih dahulu, masukan bebek yang sudah di slice, berikan sauce yakiniku, lalu masak hingga matang
A41: Rice | B41: GR | C41: =IFERROR(VLOOKUP(A41,'Market List'!$B:$F,5,FALSE),0) -> 41.26 | D41: 160 | E41: =IFERROR(C41*D41,0) -> 6601.6 | F41: namun dipastikan tidak gosong dari bagian sauce nya gunakan api sedang dan terus di tumis.
A42: Furikake WIP | B42: GR | C42: ='WIP FOOD'!$B$218 -> 362.72092 | D42: 3 | E42: =IFERROR(C42*D42,0) -> 1088.1628 | F42: tuang nasi kedalam mangkuk, taburi furikake terlebih dahulu, tata rapih smoked duck yang sudah dimasak, tempatkan onsen egg dibagian tengahnya, taburi daun bawang pada final
A43: Telur | B43: PCS | C43: =IFERROR(VLOOKUP(A43,'Market List'!$B:$F,5,FALSE),0) -> 1785.7143 | D43: 1 | E43: =IFERROR(C43*D43,0) -> 1785.7143 | F43: Untuk chili oilnya diberikan on the side
A44: Daun Bawang | B44: GR | C44: =IFERROR(VLOOKUP(A44,'Market List'!$B:$F,5,FALSE),0) -> 20 | D44: 3 | E44: =IFERROR(C44*D44,0) -> 60 | F44: NOODLES STALL
A45: Chili Oil WIP | B45: GR | C45: ='WIP FOOD'!$B$72 -> 120.11858 | D45: 15 | E45: =IFERROR(C45*D45,0) -> 1801.7786
A46: Butter | B46: GR | C46: =IFERROR(VLOOKUP(A46,'Market List'!$B:$F,5,FALSE),0) -> 140 | D46: 8 | E46: =IFERROR(C46*D46,0) -> 1120
A47: Bawang Bombay | B47: GR | C47: =IFERROR(VLOOKUP(A47,'Market List'!$B:$F,5,FALSE),0) -> 35 | D47: 8 | E47: =IFERROR(C47*D47,0) -> 280
A48: Boxes, packaging, etc. | E48: 0
A49: Direct Cost | E49: =SUM(E40:E48) -> 33097.256 | F49: Source: SULU-bdg FoodTesting.xlsx - ITEM SALES RECIPE
A50: Indirect Cost | E50: =E49*15% -> 4964.5884 | F50: Status: Recipe Available
A51: Cost of Goods Sold (COGS) | E51: =E49+E50 -> 38061.844
A52: Margin | E52: =IF(E54>0,E54-E51,0) -> 41938.156
A53: Div COGS | E53: =IFERROR(E51/E54,0) -> 0.47577305
A54: Selling Price | E54: 80000

Sheet Ramen - Noodles Stall
A1: Ramen - Noodles Stall
A2: Aka Miso Ramen
A3: Element | B3: UOM | C3: Element Cost/(g) | D3: Portion Used | E3: Value /pcs | F3: Major Step | G3: Units
A4: Ramen | B4: GR | C4: =IFERROR(VLOOKUP(A4,'Market List'!$B:$F,5,FALSE),0) -> 28.070175 | D4: 80 | E4: =IFERROR(C4*D4,0) -> 2245.614 | F4: Pastikan boiler mendidih dengan sempurna, masukan ramen noodles dan berikan timer 1 menit. siapkan mangkok ramen, masukan garlic oil dan lada
A5: Miso Soup WIP | B5: ML | C5: ='WIP FOOD'!$B$391 -> 8.7389381 | D5: 240 | E5: =IFERROR(C5*D5,0) -> 2097.3451 | F5: panaskan miso soup menggunakan sauce pot dan pastikan mendidih maksimal, matikan kompor, tuang sesuai takaran yang dibutuhkan, lalu angkat ramen kalau sudah selesai timernya
A6: Garlic Oil | B6: GR | C6: =IFERROR(VLOOKUP(A6,'Market List'!$B:$F,5,FALSE),0) -> 86 | D6: 1 | E6: =IFERROR(C6*D6,0) -> 86 | F6: kocok kocok dulu untuk membuang sisa air dari boiler tadi, dan masukan ramen kedalam mangkoknya. berikan semua topping dengan cara ditata rapih dengan posisi menggunung
A7: Lada Putih | B7: GR | C7: =IFERROR(VLOOKUP(A7,'Market List'!$B:$F,5,FALSE),0) -> 200 | D7: 0.5 | E7: =IFERROR(C7*D7,0) -> 100 | F7: namun tidak menutupi satu sama lain topping nya
A8: Chili Oil WIP | B8: GR | C8: ='WIP FOOD'!$B$72 -> 120.11858 | D8: 35 | E8: =IFERROR(C8*D8,0) -> 4204.1502
A9: Soy Chicken WIP | B9: GR | C9: ='WIP FOOD'!$B$543 -> 1225.7319 | D9: 28 | E9: =IFERROR(C9*D9,0) -> 34320.492
A10: Smoked Duck Slice | B10: GR | C10: =IFERROR(VLOOKUP(A10,'Market List'!$B:$F,5,FALSE),0) -> 254.5 | D10: 10 | E10: =IFERROR(C10*D10,0) -> 2545 | F10: Prep: Grill; 1 slice.
A11: Jukut | B11: GR | C11: =IFERROR(VLOOKUP(A11,'Market List'!$B:$F,5,FALSE),0) -> 0 | D11: 4 | E11: =IFERROR(C11*D11,0) -> 0
A12: Daun Bawang | B12: GR | C12: =IFERROR(VLOOKUP(A12,'Market List'!$B:$F,5,FALSE),0) -> 20 | D12: 4 | E12: =IFERROR(C12*D12,0) -> 80
A13: Telur Omega | B13: BUTIR | C13: =IFERROR(VLOOKUP(A13,'Market List'!$B:$F,5,FALSE),0) -> 3600 | D13: 0.5 | E13: =IFERROR(C13*D13,0) -> 1800
A14: Boxes, packaging, etc. | E14: 0
A15: Direct Cost | E15: =SUM(E4:E14) -> 47478.602 | F15: Source: SULU-bdg FoodTesting.xlsx - ITEM SALES RECIPE
A16: Indirect Cost | E16: =E15*15% -> 7121.7902 | F16: Status: Recipe Available
A17: Cost of Goods Sold (COGS) | E17: =E15+E16 -> 54600.392
A18: Margin | E18: =IF(E20>0,E20-E17,0) -> 0
A19: Div Margin | E19: =IFERROR(E17/E20,0) -> 0
A20: Selling Price
A22: Spicy Goma Ramen
A23: Element | B23: UOM | C23: Element Cost/(g) | D23: Portion Used | E23: Value /pcs | F23: Major Step | G23: Units
A24: Ramen | B24: GR | C24: =IFERROR(VLOOKUP(A24,'Market List'!$B:$F,5,FALSE),0) -> 28.070175 | D24: 80 | E24: =IFERROR(C24*D24,0) -> 2245.614 | F24: Pastikan boiler mendidih dengan sempurna, masukan ramen noodles dan berikan timer 1 menit. siapkan mangkok ramen, tuang goma ramen sauce,garlic oil,royco dan lada
A25: Chicken Broth | B25: ML | C25: =IFERROR(VLOOKUP(A25,'Market List'!$B:$F,5,FALSE),0) -> 0 | D25: 240 | E25: =IFERROR(C25*D25,0) -> 0 | F25: panaskan broth menggunakan sauce pot dan pastikan mendidih maksimal, matikan kompor, tuang sesuai takaran yang dibutuhkan, lalu angkat ramen kalau sudah selesai timernya
A26: Spicy Goma Sauce WIP | B26: ML | C26: ='WIP FOOD'!$B$553 -> 45.940387 | D26: 30 | E26: =IFERROR(C26*D26,0) -> 1378.2116 | F26: kocok kocok dulu untuk membuang sisa air dari boiler tadi, dan masukan ramen kedalam mangkoknya. berikan semua topping dengan cara ditata rapih dengan posisi menggunung
A27: Royco | B27: GR | C27: =IFERROR(VLOOKUP(A27,'Market List'!$B:$F,5,FALSE),0) -> 43.181818 | D27: 1 | E27: =IFERROR(C27*D27,0) -> 43.181818 | F27: namun tidak menutupi satu sama lain topping nya
A28: Garlic Oil | B28: GR | C28: =IFERROR(VLOOKUP(A28,'Market List'!$B:$F,5,FALSE),0) -> 86 | D28: 1 | E28: =IFERROR(C28*D28,0) -> 86
A29: Lada Putih | B29: GR | C29: =IFERROR(VLOOKUP(A29,'Market List'!$B:$F,5,FALSE),0) -> 200 | D29: 0.5 | E29: =IFERROR(C29*D29,0) -> 100
A30: Smoked Duck Slice | B30: GR | C30: =IFERROR(VLOOKUP(A30,'Market List'!$B:$F,5,FALSE),0) -> 254.5 | D30: 30 | E30: =IFERROR(C30*D30,0) -> 7635 | F30: Prep: Grill; 3 slice.
A31: Jukut | B31: GR | C31: =IFERROR(VLOOKUP(A31,'Market List'!$B:$F,5,FALSE),0) -> 0 | D31: 4 | E31: =IFERROR(C31*D31,0) -> 0
A32: Daun Bawang | B32: GR | C32: =IFERROR(VLOOKUP(A32,'Market List'!$B:$F,5,FALSE),0) -> 20 | D32: 4 | E32: =IFERROR(C32*D32,0) -> 80
A33: Telur Omega | B33: BUTIR | C33: =IFERROR(VLOOKUP(A33,'Market List'!$B:$F,5,FALSE),0) -> 3600 | D33: 0.5 | E33: =IFERROR(C33*D33,0) -> 1800
A34: Chili Oil WIP | B34: GR | C34: ='WIP FOOD'!$B$72 -> 120.11858 | D34: 35 | E34: =IFERROR(C34*D34,0) -> 4204.1502
A35: Boxes, packaging, etc. | E35: 0
A36: Direct Cost | E36: =SUM(E24:E35) -> 17572.158 | F36: Source: SULU-bdg FoodTesting.xlsx - ITEM SALES RECIPE
A37: Indirect Cost | E37: =E36*15% -> 2635.8236 | F37: Status: Recipe Available
A38: Cost of Goods Sold (COGS) | E38: =E36+E37 -> 20207.981
A39: Margin | E39: =IF(E41>0,E41-E38,0) -> 0
A40: Div Margin | E40: =IFERROR(E38/E41,0) -> 0
A41: Selling Price
A43: Signature Shoyu Ramen
A44: Element | B44: UOM | C44: Element Cost/(g) | D44: Portion Used | E44: Value /pcs | F44: Major Step | G44: Units
A45: Ramen | B45: GR | C45: =IFERROR(VLOOKUP(A45,'Market List'!$B:$F,5,FALSE),0) -> 28.070175 | D45: 80 | E45: =IFERROR(C45*D45,0) -> 2245.614 | F45: Pastikan boiler mendidih dengan sempurna, masukan ramen noodles dan berikan timer 1 menit. siapkan mangkok ramen, tuang shoyu ramen sauce,garlic oil,royco dan lada
A46: Chicken Broth | B46: ML | C46: =IFERROR(VLOOKUP(A46,'Market List'!$B:$F,5,FALSE),0) -> 0 | D46: 240 | E46: =IFERROR(C46*D46,0) -> 0 | F46: panaskan broth menggunakan sauce pot dan pastikan mendidih maksimal, matikan kompor, tuang sesuai takaran yang dibutuhkan, lalu angkat ramen kalau sudah selesai timernya
A47: Shoyu Ramen Sauce | B47: ML | C47: =IFERROR(VLOOKUP(A47,'Market List'!$B:$F,5,FALSE),0) -> 0 | D47: 30 | E47: =IFERROR(C47*D47,0) -> 0 | F47: kocok kocok dulu untuk membuang sisa air dari boiler tadi, dan masukan ramen kedalam mangkoknya. berikan semua topping dengan cara ditata rapih dengan posisi menggunung
A48: Royco | B48: GR | C48: =IFERROR(VLOOKUP(A48,'Market List'!$B:$F,5,FALSE),0) -> 43.181818 | D48: 1 | E48: =IFERROR(C48*D48,0) -> 43.181818 | F48: namun tidak menutupi satu sama lain topping nya
A49: Garlic Oil | B49: GR | C49: =IFERROR(VLOOKUP(A49,'Market List'!$B:$F,5,FALSE),0) -> 86 | D49: 1 | E49: =IFERROR(C49*D49,0) -> 86
A50: Lada Putih | B50: GR | C50: =IFERROR(VLOOKUP(A50,'Market List'!$B:$F,5,FALSE),0) -> 200 | D50: 0.5 | E50: =IFERROR(C50*D50,0) -> 100
A51: Marinasi Beef (Noodles) WIP | B51: GR | C51: ='WIP FOOD'!$B$298 -> 86.808706 | D51: 30 | E51: =IFERROR(C51*D51,0) -> 2604.2612
A52: Jukut | B52: GR | C52: =IFERROR(VLOOKUP(A52,'Market List'!$B:$F,5,FALSE),0) -> 0 | D52: 4 | E52: =IFERROR(C52*D52,0) -> 0
A53: Daun Bawang | B53: GR | C53: =IFERROR(VLOOKUP(A53,'Market List'!$B:$F,5,FALSE),0) -> 20 | D53: 4 | E53: =IFERROR(C53*D53,0) -> 80
A54: Telur Omega | B54: BUTIR | C54: =IFERROR(VLOOKUP(A54,'Market List'!$B:$F,5,FALSE),0) -> 3600 | D54: 0.5 | E54: =IFERROR(C54*D54,0) -> 1800
A55: Boxes, packaging, etc. | E55: 0
A56: Direct Cost | E56: =SUM(E45:E55) -> 6959.057 | F56: Source: SULU-bdg FoodTesting.xlsx - ITEM SALES RECIPE
A57: Indirect Cost | E57: =E56*15% -> 1043.8586 | F57: Status: Recipe Available
A58: Cost of Goods Sold (COGS) | E58: =E56+E57 -> 8002.9156
A59: Margin | E59: =IF(E61>0,E61-E58,0) -> 0
A60: Div Margin | E60: =IFERROR(E58/E61,0) -> 0
A61: Selling Price
A63: Beef Abura Soba
A64: Element | B64: UOM | C64: Element Cost/(g) | D64: Portion Used | E64: Value /pcs | F64: Major Step | G64: Units
A65: Ramen | B65: GR | C65: =IFERROR(VLOOKUP(A65,'Market List'!$B:$F,5,FALSE),0) -> 28.070175 | D65: 80 | E65: =IFERROR(C65*D65,0) -> 2245.614 | F65: Pastikan boiler mendidih dengan sempurna, masukan ramen noodles dan berikan timer 1 menit. siapkan sauce pot , tuang mazesoba sauce,garlic oil,royco,curry , lada dan butter
A66: Mazesoba Sauce WIP | B66: GR | C66: ='WIP FOOD'!$B$349 -> 119.37364 | D66: 40 | E66: =IFERROR(C66*D66,0) -> 4774.9456 | F66: Angkat ramen, masukan ke sauce pot yang sudah ada saucenya, aduk secara gentle dan merata bagus, tuang ke mangkuk secara rapih (center)
A67: Garlic Oil | B67: GR | C67: =IFERROR(VLOOKUP(A67,'Market List'!$B:$F,5,FALSE),0) -> 86 | D67: 1 | E67: =IFERROR(C67*D67,0) -> 86 | F67: tata rapih semua topping dan tidak menutupi topping satu sama lain.
A68: Lada Putih | B68: GR | C68: =IFERROR(VLOOKUP(A68,'Market List'!$B:$F,5,FALSE),0) -> 200 | D68: 0.5 | E68: =IFERROR(C68*D68,0) -> 100
A69: Royco | B69: GR | C69: =IFERROR(VLOOKUP(A69,'Market List'!$B:$F,5,FALSE),0) -> 43.181818 | D69: 1 | E69: =IFERROR(C69*D69,0) -> 43.181818
A70: Curry Powder | B70: PINCHED | C70: =IFERROR(VLOOKUP(A70,'Market List'!$B:$F,5,FALSE),0) -> 136 | D70: 1 | E70: =IFERROR(C70*D70,0) -> 136
A71: Truffle Oil | B71: GR | C71: =IFERROR(VLOOKUP(A71,'Market List'!$B:$F,5,FALSE),0) -> 971.8 | D71: 2 | E71: =IFERROR(C71*D71,0) -> 1943.6
A72: Butter | B72: GR | C72: =IFERROR(VLOOKUP(A72,'Market List'!$B:$F,5,FALSE),0) -> 140 | D72: 10 | E72: =IFERROR(C72*D72,0) -> 1400
A73: Smoked Beef | B73: GR | C73: =IFERROR(VLOOKUP(A73,'Market List'!$B:$F,5,FALSE),0) -> 90 | D73: 30 | E73: =IFERROR(C73*D73,0) -> 2700 | F73: Prep: Potong-potong.
A74: Jukut | B74: GR | C74: =IFERROR(VLOOKUP(A74,'Market List'!$B:$F,5,FALSE),0) -> 0 | D74: 4 | E74: =IFERROR(C74*D74,0) -> 0
A75: Cucumber Pickles WIP | B75: GR | C75: ='WIP FOOD'!$B$119 -> 13.97688 | D75: 4 | E75: =IFERROR(C75*D75,0) -> 55.907518
A76: Telur Omega | B76: BUTIR | C76: =IFERROR(VLOOKUP(A76,'Market List'!$B:$F,5,FALSE),0) -> 3600 | D76: 0.5 | E76: =IFERROR(C76*D76,0) -> 1800
A77: Sawi Kimchi WIP | B77: GR | C77: ='WIP FOOD'!$B$498 -> 26.065102 | D77: 40 | E77: =IFERROR(C77*D77,0) -> 1042.6041
A78: Garlic Chip | B78: GR | C78: =IFERROR(VLOOKUP(A78,'Market List'!$B:$F,5,FALSE),0) -> 1000 | D78: 1 | E78: =IFERROR(C78*D78,0) -> 1000
A79: Boxes, packaging, etc. | E79: 0
A80: Direct Cost | E80: =SUM(E65:E79) -> 17327.853 | F80: Source: SULU-bdg FoodTesting.xlsx - ITEM SALES RECIPE
A81: Indirect Cost | E81: =E80*15% -> 2599.178 | F81: Status: Recipe Available
A82: Cost of Goods Sold (COGS) | E82: =E80+E81 -> 19927.031
A83: Margin | E83: =IF(E85>0,E85-E82,0) -> 0
A84: Div Margin | E84: =IFERROR(E82/E85,0) -> 0
A85: Selling Price
A87: Smoked Duck Abura Soba
A88: Element | B88: UOM | C88: Element Cost/(g) | D88: Portion Used | E88: Value /pcs | F88: Major Step | G88: Units
A89: Ramen | B89: GR | C89: =IFERROR(VLOOKUP(A89,'Market List'!$B:$F,5,FALSE),0) -> 28.070175 | D89: 80 | E89: =IFERROR(C89*D89,0) -> 2245.614 | F89: Pastikan boiler mendidih dengan sempurna, masukan ramen noodles dan berikan timer 1 menit. siapkan sauce pot , tuang mazesoba sauce,garlic oil,royco,curry , lada dan butter
A90: Mazesoba Sauce WIP | B90: GR | C90: ='WIP FOOD'!$B$349 -> 119.37364 | D90: 40 | E90: =IFERROR(C90*D90,0) -> 4774.9456 | F90: Angkat ramen, masukan ke sauce pot yang sudah ada saucenya, aduk secara gentle dan merata bagus, tuang ke mangkuk secara rapih (center)
A91: Garlic Oil | B91: GR | C91: =IFERROR(VLOOKUP(A91,'Market List'!$B:$F,5,FALSE),0) -> 86 | D91: 1 | E91: =IFERROR(C91*D91,0) -> 86 | F91: tata rapih semua topping dan tidak menutupi topping satu sama lain.
A92: Lada Putih | B92: GR | C92: =IFERROR(VLOOKUP(A92,'Market List'!$B:$F,5,FALSE),0) -> 200 | D92: 0.5 | E92: =IFERROR(C92*D92,0) -> 100
A93: Royco | B93: GR | C93: =IFERROR(VLOOKUP(A93,'Market List'!$B:$F,5,FALSE),0) -> 43.181818 | D93: 1 | E93: =IFERROR(C93*D93,0) -> 43.181818
A94: Curry Powder | B94: PINCHED | C94: =IFERROR(VLOOKUP(A94,'Market List'!$B:$F,5,FALSE),0) -> 136 | D94: 1 | E94: =IFERROR(C94*D94,0) -> 136
A95: Truffle Oil | B95: GR | C95: =IFERROR(VLOOKUP(A95,'Market List'!$B:$F,5,FALSE),0) -> 971.8 | D95: 2 | E95: =IFERROR(C95*D95,0) -> 1943.6
A96: Butter | B96: GR | C96: =IFERROR(VLOOKUP(A96,'Market List'!$B:$F,5,FALSE),0) -> 140 | D96: 10 | E96: =IFERROR(C96*D96,0) -> 1400
A97: Smoked Duck Slice | B97: GR | C97: =IFERROR(VLOOKUP(A97,'Market List'!$B:$F,5,FALSE),0) -> 254.5 | D97: 30 | E97: =IFERROR(C97*D97,0) -> 7635 | F97: Prep: Grill; 3 slice.
A98: Jukut | B98: GR | C98: =IFERROR(VLOOKUP(A98,'Market List'!$B:$F,5,FALSE),0) -> 0 | D98: 4 | E98: =IFERROR(C98*D98,0) -> 0
A99: Cucumber Pickles WIP | B99: GR | C99: ='WIP FOOD'!$B$119 -> 13.97688 | D99: 4 | E99: =IFERROR(C99*D99,0) -> 55.907518
A100: Telur Omega | B100: BUTIR | C100: =IFERROR(VLOOKUP(A100,'Market List'!$B:$F,5,FALSE),0) -> 3600 | D100: 0.5 | E100: =IFERROR(C100*D100,0) -> 1800
A101: Sawi Kimchi WIP | B101: GR | C101: ='WIP FOOD'!$B$498 -> 26.065102 | D101: 40 | E101: =IFERROR(C101*D101,0) -> 1042.6041
A102: Garlic Chip | B102: GR | C102: =IFERROR(VLOOKUP(A102,'Market List'!$B:$F,5,FALSE),0) -> 1000 | D102: 1 | E102: =IFERROR(C102*D102,0) -> 1000
A103: Boxes, packaging, etc. | E103: 0
A104: Direct Cost | E104: =SUM(E89:E103) -> 22262.853 | F104: Source: SULU-bdg FoodTesting.xlsx - ITEM SALES RECIPE
...

Sheet Udon - Noodles Stall
A1: Udon - Noodles Stall
A2: Udon Carbonara
A3: Element | B3: UOM | C3: Element Cost/(g) | D3: Portion Used | E3: Value /pcs | F3: Major Step | G3: Units
A4: Udon | B4: GR | C4: =IFERROR(VLOOKUP(A4,'Market List'!$B:$F,5,FALSE),0) -> 394.4 | D4: 180 | E4: =IFERROR(C4*D4,0) -> 70992 | F4: Pastikan boiler mendidih dengan sempurna, masukan ramen noodles dan berikan timer 1 menit. siapkan sauce pot , tuang mazesoba sauce,garlic oil,royco,curry , lada dan butter
A5: Bawang Bombay | C5: =IFERROR(VLOOKUP(A5,'Market List'!$B:$F,5,FALSE),0) -> 35 | E5: =IFERROR(C5*D5,0) -> 0 | F5: Prep: Dice. Angkat ramen, masukan ke sauce pot yang sudah ada saucenya, aduk secara gentle dan merata bagus, tuang ke mangkuk secara rapih (center)
A6: Butter | C6: =IFERROR(VLOOKUP(A6,'Market List'!$B:$F,5,FALSE),0) -> 140 | E6: =IFERROR(C6*D6,0) -> 0 | F6: tata rapih semua topping dan tidak menutupi topping satu sama lain.
A7: Cooking Cream | C7: =IFERROR(VLOOKUP(A7,'Market List'!$B:$F,5,FALSE),0) -> 69 | E7: =IFERROR(C7*D7,0) -> 0
E8: =IFERROR(C8*D8,0) -> 0
E9: =IFERROR(C9*D9,0) -> 0
E10: =IFERROR(C10*D10,0) -> 0
E11: =IFERROR(C11*D11,0) -> 0
A12: Boxes, packaging, etc. | E12: 0
A13: Direct Cost | E13: =SUM(E4:E12) -> 70992 | F13: Source: SULU-bdg FoodTesting.xlsx - ITEM SALES RECIPE
A14: Indirect Cost | E14: =E13*15% -> 10648.8 | F14: Status: Recipe Available
A15: Cost of Goods Sold (COGS) | E15: =E13+E14 -> 81640.8
A16: Margin | E16: =IF(E18>0,E18-E15,0) -> 0
A17: Div Margin | E17: =IFERROR(E15/E18,0) -> 0
A18: Selling Price
A20: Gyutan Udon
A21: Element | B21: UOM | C21: Element Cost/(g) | D21: Portion Used | E21: Value /pcs | F21: Major Step | G21: Units
E22: =IFERROR(C22*D22,0) -> 0 | F22: Recipe detail belum ditemukan pada ITEM SALES RECIPE / PDF yang tersedia.
E23: =IFERROR(C23*D23,0) -> 0
E24: =IFERROR(C24*D24,0) -> 0
E25: =IFERROR(C25*D25,0) -> 0
E26: =IFERROR(C26*D26,0) -> 0
E27: =IFERROR(C27*D27,0) -> 0
E28: =IFERROR(C28*D28,0) -> 0
E29: =IFERROR(C29*D29,0) -> 0
A30: Boxes, packaging, etc. | E30: 0
A31: Direct Cost | E31: =SUM(E22:E30) -> 0 | F31: Source: -
A32: Indirect Cost | E32: =E31*15% -> 0 | F32: Status: Recipe Pending
A33: Cost of Goods Sold (COGS) | E33: =E31+E32 -> 0
A34: Margin | E34: =IF(E36>0,E36-E33,0) -> 0
A35: Div Margin | E35: =IFERROR(E33/E36,0) -> 0
A36: Selling Price
A38: Beefu Udon
A39: Element | B39: UOM | C39: Element Cost/(g) | D39: Portion Used | E39: Value /pcs | F39: Major Step | G39: Units
E40: =IFERROR(C40*D40,0) -> 0 | F40: Recipe detail belum ditemukan pada ITEM SALES RECIPE / PDF yang tersedia.
E41: =IFERROR(C41*D41,0) -> 0
E42: =IFERROR(C42*D42,0) -> 0
E43: =IFERROR(C43*D43,0) -> 0
E44: =IFERROR(C44*D44,0) -> 0
E45: =IFERROR(C45*D45,0) -> 0
E46: =IFERROR(C46*D46,0) -> 0
E47: =IFERROR(C47*D47,0) -> 0
A48: Boxes, packaging, etc. | E48: 0
A49: Direct Cost | E49: =SUM(E40:E48) -> 0 | F49: Source: -
A50: Indirect Cost | E50: =E49*15% -> 0 | F50: Status: Recipe Pending
A51: Cost of Goods Sold (COGS) | E51: =E49+E50 -> 0
A52: Margin | E52: =IF(E54>0,E54-E51,0) -> 0
A53: Div Margin | E53: =IFERROR(E51/E54,0) -> 0
A54: Selling Price

Sheet Japanese Poridge Stall
A1: Japanese Poridge Stall
A2: Okayu Beef
A3: Element | B3: UOM | C3: Element Cost/(g) | D3: Portion Used | E3: Value /pcs | F3: Major Step | G3: Units
E4: =IFERROR(C4*D4,0) -> 0 | F4: Recipe detail belum ditemukan pada ITEM SALES RECIPE / PDF yang tersedia.
E5: =IFERROR(C5*D5,0) -> 0
E6: =IFERROR(C6*D6,0) -> 0
E7: =IFERROR(C7*D7,0) -> 0
E8: =IFERROR(C8*D8,0) -> 0
E9: =IFERROR(C9*D9,0) -> 0
E10: =IFERROR(C10*D10,0) -> 0
E11: =IFERROR(C11*D11,0) -> 0
A12: Boxes, packaging, etc. | E12: 0
A13: Direct Cost | E13: =SUM(E4:E12) -> 0 | F13: Source: -
A14: Indirect Cost | E14: =E13*15% -> 0 | F14: Status: Recipe Pending
A15: Cost of Goods Sold (COGS) | E15: =E13+E14 -> 0
A16: Margin | E16: =IF(E18>0,E18-E15,0) -> 0
A17: Div Margin | E17: =IFERROR(E15/E18,0) -> 0
A18: Selling Price
A20: Smoked Duck Okayu
A21: Element | B21: UOM | C21: Element Cost/(g) | D21: Portion Used | E21: Value /pcs | F21: Major Step | G21: Units
E22: =IFERROR(C22*D22,0) -> 0 | F22: Recipe detail belum ditemukan pada ITEM SALES RECIPE / PDF yang tersedia.
E23: =IFERROR(C23*D23,0) -> 0
E24: =IFERROR(C24*D24,0) -> 0
E25: =IFERROR(C25*D25,0) -> 0
E26: =IFERROR(C26*D26,0) -> 0
E27: =IFERROR(C27*D27,0) -> 0
E28: =IFERROR(C28*D28,0) -> 0
E29: =IFERROR(C29*D29,0) -> 0
A30: Boxes, packaging, etc. | E30: 0
A31: Direct Cost | E31: =SUM(E22:E30) -> 0 | F31: Source: -
A32: Indirect Cost | E32: =E31*15% -> 0 | F32: Status: Recipe Pending
A33: Cost of Goods Sold (COGS) | E33: =E31+E32 -> 0
A34: Margin | E34: =IF(E36>0,E36-E33,0) -> 0
A35: Div Margin | E35: =IFERROR(E33/E36,0) -> 0
A36: Selling Price
A38: Tori Okayu
A39: Element | B39: UOM | C39: Element Cost/(g) | D39: Portion Used | E39: Value /pcs | F39: Major Step | G39: Units
E40: =IFERROR(C40*D40,0) -> 0 | F40: Recipe detail belum ditemukan pada ITEM SALES RECIPE / PDF yang tersedia.
E41: =IFERROR(C41*D41,0) -> 0
E42: =IFERROR(C42*D42,0) -> 0
E43: =IFERROR(C43*D43,0) -> 0
E44: =IFERROR(C44*D44,0) -> 0
E45: =IFERROR(C45*D45,0) -> 0
E46: =IFERROR(C46*D46,0) -> 0
E47: =IFERROR(C47*D47,0) -> 0
A48: Boxes, packaging, etc. | E48: 0
A49: Direct Cost | E49: =SUM(E40:E48) -> 0 | F49: Source: -
A50: Indirect Cost | E50: =E49*15% -> 0 | F50: Status: Recipe Pending
A51: Cost of Goods Sold (COGS) | E51: =E49+E50 -> 0
A52: Margin | E52: =IF(E54>0,E54-E51,0) -> 0
A53: Div Margin | E53: =IFERROR(E51/E54,0) -> 0
A54: Selling Price

Sheet Yakimono - Griiled Stall
A1: Yakimono - Griiled Stall
A2: Beefu Hikiniku
A3: Element | B3: UOM | C3: Element Cost/(g) | D3: Portion Used | E3: Value /pcs | F3: Major Step | G3: Units
E4: =IFERROR(C4*D4,0) -> 0 | F4: Recipe detail belum ditemukan pada ITEM SALES RECIPE / PDF yang tersedia.
E5: =IFERROR(C5*D5,0) -> 0
E6: =IFERROR(C6*D6,0) -> 0
E7: =IFERROR(C7*D7,0) -> 0
E8: =IFERROR(C8*D8,0) -> 0
E9: =IFERROR(C9*D9,0) -> 0
E10: =IFERROR(C10*D10,0) -> 0
E11: =IFERROR(C11*D11,0) -> 0
A12: Boxes, packaging, etc. | E12: 0
A13: Direct Cost | E13: =SUM(E4:E12) -> 0 | F13: Source: -
A14: Indirect Cost | E14: =E13*15% -> 0 | F14: Status: Recipe Pending
A15: Cost of Goods Sold (COGS) | E15: =E13+E14 -> 0
A16: Margin | E16: =IF(E18>0,E18-E15,0) -> 0
A17: Div Margin | E17: =IFERROR(E15/E18,0) -> 0
A18: Selling Price
A20: Salmon Don
A21: Element | B21: UOM | C21: Element Cost/(g) | D21: Portion Used | E21: Value /pcs | F21: Major Step | G21: Units
E22: =IFERROR(C22*D22,0) -> 0 | F22: Recipe detail belum ditemukan pada ITEM SALES RECIPE / PDF yang tersedia.
E23: =IFERROR(C23*D23,0) -> 0
E24: =IFERROR(C24*D24,0) -> 0
E25: =IFERROR(C25*D25,0) -> 0
E26: =IFERROR(C26*D26,0) -> 0
E27: =IFERROR(C27*D27,0) -> 0
E28: =IFERROR(C28*D28,0) -> 0
E29: =IFERROR(C29*D29,0) -> 0
A30: Boxes, packaging, etc. | E30: 0
A31: Direct Cost | E31: =SUM(E22:E30) -> 0 | F31: Source: -
A32: Indirect Cost | E32: =E31*15% -> 0 | F32: Status: Recipe Pending
A33: Cost of Goods Sold (COGS) | E33: =E31+E32 -> 0
A34: Margin | E34: =IF(E36>0,E36-E33,0) -> 0
A35: Div Margin | E35: =IFERROR(E33/E36,0) -> 0
A36: Selling Price
A38: Unagimeshi
A39: Element | B39: UOM | C39: Element Cost/(g) | D39: Portion Used | E39: Value /pcs | F39: Major Step | G39: Units
E40: =IFERROR(C40*D40,0) -> 0 | F40: Recipe detail belum ditemukan pada ITEM SALES RECIPE / PDF yang tersedia.
E41: =IFERROR(C41*D41,0) -> 0
E42: =IFERROR(C42*D42,0) -> 0
E43: =IFERROR(C43*D43,0) -> 0
E44: =IFERROR(C44*D44,0) -> 0
E45: =IFERROR(C45*D45,0) -> 0
E46: =IFERROR(C46*D46,0) -> 0
E47: =IFERROR(C47*D47,0) -> 0
A48: Boxes, packaging, etc. | E48: 0
A49: Direct Cost | E49: =SUM(E40:E48) -> 0 | F49: Source: -
A50: Indirect Cost | E50: =E49*15% -> 0 | F50: Status: Recipe Pending
A51: Cost of Goods Sold (COGS) | E51: =E49+E50 -> 0
A52: Margin | E52: =IF(E54>0,E54-E51,0) -> 0
A53: Div Margin | E53: =IFERROR(E51/E54,0) -> 0
A54: Selling Price
A56: Gyudon
A57: Element | B57: UOM | C57: Element Cost/(g) | D57: Portion Used | E57: Value /pcs | F57: Major Step | G57: Units
E58: =IFERROR(C58*D58,0) -> 0 | F58: Recipe detail belum ditemukan pada ITEM SALES RECIPE / PDF yang tersedia.
E59: =IFERROR(C59*D59,0) -> 0
E60: =IFERROR(C60*D60,0) -> 0
E61: =IFERROR(C61*D61,0) -> 0
E62: =IFERROR(C62*D62,0) -> 0
E63: =IFERROR(C63*D63,0) -> 0
E64: =IFERROR(C64*D64,0) -> 0
E65: =IFERROR(C65*D65,0) -> 0
A66: Boxes, packaging, etc. | E66: 0
A67: Direct Cost | E67: =SUM(E58:E66) -> 0 | F67: Source: -
A68: Indirect Cost | E68: =E67*15% -> 0 | F68: Status: Recipe Pending
A69: Cost of Goods Sold (COGS) | E69: =E67+E68 -> 0
A70: Margin | E70: =IF(E72>0,E72-E69,0) -> 0
A71: Div Margin | E71: =IFERROR(E69/E72,0) -> 0
A72: Selling Price

Sheet Onigiri Corner Stall
A1: Onigiri Corner Stall
A2: Onigiri Spicy Tuna
A3: Element | B3: UOM | C3: Element Cost/(g) | D3: Portion Used | E3: Value /pcs | F3: Major Step | G3: Units
E4: =IFERROR(C4*D4,0) -> 0 | F4: Recipe detail belum ditemukan pada ITEM SALES RECIPE / PDF yang tersedia.
E5: =IFERROR(C5*D5,0) -> 0
E6: =IFERROR(C6*D6,0) -> 0
E7: =IFERROR(C7*D7,0) -> 0
E8: =IFERROR(C8*D8,0) -> 0
E9: =IFERROR(C9*D9,0) -> 0
E10: =IFERROR(C10*D10,0) -> 0
E11: =IFERROR(C11*D11,0) -> 0
A12: Boxes, packaging, etc. | E12: 0
A13: Direct Cost | E13: =SUM(E4:E12) -> 0 | F13: Source: -
A14: Indirect Cost | E14: =E13*15% -> 0 | F14: Status: Recipe Pending
A15: Cost of Goods Sold (COGS) | E15: =E13+E14 -> 0
A16: Margin | E16: =IF(E18>0,E18-E15,0) -> 0
A17: Div Margin | E17: =IFERROR(E15/E18,0) -> 0
A18: Selling Price
A20: Cakalang Onigiri
A21: Element | B21: UOM | C21: Element Cost/(g) | D21: Portion Used | E21: Value /pcs | F21: Major Step | G21: Units
E22: =IFERROR(C22*D22,0) -> 0 | F22: Recipe detail belum ditemukan pada ITEM SALES RECIPE / PDF yang tersedia.
E23: =IFERROR(C23*D23,0) -> 0
E24: =IFERROR(C24*D24,0) -> 0
E25: =IFERROR(C25*D25,0) -> 0
E26: =IFERROR(C26*D26,0) -> 0
E27: =IFERROR(C27*D27,0) -> 0
E28: =IFERROR(C28*D28,0) -> 0
E29: =IFERROR(C29*D29,0) -> 0
A30: Boxes, packaging, etc. | E30: 0
A31: Direct Cost | E31: =SUM(E22:E30) -> 0 | F31: Source: -
A32: Indirect Cost | E32: =E31*15% -> 0 | F32: Status: Recipe Pending
A33: Cost of Goods Sold (COGS) | E33: =E31+E32 -> 0
A34: Margin | E34: =IF(E36>0,E36-E33,0) -> 0
A35: Div Margin | E35: =IFERROR(E33/E36,0) -> 0
A36: Selling Price
A38: Salmon Mayo Onigiri
A39: Element | B39: UOM | C39: Element Cost/(g) | D39: Portion Used | E39: Value /pcs | F39: Major Step | G39: Units
E40: =IFERROR(C40*D40,0) -> 0 | F40: Recipe detail belum ditemukan pada ITEM SALES RECIPE / PDF yang tersedia.
E41: =IFERROR(C41*D41,0) -> 0
E42: =IFERROR(C42*D42,0) -> 0
E43: =IFERROR(C43*D43,0) -> 0
E44: =IFERROR(C44*D44,0) -> 0
E45: =IFERROR(C45*D45,0) -> 0
E46: =IFERROR(C46*D46,0) -> 0
E47: =IFERROR(C47*D47,0) -> 0
A48: Boxes, packaging, etc. | E48: 0
A49: Direct Cost | E49: =SUM(E40:E48) -> 0 | F49: Source: -
A50: Indirect Cost | E50: =E49*15% -> 0 | F50: Status: Recipe Pending
A51: Cost of Goods Sold (COGS) | E51: =E49+E50 -> 0
A52: Margin | E52: =IF(E54>0,E54-E51,0) -> 0
A53: Div Margin | E53: =IFERROR(E51/E54,0) -> 0
A54: Selling Price
A56: Onigiri Yakiniku
A57: Element | B57: UOM | C57: Element Cost/(g) | D57: Portion Used | E57: Value /pcs | F57: Major Step | G57: Units
E58: =IFERROR(C58*D58,0) -> 0 | F58: Recipe detail belum ditemukan pada ITEM SALES RECIPE / PDF yang tersedia.
E59: =IFERROR(C59*D59,0) -> 0
E60: =IFERROR(C60*D60,0) -> 0
E61: =IFERROR(C61*D61,0) -> 0
E62: =IFERROR(C62*D62,0) -> 0
E63: =IFERROR(C63*D63,0) -> 0
E64: =IFERROR(C64*D64,0) -> 0
E65: =IFERROR(C65*D65,0) -> 0
A66: Boxes, packaging, etc. | E66: 0
A67: Direct Cost | E67: =SUM(E58:E66) -> 0 | F67: Source: -
A68: Indirect Cost | E68: =E67*15% -> 0 | F68: Status: Recipe Pending
A69: Cost of Goods Sold (COGS) | E69: =E67+E68 -> 0
A70: Margin | E70: =IF(E72>0,E72-E69,0) -> 0
A71: Div Margin | E71: =IFERROR(E69/E72,0) -> 0
A72: Selling Price

Sheet Market List
A1: MARKET LIST
A2: Category | B2: Ingredients | C2: UOM | D2: Weight (gr/ea/ml) | E2: Unit Cost | F2: Unit Price (g)
A3: Raw Material | B3: Kyuri/japanese cucumber | C3: GR | D3: 1000 | E3: 17500 | F3: =IFERROR(E3/D3,0) -> 17.5
A4: Raw Material | B4: Garam | C4: GR | D4: 500 | E4: 8000 | F4: =IFERROR(E4/D4,0) -> 16
A5: Raw Material | B5: Dry chili | C5: GR | D5: 1000 | E5: 140000 | F5: =IFERROR(E5/D5,0) -> 140
A6: Raw Material | B6: rice vinegar | C6: ML | D6: 600 | E6: 29300 | F6: =IFERROR(E6/D6,0) -> 48.833333
A7: Raw Material | B7: gula putih | C7: GR | D7: 1000 | E7: 18000 | F7: =IFERROR(E7/D7,0) -> 18
A8: Raw Material | B8: Sesame oil | C8: ML | D8: 620 | E8: 39000 | F8: =IFERROR(E8/D8,0) -> 62.903226
A9: Raw Material | B9: Air | C9: ML | D9: 18000 | E9: 56700 | F9: =IFERROR(E9/D9,0) -> 3.15
A10: Raw Material | B10: Telur rebus dan chopped | C10: GR | D10: 1000 | E10: 25000 | F10: =IFERROR(E10/D10,0) -> 25
A11: Raw Material | B11: Kewpie Mayonnaise | C11: GR | D11: 1000 | E11: 72300 | F11: =IFERROR(E11/D11,0) -> 72.3
A12: Raw Material | B12: Bawang Bombay | C12: GR | D12: 1000 | E12: 35000 | F12: =IFERROR(E12/D12,0) -> 35
A13: Raw Material | B13: Lada Putih | C13: GR | D13: 1000 | E13: 200000 | F13: =IFERROR(E13/D13,0) -> 200
A14: Raw Material | B14: Hondashi | C14: GR | D14: 1000 | E14: 155500 | F14: =IFERROR(E14/D14,0) -> 155.5
... A77: Raw Material | B77: Sawi | C77: GR | D77: 1000 | E77: 13000 | F77: =IFERROR(E77/D77,0) -> 13
A78: Raw Material | B78: Air Dashi | C78: ML | F78: =IFERROR(E78/D78,0) -> 0
A79: Raw Material | B79: Daging beef giling | C79: GR | D79: 1000 | E79: 113000 | F79: =IFERROR(E79/D79,0) -> 113
A80: Raw Material | B80: Oyster Sauce | C80: GR | D80: 770 | E80: 50000 | F80: =IFERROR(E80/D80,0) -> 64.935065
A81: Raw Material | B81: Cheese Cheddar | C81: GR | D81: 2000 | E81: 182100 | F81: =IFERROR(E81/D81,0) -> 91.05
A82: Raw Material | B82: Telur Pasar Curah | C82: BUTIR | D82: 14 | E82: 25000 | F82: =IFERROR(E82/D82,0) -> 1785.7143
A83: Raw Material | B83: Tepung roti (ditempat berbeda) | C83: KG | D83: 200 | E83: 23450 | F83: =IFERROR(E83/D83,0) -> 117.25
A84: Raw Material | B84: Tepung Segitiga biru | C84: GR | D84: 1000 | E84: 13000 | F84: =IFERROR(E84/D84,0) -> 13
A85: Raw Material | B85: Nasi Panas | C85: GR | F85: =IFERROR(E85/D85,0) -> 0
A86: Raw Material | B86: Pasta miso | C86: GR | D86: 1000 | E86: 46500 | F86: =IFERROR(E86/D86,0) -> 46.5
A87: Raw Material | B87: paprica hijau | C87: GR | D87: 1000 | E87: 65000 | F87: =IFERROR(E87/D87,0) -> 65
A88: Raw Material | B88: cabe hijau besar | C88: GR | D88: 1000 | E88: 38000 | F88: =IFERROR(E88/D88,0) -> 38
A89: Raw Material | B89: tomat hijau | C89: GR | D89: 1000 | E89: 20000 | F89: =IFERROR(E89/D89,0) -> 20
A90: Raw Material | B90: celeri steak | C90: GR | D90: 1000 | E90: 35000 | F90: =IFERROR(E90/D90,0) -> 35
A91: Raw Material | B91: minyak | C91: GR | D91: 18000 | E91: 395000 | F91: =IFERROR(E91/D91,0) -> 21.944444
A92: Raw Material | B92: terigu | C92: GR | D92: 1000 | E92: 14500 | F92: =IFERROR(E92/D92,0) -> 14.5
A93: Raw Material | B93: Shayou kikkoman | C93: GR | D93: 1600 | E93: 120000 | F93: =IFERROR(E93/D93,0) -> 75
A94: Raw Material | B94: Nasi | C94: KG | F94: =IFERROR(E94/D94,0) -> 0
A95: Raw Material | B95: Truffle Oil | C95: GR | D95: 250 | E95: 242950 | F95: =IFERROR(E95/D95,0) -> 971.8
A96: Raw Material | B96: Nori Sheets | C96: LEMBAR | D96: 60 | E96: 164500 | F96: =IFERROR(E96/D96,0) -> 2741.6667
A97: Raw Material | B97: Sichimi | C97: GR | D97: 300 | E97: 105500 | F97: =IFERROR(E97/D97,0) -> 351.66667
A98: Raw Material | B98: Telur Pasar | C98: PCS | D98: 14 | E98: 25000 | F98: =IFERROR(E98/D98,0) -> 1785.7143
A99: Raw Material | B99: Beef Shortplate Slice | C99: GR | D99: 1000 | E99: 135000 | F99: =IFERROR(E99/D99,0) -> 135
A100: Raw Material | B100: Paprika powder | C100: GR | D100: 1000 | E100: 82466 | F100: =IFERROR(E100/D100,0) -> 82.466
A101: Raw Material | B101: Jinten Powder | C101: GR | D101: 1000 | E101: 89900 | F101: =IFERROR(E101/D101,0) -> 89.9
A102: Raw Material | B102: Bulldog tonkotsu sauce | C102: GR | D102: 1800 | E102: 172700.46 | F102: =IFERROR(E102/D102,0) -> 95.9447
A103: Raw Material | B103: Madu Nusantara | C103: GR | D103: 1000 | E103: 84950 | F103: =IFERROR(E103/D103,0) -> 84.95
A104: Raw Material | B104: bulldog Wonchester sauce | C104: GR | D104: 283.5 | E104: 64600 | F104: =IFERROR(E104/D104,0) -> 227.86596
A105: Raw Material | B105: Ayam | C105: KG | D105: 1000 | E105: 39999 | F105: =IFERROR(E105/D105,0) -> 39.999
A106: Raw Material | B106: Segitiga biru | C106: GR | D106: 1000 | E106: 13000 | F106: =IFERROR(E106/D106,0) -> 13
... A111: Raw Material | B111: Miso Paste | C111: GR | D111: 1000 | E111: 46500 | F111: =IFERROR(E111/D111,0) -> 46.5
A112: Raw Material | B112: Minyak Kulit Ayam (minyak nya aja) | C112: GR | F112: =IFERROR(E112/D112,0) -> 0
A113: Raw Material | B113: Minyak sayur | C113: ML | D113: 18000 | E113: 395000 | F113: =IFERROR(E113/D113,0) -> 21.944444
A114: Raw Material | B114: Sauce Tiram | C114: GR | D114: 770 | E114: 50000 | F114: =IFERROR(E114/D114,0) -> 64.935065
A115: Raw Material | B115: Gelatine Powder | C115: GR | D115: 250 | E115: 52900 | F115: =IFERROR(E115/D115,0) -> 211.6
A116: Raw Material | B116: Whipping Cream | C116: GR | D116: 1000 | E116: 75500 | F116: =IFERROR(E116/D116,0) -> 75.5
A117: Raw Material | B117: Egg Yolk | C117: GR | D117: 1000 | E117: 130000 | F117: =IFERROR(E117/D117,0) -> 130
A118: Raw Material | B118: Gula Pasir | C118: GR | D118: 1000 | E118: 18000 | F118: =IFERROR(E118/D118,0) -> 18
A119: Raw Material | B119: Dark Chocolate 54% | C119: GR | D119: 300 | E119: 40800 | F119: =IFERROR(E119/D119,0) -> 136
A120: Raw Material | B120: Dark Chocolate 70% | C120: GR | D120: 2000 | E120: 643199 | F120: =IFERROR(E120/D120,0) -> 321.5995
A121: Raw Material | B121: Chocolate Powder | C121: GR | D121: 165 | E121: 46800 | F121: =IFERROR(E121/D121,0) -> 283.63636
A122: Raw Material | B122: Cream | C122: GR | D122: 1000 | E122: 75500 | F122: =IFERROR(E122/D122,0) -> 75.5
A123: Raw Material | B123: Maizena | C123: GR | D123: 1000 | E123: 22500 | F123: =IFERROR(E123/D123,0) -> 22.5
A124: Raw Material | B124: Hojicha Powder | C124: GR | D124: 500 | E124: 499500 | F124: =IFERROR(E124/D124,0) -> 999
... A147: Raw Material | B147: Onion Pickles | C147: GR | D147: 250 | E147: 22940 | F147: =IFERROR(E147/D147,0) -> 91.76
A148: Raw Material | B148: Tsukune | C148: GR | F148: =IFERROR(E148/D148,0) -> 0
A149: Raw Material | B149: Sayap Ayam utuh | C149: PCS | D149: 12 | E149: 35000 | F149: =IFERROR(E149/D149,0) -> 2916.6667
A150: Raw Material | B150: Beef Shorplate | C150: GR | D150: 1000 | E150: 135000 | F150: =IFERROR(E150/D150,0) -> 135
A151: Raw Material | B151: Enoki Mushroom | C151: GR | E151: 4500 | F151: =IFERROR(E151/D151,0) -> 0
A152: Raw Material | B152: Mochi Block | C152: PACK | D152: 270 | E152: 80800 | F152: =IFERROR(E152/D152,0) -> 299.25926
A153: Raw Material | B153: Garnish daun bawang dan paprika | C153: GR | F153: =IFERROR(E153/D153,0) -> 0
A154: Raw Material | B154: Lime Sichimi | C154: GR | D154: 300 | E154: 105500 | F154: =IFERROR(E154/D154,0) -> 351.66667
A155: Raw Material | B155: Cheese | C155: GR | D155: 2000 | E155: 182100 | F155: =IFERROR(E155/D155,0) -> 91.05
A156: Raw Material | B156: Daun Bawang slice | C156: PINCHED | D156: 1000 | E156: 20000 | F156: =IFERROR(E156/D156,0) -> 20
A157: Raw Material | B157: Tapioka charcoal | C157: GR | F157: =IFERROR(E157/D157,0) -> 0
A158: Raw Material | B158: Wasabi mayo | C158: GR | D158: 90 | E158: 56500 | F158: =IFERROR(E158/D158,0) -> 627.77778
A159: Raw Material | B159: Jagung Manis | C159: GR | D159: 1000 | E159: 13000 | F159: =IFERROR(E159/D159,0) -> 13
A160: Raw Material | B160: Ayam SFC marinate | C160: PCS | F160: =IFERROR(E160/D160,0) -> 0
A161: Raw Material | B161: SFC mix flour | C161: GR | F161: =IFERROR(E161/D161,0) -> 0
A162: Raw Material | B162: lemon | C162: GR | D162: 1000 | E162: 53000 | F162: =IFERROR(E162/D162,0) -> 53
A163: Raw Material | B163: Udang Tempura | D163: 500 | E163: 66000 | F163: =IFERROR(E163/D163,0) -> 132
A164: Raw Material | B164: Gyutan Marinasi | C164: GR | F164: =IFERROR(E164/D164,0) -> 0
A165: Raw Material | B165: Rice | C165: GR | D165: 5000 | E165: 206300 | F165: =IFERROR(E165/D165,0) -> 41.26
A166: Raw Material | B166: Onsen Egg | C166: PCS | F166: =IFERROR(E166/D166,0) -> 0
A167: Raw Material | B167: Beef marinasi yakiniku | C167: GR | F167: =IFERROR(E167/D167,0) -> 0
A168: Raw Material | B168: Smocked Duck | C168: GR | D168: 200 | E168: 50900 | F168: =IFERROR(E168/D168,0) -> 254.5
A169: Raw Material | B169: Ramen | C169: GR | D169: 570 | E169: 16000 | F169: =IFERROR(E169/D169,0) -> 28.070175
A170: Raw Material | B170: Garlic Oil | C170: GR | D170: 500 | E170: 43000 | F170: =IFERROR(E170/D170,0) -> 86
A171: Raw Material | B171: Smoked Duck Slice | C171: GR | D171: 200 | E171: 50900 | F171: =IFERROR(E171/D171,0) -> 254.5
A172: Raw Material | B172: Jukut | C172: GR | E172: 3000 | F172: =IFERROR(E172/D172,0) -> 0
A173: Raw Material | B173: Telur Omega | C173: BUTIR | D173: 10 | E173: 36000 | F173: =IFERROR(E173/D173,0) -> 3600
A174: Raw Material | B174: Chicken Broth | C174: ML | E174: 55000 | F174: =IFERROR(E174/D174,0) -> 0
A175: Raw Material | B175: Shoyu Ramen Sauce | C175: ML | F175: =IFERROR(E175/D175,0) -> 0
A176: Raw Material | B176: Smoked Beef | C176: GR | D176: 250 | E176: 22500 | F176: =IFERROR(E176/D176,0) -> 90
A177: Raw Material | B177: Garlic Chip | C177: GR | D177: 50 | E177: 50000 | F177: =IFERROR(E177/D177,0) -> 1000
A178: Raw Material | B178: Udon | C178: GR | D178: 125 | E178: 49300 | F178: =IFERROR(E178/D178,0) -> 394.4
A179: Raw Material | B179: Bawang Bombay | D179: 1000 | E179: 35000 | F179: =IFERROR(E179/D179,0) -> 35
A180: Raw Material | B180: Cooking Cream | D180: 1000 | E180: 69000 | F180: =IFERROR(E180/D180,0) -> 69
A181: Raw Material | B181: Blueberrys juice ( Diamond ) | C181: ML | F181: =IFERROR(E181/D181,0) -> 0
A182: Raw Material | B182: Grenadine syrup | C182: ML | E182: 170000 | F182: =IFERROR(E182/D182,0) -> 0
A183: Raw Material | B183: Espresso based | C183: ML | F183: =IFERROR(E183/D183,0) -> 0
A184: Raw Material | B184: Lychee juice (Squeeze) | C184: ML | F184: =IFERROR(E184/D184,0) -> 0
A185: Raw Material | B185: Creamer powder | C185: GR | F185: =IFERROR(E185/D185,0) -> 0
A186: Raw Material | B186: Squeeze Sirsak | C186: ML | D186: 1000 | E186: 18315 | F186: =IFERROR(E186/D186,0) -> 18.315
A187: Raw Material | B187: Simple syrup | C187: ML | F187: =IFERROR(E187/D187,0) -> 0
B188: Tuna Saku | F188: =IFERROR(E188/D188,0) -> 0
...

Sheet WIP FOOD
A1: WORK IN PROGRESS
A2: Semua Sub Menu / Sub-Recipe dan production base yang mendukung menu. Seluruh nama item menggunakan suffix WIP.
A3: Adonan Gyoza WIP | B3: =IFERROR(D15/D3,0) -> 598.22 | C3: Portion | D3: 120 | E3: Pcs
A4: Ingredients | B4: Use (g/ml/ea) | C4: Unit Price / Unit | D4: Price | E4: Major Step
A5: Ayam Giling | B5: 1000 | C5: =IFERROR(VLOOKUP(A5,'Market List'!$B:$F,5,FALSE),0) -> 45 | D5: =IFERROR(B5*C5,0) -> 45000 | E5: Aduk semua bahan pastikan tercampur dengan rata
A6: Daun Kucai | B6: 90 | C6: =IFERROR(VLOOKUP(A6,'Market List'!$B:$F,5,FALSE),0) -> 25 | D6: =IFERROR(B6*C6,0) -> 2250 | E6: Prep: Slice.
A7: Sawi Putih | B7: 750 | C7: =IFERROR(VLOOKUP(A7,'Market List'!$B:$F,5,FALSE),0) -> 13 | D7: =IFERROR(B7*C7,0) -> 9750 | E7: Prep: Chopped.
A8: Bawang Putih | B8: 12 | C8: =IFERROR(VLOOKUP(A8,'Market List'!$B:$F,5,FALSE),0) -> 45 | D8: =IFERROR(B8*C8,0) -> 540 | E8: Prep: Parut.
A9: Jahe | B9: 8 | C9: =IFERROR(VLOOKUP(A9,'Market List'!$B:$F,5,FALSE),0) -> 33 | D9: =IFERROR(B9*C9,0) -> 264 | E9: Prep: Parut.
A10: soy kikkoman | B10: 120 | C10: =IFERROR(VLOOKUP(A10,'Market List'!$B:$F,5,FALSE),0) -> 75 | D10: =IFERROR(B10*C10,0) -> 9000
A11: Lada putih bubuk | B11: 1 | C11: =IFERROR(VLOOKUP(A11,'Market List'!$B:$F,5,FALSE),0) -> 114.4 | D11: =IFERROR(B11*C11,0) -> 114.4
A12: Hondashi | B12: 20 | C12: =IFERROR(VLOOKUP(A12,'Market List'!$B:$F,5,FALSE),0) -> 155.5 | D12: =IFERROR(B12*C12,0) -> 3110
A13: Campignon | B13: 30 | C13: =IFERROR(VLOOKUP(A13,'Market List'!$B:$F,5,FALSE),0) -> 45 | D13: =IFERROR(B13*C13,0) -> 1350 | E13: Prep: Chopped.
A14: Curry Powder | B14: 3 | C14: =IFERROR(VLOOKUP(A14,'Market List'!$B:$F,5,FALSE),0) -> 136 | D14: =IFERROR(B14*C14,0) -> 408
A15: Element Cost | D15: =SUM(D5:D14) -> 71786.4 | E15: Source: SULU-bdg FoodTesting.xlsx - SUB-RECIPE CARD
A17: Adonan Okonomiyaki WIP | B17: =IFERROR(D26/D17,0) -> 2346.1984 | C17: Portion | D17: 10 | E17: Portion
A18: Ingredients | B18: Use (g/ml/ea) | C18: Unit Price / Unit | D18: Price | E18: Major Step
A19: Tepung Segitiga biru | B19: 900 | C19: =IFERROR(VLOOKUP(A19,'Market List'!$B:$F,5,FALSE),0) -> 13 | D19: =IFERROR(B19*C19,0) -> 11700 | E19: Siapkan Stainless bowl, masukan semua bahan nya dan aduk menggunakan baloon whisk hingga rata dan bagus (tidak ada gumpalan)
A20: Telur | B20: 2 | C20: =IFERROR(VLOOKUP(A20,'Market List'!$B:$F,5,FALSE),0) -> 1785.7143 | D20: =IFERROR(B20*C20,0) -> 3571.4286
A21: Garam | B21: 10 | C21: =IFERROR(VLOOKUP(A21,'Market List'!$B:$F,5,FALSE),0) -> 16 | D21: =IFERROR(B21*C21,0) -> 160
A22: Gula | B22: 15 | C22: =IFERROR(VLOOKUP(A22,'Market List'!$B:$F,5,FALSE),0) -> 18 | D22: =IFERROR(B22*C22,0) -> 270
A23: Baking Powder | B23: 5 | C23: =IFERROR(VLOOKUP(A23,'Market List'!$B:$F,5,FALSE),0) -> 111.11111 | D23: =IFERROR(B23*C23,0) -> 555.55556
A24: Hondashi | B24: 20 | C24: =IFERROR(VLOOKUP(A24,'Market List'!$B:$F,5,FALSE),0) -> 155.5 | D24: =IFERROR(B24*C24,0) -> 3110
A25: Air | B25: 1300 | C25: =IFERROR(VLOOKUP(A25,'Market List'!$B:$F,5,FALSE),0) -> 3.15 | D25: =IFERROR(B25*C25,0) -> 4095
A26: Element Cost | D26: =SUM(D19:D25) -> 23461.984 | E26: Source: SULU-bdg FoodTesting.xlsx - SUB-RECIPE CARD
A28: Adonan Takoyaki WIP | B28: =IFERROR(D39/D28,0) -> 546.0819 | C28: Portion | D28: 25 | E28: Pcs
A29: Ingredients | B29: Use (g/ml/ea) | C29: Unit Price / Unit | D29: Price | E29: Major Step
A30: Tepung Segitiga biru | B30: 300 | C30: =IFERROR(VLOOKUP(A30,'Market List'!$B:$F,5,FALSE),0) -> 13 | D30: =IFERROR(B30*C30,0) -> 3900 | E30: Siapkan Stainless bowl, masukan semua bahan nya dan aduk menggunakan baloon whisk hingga rata dan bagus (tidak ada gumpalan)
A31: Meizena | B31: 80 | C31: =IFERROR(VLOOKUP(A31,'Market List'!$B:$F,5,FALSE),0) -> 22.5 | D31: =IFERROR(B31*C31,0) -> 1800
A32: Telur | B32: 1 | C32: =IFERROR(VLOOKUP(A32,'Market List'!$B:$F,5,FALSE),0) -> 1785.7143 | D32: =IFERROR(B32*C32,0) -> 1785.7143
A33: Baking Powder | B33: 3 | C33: =IFERROR(VLOOKUP(A33,'Market List'!$B:$F,5,FALSE),0) -> 111.11111 | D33: =IFERROR(B33*C33,0) -> 333.33333
A34: Aonori | B34: 3 | C34: =IFERROR(VLOOKUP(A34,'Market List'!$B:$F,5,FALSE),0) -> 496 | D34: =IFERROR(B34*C34,0) -> 1488
A35: Air | B35: 750 | C35: =IFERROR(VLOOKUP(A35,'Market List'!$B:$F,5,FALSE),0) -> 3.15 | D35: =IFERROR(B35*C35,0) -> 2362.5
A36: Hondashi | B36: 3 | C36: =IFERROR(VLOOKUP(A36,'Market List'!$B:$F,5,FALSE),0) -> 155.5 | D36: =IFERROR(B36*C36,0) -> 466.5
A37: Garam | B37: 1 | C37: =IFERROR(VLOOKUP(A37,'Market List'!$B:$F,5,FALSE),0) -> 16 | D37: =IFERROR(B37*C37,0) -> 16
A38: Shoyu kikkoman | B38: 20 | C38: =IFERROR(VLOOKUP(A38,'Market List'!$B:$F,5,FALSE),0) -> 75 | D38: =IFERROR(B38*C38,0) -> 1500
A39: Element Cost | D39: =SUM(D30:D38) -> 13652.048 | E39: Source: SULU-bdg FoodTesting.xlsx - SUB-RECIPE CARD
A41: Adonan Tamagoyaki WIP | B41: =IFERROR(D49/D41,0) -> 1405.0439 | C41: Portion | D41: 15 | E41: Pcs
A42: Ingredients | B42: Use (g/ml/ea) | C42: Unit Price / Unit | D42: Price | E42: Major Step
A43: Telur Pasar | B43: 8 | C43: =IFERROR(VLOOKUP(A43,'Market List'!$B:$F,5,FALSE),0) -> 1785.7143 | D43: =IFERROR(B43*C43,0) -> 14285.714 | E43: Pecahkan telur dengan cara hati hati, dikarnakan khawatir ada yang busuk dan rusak, setelah itu masukan semua bahan menjadi 1 di stainless bowl
A44: Air | B44: 180 | C44: =IFERROR(VLOOKUP(A44,'Market List'!$B:$F,5,FALSE),0) -> 3.15 | D44: =IFERROR(B44*C44,0) -> 567 | E44: aduk hingga merata dan berbusa (aduk dengan kuat) , setelah itu di saring ke stainless 1 nya, guna takut ada benda asing didalam adukan telur itu
A45: Gula | B45: 80 | C45: =IFERROR(VLOOKUP(A45,'Market List'!$B:$F,5,FALSE),0) -> 18 | D45: =IFERROR(B45*C45,0) -> 1440 | E45: panas kan teflon tamagoyaki, tuangkan minyak dan masak adonan tamagoyaki dengan cara perlahan dan bertahap dengan cara tuang setiap lembar
A46: Shoyu | B46: 20 | C46: =IFERROR(VLOOKUP(A46,'Market List'!$B:$F,5,FALSE),0) -> 75 | D46: =IFERROR(B46*C46,0) -> 1500 | E46: Lakukan hingga selesai dan berbentuk kotak (balok)
A47: Hondashi | B47: 7 | C47: =IFERROR(VLOOKUP(A47,'Market List'!$B:$F,5,FALSE),0) -> 155.5 | D47: =IFERROR(B47*C47,0) -> 1088.5
A48: Minyak Goreng | B48: 100 | C48: =IFERROR(VLOOKUP(A48,'Market List'!$B:$F,5,FALSE),0) -> 21.944444 | D48: =IFERROR(B48*C48,0) -> 2194.4444 | E48: Prep: Untuk masak.
A49: Element Cost | D49: =SUM(D43:D48) -> 21075.659 | E49: Source: SULU-bdg FoodTesting.xlsx - SUB-RECIPE CARD
A51: Brioche Burger Bun WIP | B51: =IFERROR(D60/D51,0) -> 3998.7741 | C51: Portion | D51: 12 | E51: PCS
A52: Ingredients | B52: Use (g/ml/ea) | C52: Unit Price / Unit | D52: Price | E52: Major Step
A53: Tepung Terigu Protein Tinggi (Cakra) | B53: 463 | C53: =IFERROR(VLOOKUP(A53,'Market List'!$B:$F,5,FALSE),0) -> 13.5 | D53: =IFERROR(B53*C53,0) -> 6250.5
A54: Whole Egg | B54: 231 | C54: =IFERROR(VLOOKUP(A54,'Market List'!$B:$F,5,FALSE),0) -> 25 | D54: =IFERROR(B54*C54,0) -> 5775
A55: Fresh milk | B55: 47 | C55: =IFERROR(VLOOKUP(A55,'Market List'!$B:$F,5,FALSE),0) -> 38.421053 | D55: =IFERROR(B55*C55,0) -> 1805.7895
A56: Ragi Instan | B56: 5 | C56: =IFERROR(VLOOKUP(A56,'Market List'!$B:$F,5,FALSE),0) -> 100 | D56: =IFERROR(B56*C56,0) -> 500
A57: Gula Pasir | B57: 65 | C57: =IFERROR(VLOOKUP(A57,'Market List'!$B:$F,5,FALSE),0) -> 18 | D57: =IFERROR(B57*C57,0) -> 1170
A58: Garam | B58: 9 | C58: =IFERROR(VLOOKUP(A58,'Market List'!$B:$F,5,FALSE),0) -> 16 | D58: =IFERROR(B58*C58,0) -> 144
A59: Butter | B59: 231 | C59: =IFERROR(VLOOKUP(A59,'Market List'!$B:$F,5,FALSE),0) -> 140 | D59: =IFERROR(B59*C59,0) -> 32340
A60: Element Cost | D60: =SUM(D53:D59) -> 47985.289 | E60: Source: resep brioche burger bun. hotdog(1).pdf
A62: Cheese Sauce WIP | B62: =IFERROR(D70/D62,0) -> 89.062036 | C62: Portion | D62: =SUM(B64:B69)*90% -> 599.4 | E62: GR/ML
A63: Ingredients | B63: Use (g/ml/ea) | C63: Unit Price / Unit | D63: Price | E63: Major Step
A64: Butter unsalted | B64: 20 | C64: =IFERROR(VLOOKUP(A64,'Market List'!$B:$F,5,FALSE),0) -> 140 | D64: =IFERROR(B64*C64,0) -> 2800 | E64: panas kan panci, masukan tepung segitigabiru, sauted terlebih dahulu, kurang lebih 2 menit menggunakan api sedang,lalu masukan butter
A65: Tepung Segitiga biru | B65: 20 | C65: =IFERROR(VLOOKUP(A65,'Market List'!$B:$F,5,FALSE),0) -> 13 | D65: =IFERROR(B65*C65,0) -> 260 | E65: aduk kembali butter dan segitigabiru hingga mengikat, lalu masukan freshmilk langsung aduk hingga rata menggunakan api kecil
A66: Fresh milk | B66: 270 | C66: =IFERROR(VLOOKUP(A66,'Market List'!$B:$F,5,FALSE),0) -> 38.421053 | D66: =IFERROR(B66*C66,0) -> 10373.684 | E66: masukan cheese yang sudah diparut aduk kembali hingga rata (Jangan ada gumpalan), lalu masukan hondashi dan garam. matikan kompor
A67: Parmesan Cheese | B67: 350 | C67: =IFERROR(VLOOKUP(A67,'Market List'!$B:$F,5,FALSE),0) -> 111.876 | D67: =IFERROR(B67*C67,0) -> 39156.6 | E67: Prep: Parut.
A68: Hondashi | B68: 5 | C68: =IFERROR(VLOOKUP(A68,'Market List'!$B:$F,5,FALSE),0) -> 155.5 | D68: =IFERROR(B68*C68,0) -> 777.5
A69: Garam | B69: 1 | C69: =IFERROR(VLOOKUP(A69,'Market List'!$B:$F,5,FALSE),0) -> 16 | D69: =IFERROR(B69*C69,0) -> 16
A70: Element Cost | D70: =SUM(D64:D69) -> 53383.784 | E70: Source: SULU-bdg FoodTesting.xlsx - SUB-RECIPE CARD
A72: Chili Oil WIP | B72: =IFERROR(D86/D72,0) -> 120.11858 | C72: Portion | D72: =SUM(B74:B85)*90% -> 648.9 | E72: GR/ML
A73: Ingredients | B73: Use (g/ml/ea) | C73: Unit Price / Unit | D73: Price | E73: Major Step
A74: Katsuobushi | B74: 60 | C74: =IFERROR(VLOOKUP(A74,'Market List'!$B:$F,5,FALSE),0) -> 478.3989 | D74: =IFERROR(B74*C74,0) -> 28703.934 | E74: Panas kan Panci lalu masukan minyak sedikit dulu untuk tumis jahe,bawang putih dan bawang merah terlebih dahulu
A75: Bawang Putih Goreng | B75: 25 | C75: =IFERROR(VLOOKUP(A75,'Market List'!$B:$F,5,FALSE),0) -> 150 | D75: =IFERROR(B75*C75,0) -> 3750 | E75: Prep: Blender. masukan air,tunggu hingga mendidih dan sedikit surut. masukan semua bahan yang tersisa kecuali katsuobushi
A76: Chili Flakes/ dry chili chop | B76: 60 | C76: =IFERROR(VLOOKUP(A76,'Market List'!$B:$F,5,FALSE),0) -> 256 | D76: =IFERROR(B76*C76,0) -> 15360 | E76: ditempat lain, katsuobushi dipanaskan terlebih dahulu menggunakan teflon kering menggunakan api kecil, bertujuan untuk
A77: Shicimi Togarashi / Chili powder | B77: 48 | C77: =IFERROR(VLOOKUP(A77,'Market List'!$B:$F,5,FALSE),0) -> 351.66667 | D77: =IFERROR(B77*C77,0) -> 16880 | E77: mengering kan katsuobushi dan mudah di remas remas hingga hancur. setelah dirasa cukup hancur.
A78: Hondasi | B78: 20 | C78: =IFERROR(VLOOKUP(A78,'Market List'!$B:$F,5,FALSE),0) -> 155.5 | D78: =IFERROR(B78*C78,0) -> 3110 | E78: satukan katsuobushi yang sudah hancur
A79: Royco | B79: 8 | C79: =IFERROR(VLOOKUP(A79,'Market List'!$B:$F,5,FALSE),0) -> 43.181818 | D79: =IFERROR(B79*C79,0) -> 345.45455 | E79: kedalam panci bersama bahan bahan tadi di awal, panas kan menggunakan api kecil kurang lebih 10 menitan sambil diaduk aduk.
A80: Gula | B80: 20 | C80: =IFERROR(VLOOKUP(A80,'Market List'!$B:$F,5,FALSE),0) -> 18 | D80: =IFERROR(B80*C80,0) -> 360
A81: Bawang Putih | B81: 10 | C81: =IFERROR(VLOOKUP(A81,'Market List'!$B:$F,5,FALSE),0) -> 45 | D81: =IFERROR(B81*C81,0) -> 450 | E81: Prep: Blender halus.
A82: Jahe | B82: 5 | C82: =IFERROR(VLOOKUP(A82,'Market List'!$B:$F,5,FALSE),0) -> 33 | D82: =IFERROR(B82*C82,0) -> 165 | E82: Prep: Kupas; blender halus.
A83: Bawang Merah | B83: 15 | C83: =IFERROR(VLOOKUP(A83,'Market List'!$B:$F,5,FALSE),0) -> 55 | D83: =IFERROR(B83*C83,0) -> 825 | E83: Prep: Blender halus.
A84: Minyak Goreng | B84: 350 | C84: =IFERROR(VLOOKUP(A84,'Market List'!$B:$F,5,FALSE),0) -> 21.944444 | D84: =IFERROR(B84*C84,0) -> 7680.5556
A85: Air | B85: 100 | C85: =IFERROR(VLOOKUP(A85,'Market List'!$B:$F,5,FALSE),0) -> 3.15 | D85: =IFERROR(B85*C85,0) -> 315
A86: Element Cost | D86: =SUM(D74:D85) -> 77944.944 | E86: Source: SULU-bdg FoodTesting.xlsx - SUB-RECIPE CARD
A88: Chocolate Base WIP | B88: =IFERROR(D97/D88,0) -> 141.41583 | C88: Portion | D88: =SUM(B90:B96)*90% -> 937.8 | E88: GR
A89: Ingredients | B89: Use (g/ml/ea) | C89: Unit Price / Unit | D89: Price | E89: Major Step
A90: Gelatine Powder | B90: 5 | C90: =IFERROR(VLOOKUP(A90,'Market List'!$B:$F,5,FALSE),0) -> 211.6 | D90: =IFERROR(B90*C90,0) -> 1058
A91: Fresh milk | B91: 53 | C91: =IFERROR(VLOOKUP(A91,'Market List'!$B:$F,5,FALSE),0) -> 38.421053 | D91: =IFERROR(B91*C91,0) -> 2036.3158
A92: Whipping Cream | B92: 225 | C92: =IFERROR(VLOOKUP(A92,'Market List'!$B:$F,5,FALSE),0) -> 75.5 | D92: =IFERROR(B92*C92,0) -> 16987.5
A93: Egg Yolk | B93: 243 | C93: =IFERROR(VLOOKUP(A93,'Market List'!$B:$F,5,FALSE),0) -> 130 | D93: =IFERROR(B93*C93,0) -> 31590
A94: Gula Pasir | B94: 66 | C94: =IFERROR(VLOOKUP(A94,'Market List'!$B:$F,5,FALSE),0) -> 18 | D94: =IFERROR(B94*C94,0) -> 1188
A95: Dark Chocolate 54% | B95: 350 | C95: =IFERROR(VLOOKUP(A95,'Market List'!$B:$F,5,FALSE),0) -> 136 | D95: =IFERROR(B95*C95,0) -> 47600
A96: Dark Chocolate 70% | B96: 100 | C96: =IFERROR(VLOOKUP(A96,'Market List'!$B:$F,5,FALSE),0) -> 321.5995 | D96: =IFERROR(B96*C96,0) -> 32159.95
A97: Element Cost | D97: =SUM(D90:D96) -> 132619.77 | E97: Source: resep chocolate base(1).pdf
A99: Chocolate Filling WIP | B99: =IFERROR(D107/D99,0) -> 108.45792 | C99: Portion | D99: =SUM(B101:B106) -> 200 | E99: GR
A100: Ingredients | B100: Use (g/ml/ea) | C100: Unit Price / Unit | D100: Price | E100: Major Step
A101: Chocolate Base WIP | B101: 100 | C101: ='WIP FOOD'!$B$88 -> 141.41583 | D101: =IFERROR(B101*C101,0) -> 14141.583
A102: Whipping Cream | B102: 100 | C102: =IFERROR(VLOOKUP(A102,'Market List'!$B:$F,5,FALSE),0) -> 75.5 | D102: =IFERROR(B102*C102,0) -> 7550
D103: =IFERROR(B103*C103,0) -> 0
D104: =IFERROR(B104*C104,0) -> 0
D105: =IFERROR(B105*C105,0) -> 0
D106: =IFERROR(B106*C106,0) -> 0
A107: Element Cost | D107: =SUM(D101:D106) -> 21691.583 | E107: Source: chocolate filling.pdf
A109: Chocolate Sauce WIP | B109: =IFERROR(D117/D109,0) -> 76.641669 | C109: Portion | D109: =SUM(B111:B116)*90% -> 296.1 | E109: GR
...

Sheet Yokoco Beverage Stall
A1: Yokoco Beverage Stall
A2: Sour Plum
A3: Element | B3: UOM | C3: Element Cost/(g) | D3: Portion Used | E3: Value /pcs | F3: Major Step | G3: Units
A4: Plum syrup | B4: GR | C4: =IFERROR(VLOOKUP(A4,'Market List'!$B:$F,5,FALSE),0) -> 0 | D4: 20 | E4: =C4*D4 -> 0
A5: Grenadine syrup | B5: GR | C5: =IFERROR(VLOOKUP(A5,'Market List'!$B:$F,5,FALSE),0) -> 0 | D5: 10 | E5: =C5*D5 -> 0
A6: Simple syrup | B6: GR | C6: =IFERROR(VLOOKUP(A6,'Market List'!$B:$F,5,FALSE),0) -> 0 | D6: 5 | E6: =C6*D6 -> 0
A7: Soda | B7: GR | C7: =IFERROR(VLOOKUP(A7,'Market List'!$B:$F,5,FALSE),0) -> 0 | D7: 180 | E7: =C7*D7 -> 0
A12: Boxes, packaging, etc.
A13: Direct Cost | E13: =sum(E4:E12) -> 0 | F13: Source: User recipe - Yokoco Beverage
A14: Indirect Cost | E14: =E13*15% -> 0 | F14: Status: Recipe Available
A15: Cost of Goods Sold (COGS) | E15: =E13+E14 -> 0
A16: Margin | E16: =E18-E15 -> 0
A17: Div COGS | E17: =E15/E18 -> #DIV/0!
A18: Selling Price
A20: Yuzu Milk
A21: Element | B21: UOM | C21: Element Cost/(g) | D21: Portion Used | E21: Value /pcs | F21: Major Step | G21: Units
A22: Orange juice | B22: GR | C22: =IFERROR(VLOOKUP(A22,'Market List'!$B:$F,5,FALSE),0) -> 0 | D22: 30 | E22: =C22*D22 -> 0
A23: Fresh milk | B23: GR | C23: =IFERROR(VLOOKUP(A23,'Market List'!$B:$F,5,FALSE),0) -> 38.421053 | D23: 50 | E23: =C23*D23 -> 1921.0526
A24: Milac Cream | B24: GR | C24: =IFERROR(VLOOKUP(A24,'Market List'!$B:$F,5,FALSE),0) -> 0 | D24: 25 | E24: =C24*D24 -> 0
A25: Yuzu syrup | B25: GR | C25: =IFERROR(VLOOKUP(A25,'Market List'!$B:$F,5,FALSE),0) -> 733.33333 | D25: 7.5 | E25: =C25*D25 -> 5500
A26: Simple syrup | B26: GR | C26: =IFERROR(VLOOKUP(A26,'Market List'!$B:$F,5,FALSE),0) -> 0 | D26: 7.5 | E26: =C26*D26 -> 0
A30: Boxes, packaging, etc. | E30: =C30*D30 -> 0
A31: Direct Cost | E31: =sum(E22:E30) -> 7421.0526 | F31: Source: User recipe - Yokoco Beverage
A32: Indirect Cost | E32: =E31*15% -> 1113.1579 | F32: Status: Recipe Available
A33: Cost of Goods Sold (COGS) | E33: =E31+E32 -> 8534.2105
A34: Margin | E34: =E36-E33 -> 16465.789
A35: Div Margin | E35: =E33/E36 -> 0.34136842
A36: Selling Price | E36: 25000
A38: Oolong Peach
A39: Element | B39: UOM | C39: Element Cost/(g) | D39: Portion Used | E39: Value /pcs | F39: Major Step | G39: Units
A40: Orange Syrup WIP | B40: GR | C40: =IFERROR(VLOOKUP(A40,'Market List'!$B:$F,5,FALSE),0) -> 0 | D40: 20 | E40: =C40*D40 -> 0
A41: Peach syrup | B41: GR | C41: =IFERROR(VLOOKUP(A41,'Market List'!$B:$F,5,FALSE),0) -> 0 | D41: 10 | E41: =C41*D41 -> 0
A42: Oolong Tea WIP | B42: GR | C42: =IFERROR(VLOOKUP(A42,'Market List'!$B:$F,5,FALSE),0) -> 0 | D42: 60 | E42: =C42*D42 -> 0
A43: Lemon Juice | B43: GR | C43: =IFERROR(VLOOKUP(A43,'Market List'!$B:$F,5,FALSE),0) -> 42.79 | D43: 5 | E43: =C43*D43 -> 213.95
A44: Soda | B44: GR | C44: =IFERROR(VLOOKUP(A44,'Market List'!$B:$F,5,FALSE),0) -> 0 | D44: 40 | E44: =C44*D44 -> 0
A48: Boxes, packaging, etc. | E48: =C48*D48 -> 0
A49: Direct Cost | E49: =sum(E40:E48) -> 213.95 | F49: Source: User recipe - Yokoco Beverage
A50: Indirect Cost | E50: =E49*15% -> 32.0925 | F50: Status: Recipe Available
A51: Cost of Goods Sold (COGS) | E51: =sum(E49+E50) -> 246.0425
A52: Margin | E52: =E54-E51 -> 24753.958
A53: Div Margin | E53: 0,00%
A54: Selling Price | E54: 25000

Sheet Sando Stall
A1: Sando Stall
A2: Beef Katsu Sando
A3: Element | B3: UOM | C3: Element Cost/(g) | D3: Portion Used | E3: Value /pcs | F3: Major Step | G3: Units
A4: Brioche Sandwich Toast WIP | B4: GR | C4: ='WIP FOOD'!$B$723 -> 2999.0806 | E4: =IFERROR(C4*D4,0) -> 0 | F4: Recipe detail belum ditemukan pada ITEM SALES RECIPE / PDF yang tersedia.
A5: BEEF STEAK | C5: =IFERROR(VLOOKUP(A5,'Market List'!$B:$F,5,FALSE),0) -> 0 | E5: =IFERROR(C5*D5,0) -> 0
A6: Furikake WIP | C6: ='WIP FOOD'!$B$218 -> 362.72092 | E6: =IFERROR(C6*D6,0) -> 0
A7: Okonomiyaki Sauce WIP | C7: ='WIP FOOD'!$B$452 -> 74.822755 | E7: =IFERROR(C7*D7,0) -> 0
A8: KOREANDER | C8: =IFERROR(VLOOKUP(A8,'Market List'!$B:$F,5,FALSE),0) -> 0 | E8: =IFERROR(C8*D8,0) -> 0
E9: 0
E10: 0
E11: 0
A12: Boxes, packaging, etc. | E12: 0
A13: Direct Cost | E13: =SUM(E4:E12) -> 0 | F13: Source: -
A14: Indirect Cost | E14: =E13*15% -> 0 | F14: Status: Recipe Pending
A15: Cost of Goods Sold (COGS) | E15: =E13+E14 -> 0
A16: Margin | E16: =IF(E18>0,E18-E15,0) -> 0
A17: Div Margin | E17: =IFERROR(E15/E18,0) -> 0
A18: Selling Price
